{
  "generated_at": "2026-04-04T11:01:45.246121Z",
  "deployed_at": "2026-04-04T08:13:54.538868Z",
  "mode": "live",
  "account": 591502727,
  "initial_equity": 10000.0,
  "period": {
    "start": "2026-04-04",
    "end": "2026-04-04"
  },
  "stats": {
    "total_trades": 0,
    "winning_trades": 0,
    "losing_trades": 0,
    "win_rate_pct": 0.0,
    "total_pnl_usd": 0,
    "total_r": 0.0,
    "r_per_day": 0.0,
    "avg_win_usd": 0.0,
    "avg_loss_usd": 0.0,
    "profit_factor": 999.0,
    "max_drawdown_pct": 0.0,
    "initial_equity": 10000.0,
    "final_equity": 10000.0,
    "return_pct": 0.0,
    "avg_duration_bars": 0,
    "daily_pnl": {},
    "weekly_pnl": {},
    "weekly_r": {},
    "by_symbol": {},
    "by_strategy": {}
  },
  "equity_curve": [
    {
      "time": "2026-04-04T08:13:54",
      "equity": 10000.0
    }
  ],
  "trades": []
}