{
  "generated_at": "2026-04-04T09:29:17.373509Z",
  "mode": "dummy",
  "initial_equity": 10000.0,
  "period": {
    "start": "2025-11-01",
    "end": "2026-03-28"
  },
  "stats": {
    "total_trades": 120,
    "winning_trades": 69,
    "losing_trades": 51,
    "win_rate_pct": 57.5,
    "total_pnl_usd": 9552.6,
    "total_r": 95.528,
    "r_per_day": 1.194,
    "avg_win_usd": 201.8,
    "avg_loss_usd": -85.72,
    "profit_factor": 3.185,
    "max_drawdown_pct": 3.48,
    "initial_equity": 10000.0,
    "final_equity": 19552.6,
    "return_pct": 95.53,
    "avg_duration_bars": 307.8,
    "daily_pnl": {
      "2025-11-01": 187.66,
      "2025-11-03": -91.46,
      "2025-11-06": 279.14,
      "2025-11-08": 125.16,
      "2025-11-10": 54.25,
      "2025-11-12": -80.1,
      "2025-11-13": 181.45999999999998,
      "2025-11-14": 203.51,
      "2025-11-15": 407.27,
      "2025-11-18": 573.98,
      "2025-11-20": -111.94,
      "2025-11-21": 174.8,
      "2025-11-23": -84.48,
      "2025-11-25": -96.16,
      "2025-11-28": 300.78,
      "2025-11-29": 258.68,
      "2025-12-01": 294.84,
      "2025-12-03": 186.59,
      "2025-12-04": 136.99,
      "2025-12-06": 160.75,
      "2025-12-09": 262.47,
      "2025-12-10": 349.72,
      "2025-12-12": 223.77,
      "2025-12-13": 134.57,
      "2025-12-15": -410.0,
      "2025-12-18": 41.17,
      "2025-12-19": 104.37,
      "2025-12-22": -117.47,
      "2025-12-25": 283.35,
      "2025-12-24": 442.97,
      "2025-12-28": 337.94,
      "2025-12-27": 245.26000000000002,
      "2025-12-29": -58.6,
      "2026-01-01": 144.18,
      "2026-01-02": -105.96,
      "2026-01-03": -117.64,
      "2026-01-04": -160.24,
      "2026-01-05": -76.76,
      "2026-01-06": 232.46,
      "2026-01-09": 589.28,
      "2026-01-08": -117.07,
      "2026-01-13": 125.37,
      "2026-01-14": -288.68,
      "2026-01-15": 100.76,
      "2026-01-16": 290.5,
      "2026-01-19": -98.98,
      "2026-01-20": -119.03,
      "2026-01-21": -24.959999999999994,
      "2026-01-23": -50.94,
      "2026-01-25": 524.39,
      "2026-01-26": -103.73,
      "2026-01-28": 202.03,
      "2026-01-31": -97.69,
      "2026-02-01": -85.99,
      "2026-02-02": -99.07,
      "2026-02-03": 329.23,
      "2026-02-05": 524.49,
      "2026-02-07": 125.71,
      "2026-02-08": 164.53,
      "2026-02-11": 122.51,
      "2026-02-10": 177.02,
      "2026-02-12": 127.16,
      "2026-02-14": -54.71000000000001,
      "2026-02-15": 218.31,
      "2026-02-17": 180.63,
      "2026-02-19": -55.12,
      "2026-02-18": 131.83,
      "2026-02-20": 103.36999999999999,
      "2026-02-21": 49.08999999999999,
      "2026-02-23": 207.25,
      "2026-02-26": 178.06,
      "2026-02-27": 133.1,
      "2026-03-01": 281.46,
      "2026-02-28": -106.1,
      "2026-03-02": 401.24,
      "2026-03-05": 151.95000000000002,
      "2026-03-07": 160.97,
      "2026-03-09": 213.94,
      "2026-03-10": -70.53,
      "2026-03-11": 293.74
    },
    "weekly_pnl": {
      "2025-W44": 187.66,
      "2025-W45": 312.84,
      "2025-W46": 766.39,
      "2025-W47": 552.36,
      "2025-W48": 463.3,
      "2025-W49": 779.17,
      "2025-W50": 970.53,
      "2025-W51": -264.46,
      "2025-W52": 1192.05,
      "2025-W01": -58.6,
      "2026-W01": -239.66,
      "2026-W02": 627.91,
      "2026-W03": 227.95,
      "2026-W04": 230.48,
      "2026-W05": -85.38,
      "2026-W06": 1044.89,
      "2026-W07": 590.29,
      "2026-W08": 409.8,
      "2026-W09": 693.77,
      "2026-W10": 714.16,
      "2026-W11": 437.15
    },
    "weekly_r": {
      "2025-W44": 1.877,
      "2025-W45": 3.128,
      "2025-W46": 7.665,
      "2025-W47": 5.524,
      "2025-W48": 4.633,
      "2025-W49": 7.791,
      "2025-W50": 9.706,
      "2025-W51": -2.644,
      "2025-W52": 11.919,
      "2025-W01": -0.586,
      "2026-W01": -2.397,
      "2026-W02": 6.279,
      "2026-W03": 2.281,
      "2026-W04": 2.305,
      "2026-W05": -0.854,
      "2026-W06": 10.449,
      "2026-W07": 5.903,
      "2026-W08": 4.098,
      "2026-W09": 6.938,
      "2026-W10": 7.142,
      "2026-W11": 4.371
    },
    "by_symbol": {
      "EURUSD": {
        "trades": 16,
        "win_rate": 50.0,
        "total_pnl": 692.02,
        "total_r": 6.918
      },
      "GBPUSD": {
        "trades": 12,
        "win_rate": 58.3,
        "total_pnl": 781.08,
        "total_r": 7.812
      },
      "USDJPY": {
        "trades": 4,
        "win_rate": 0.0,
        "total_pnl": -335.01,
        "total_r": -3.351
      },
      "AUDUSD": {
        "trades": 12,
        "win_rate": 66.7,
        "total_pnl": 1062.77,
        "total_r": 10.629
      },
      "USDCAD": {
        "trades": 11,
        "win_rate": 63.6,
        "total_pnl": 1483.39,
        "total_r": 14.834
      },
      "USDCHF": {
        "trades": 11,
        "win_rate": 90.9,
        "total_pnl": 2269.2,
        "total_r": 22.692
      },
      "EURGBP": {
        "trades": 13,
        "win_rate": 61.5,
        "total_pnl": 1160.11,
        "total_r": 11.602
      },
      "EURJPY": {
        "trades": 15,
        "win_rate": 53.3,
        "total_pnl": 1027.96,
        "total_r": 10.281
      },
      "GBPJPY": {
        "trades": 17,
        "win_rate": 52.9,
        "total_pnl": 1041.32,
        "total_r": 10.414
      },
      "XAUUSD": {
        "trades": 9,
        "win_rate": 44.4,
        "total_pnl": 369.76,
        "total_r": 3.697
      }
    }
  },
  "equity_curve": [
    {
      "time": "2025-11-01T08:31:12",
      "equity": 10000.0
    },
    {
      "time": "2025-11-01T23:34:18",
      "equity": 10187.66
    },
    {
      "time": "2025-11-03T14:20:43",
      "equity": 10096.2
    },
    {
      "time": "2025-11-06T14:00:33",
      "equity": 10375.34
    },
    {
      "time": "2025-11-08T10:10:04",
      "equity": 10500.5
    },
    {
      "time": "2025-11-10T13:38:51",
      "equity": 10673.37
    },
    {
      "time": "2025-11-10T10:37:09",
      "equity": 10554.75
    },
    {
      "time": "2025-11-12T23:20:43",
      "equity": 10474.65
    },
    {
      "time": "2025-11-13T10:17:54",
      "equity": 10707.16
    },
    {
      "time": "2025-11-13T11:22:07",
      "equity": 10656.11
    },
    {
      "time": "2025-11-14T15:44:24",
      "equity": 10859.62
    },
    {
      "time": "2025-11-15T00:34:39",
      "equity": 11008.37
    },
    {
      "time": "2025-11-15T01:01:09",
      "equity": 11266.89
    },
    {
      "time": "2025-11-18T01:12:47",
      "equity": 11549.84
    },
    {
      "time": "2025-11-18T06:49:25",
      "equity": 11840.87
    },
    {
      "time": "2025-11-20T01:33:36",
      "equity": 11788.17
    },
    {
      "time": "2025-11-20T14:19:05",
      "equity": 11728.93
    },
    {
      "time": "2025-11-21T08:09:25",
      "equity": 11964.89
    },
    {
      "time": "2025-11-21T07:39:25",
      "equity": 11903.73
    },
    {
      "time": "2025-11-23T14:54:26",
      "equity": 11819.25
    },
    {
      "time": "2025-11-25T07:40:41",
      "equity": 11723.09
    },
    {
      "time": "2025-11-28T00:59:31",
      "equity": 11867.19
    },
    {
      "time": "2025-11-28T13:35:55",
      "equity": 12023.87
    },
    {
      "time": "2025-11-29T08:25:22",
      "equity": 12282.55
    },
    {
      "time": "2025-12-01T01:17:20",
      "equity": 12577.39
    },
    {
      "time": "2025-12-03T17:51:31",
      "equity": 12763.98
    },
    {
      "time": "2025-12-04T03:34:07",
      "equity": 12978.02
    },
    {
      "time": "2025-12-04T07:08:20",
      "equity": 12900.97
    },
    {
      "time": "2025-12-06T08:44:28",
      "equity": 13061.72
    },
    {
      "time": "2025-12-09T04:15:55",
      "equity": 13324.19
    },
    {
      "time": "2025-12-10T09:40:38",
      "equity": 13485.97
    },
    {
      "time": "2025-12-10T00:44:04",
      "equity": 13673.91
    },
    {
      "time": "2025-12-12T03:29:56",
      "equity": 13897.68
    },
    {
      "time": "2025-12-13T09:59:03",
      "equity": 13843.88
    },
    {
      "time": "2025-12-13T21:37:38",
      "equity": 14032.25
    },
    {
      "time": "2025-12-15T17:00:28",
      "equity": 13942.63
    },
    {
      "time": "2025-12-15T09:36:56",
      "equity": 13823.45
    },
    {
      "time": "2025-12-15T07:36:24",
      "equity": 13715.6
    },
    {
      "time": "2025-12-15T17:13:28",
      "equity": 13622.25
    },
    {
      "time": "2025-12-18T11:51:36",
      "equity": 13556.83
    },
    {
      "time": "2025-12-18T13:19:30",
      "equity": 13663.42
    },
    {
      "time": "2025-12-19T13:58:45",
      "equity": 13767.79
    },
    {
      "time": "2025-12-22T01:27:53",
      "equity": 13650.32
    },
    {
      "time": "2025-12-25T17:02:37",
      "equity": 13933.67
    },
    {
      "time": "2025-12-24T08:07:04",
      "equity": 14141.62
    },
    {
      "time": "2025-12-24T16:48:06",
      "equity": 14376.64
    },
    {
      "time": "2025-12-28T05:46:29",
      "equity": 14478.58
    },
    {
      "time": "2025-12-27T03:15:14",
      "equity": 14423.85
    },
    {
      "time": "2025-12-27T11:03:27",
      "equity": 14723.84
    },
    {
      "time": "2025-12-29T07:53:50",
      "equity": 14665.24
    },
    {
      "time": "2025-12-28T22:53:44",
      "equity": 14901.24
    },
    {
      "time": "2026-01-01T11:49:24",
      "equity": 15045.42
    },
    {
      "time": "2026-01-02T01:18:47",
      "equity": 14939.46
    },
    {
      "time": "2026-01-03T03:21:39",
      "equity": 14821.82
    },
    {
      "time": "2026-01-04T11:14:56",
      "equity": 14769.45
    },
    {
      "time": "2026-01-05T05:14:29",
      "equity": 14692.69
    },
    {
      "time": "2026-01-04T12:59:11",
      "equity": 14584.82
    },
    {
      "time": "2026-01-06T20:20:15",
      "equity": 14521.73
    },
    {
      "time": "2026-01-06T21:54:00",
      "equity": 14817.28
    },
    {
      "time": "2026-01-09T02:36:35",
      "equity": 15005.76
    },
    {
      "time": "2026-01-08T22:15:54",
      "equity": 14888.69
    },
    {
      "time": "2026-01-09T18:58:04",
      "equity": 15128.42
    },
    {
      "time": "2026-01-09T13:26:36",
      "equity": 15289.49
    },
    {
      "time": "2026-01-13T00:48:37",
      "equity": 15217.9
    },
    {
      "time": "2026-01-13T10:31:44",
      "equity": 15414.86
    },
    {
      "time": "2026-01-14T18:28:31",
      "equity": 15308.83
    },
    {
      "time": "2026-01-14T13:07:42",
      "equity": 15190.03
    },
    {
      "time": "2026-01-15T05:49:40",
      "equity": 15290.79
    },
    {
      "time": "2026-01-14T21:54:15",
      "equity": 15226.94
    },
    {
      "time": "2026-01-16T02:27:35",
      "equity": 15171.94
    },
    {
      "time": "2026-01-16T08:48:33",
      "equity": 15443.55
    },
    {
      "time": "2026-01-16T17:40:51",
      "equity": 15325.44
    },
    {
      "time": "2026-01-16T21:10:47",
      "equity": 15517.44
    },
    {
      "time": "2026-01-19T17:30:45",
      "equity": 15418.46
    },
    {
      "time": "2026-01-20T16:44:56",
      "equity": 15299.43
    },
    {
      "time": "2026-01-21T22:54:34",
      "equity": 15180.13
    },
    {
      "time": "2026-01-21T22:51:27",
      "equity": 15385.54
    },
    {
      "time": "2026-01-21T12:10:03",
      "equity": 15274.47
    },
    {
      "time": "2026-01-23T09:59:25",
      "equity": 15223.53
    },
    {
      "time": "2026-01-25T18:54:44",
      "equity": 15520.32
    },
    {
      "time": "2026-01-26T13:53:44",
      "equity": 15416.59
    },
    {
      "time": "2026-01-25T08:07:34",
      "equity": 15644.19
    },
    {
      "time": "2026-01-28T01:11:18",
      "equity": 15908.88
    },
    {
      "time": "2026-01-28T08:41:34",
      "equity": 15846.22
    },
    {
      "time": "2026-01-31T00:21:58",
      "equity": 15748.53
    },
    {
      "time": "2026-02-01T01:17:14",
      "equity": 15662.54
    },
    {
      "time": "2026-02-02T23:36:47",
      "equity": 15563.47
    },
    {
      "time": "2026-02-03T06:03:17",
      "equity": 15786.72
    },
    {
      "time": "2026-02-03T08:09:51",
      "equity": 15892.7
    },
    {
      "time": "2026-02-05T05:38:43",
      "equity": 16177.05
    },
    {
      "time": "2026-02-05T04:22:01",
      "equity": 16417.19
    },
    {
      "time": "2026-02-07T19:34:12",
      "equity": 16542.9
    },
    {
      "time": "2026-02-08T13:13:18",
      "equity": 16707.43
    },
    {
      "time": "2026-02-11T16:38:51",
      "equity": 16829.94
    },
    {
      "time": "2026-02-10T00:08:46",
      "equity": 17006.96
    },
    {
      "time": "2026-02-12T03:53:22",
      "equity": 17134.12
    },
    {
      "time": "2026-02-14T16:57:44",
      "equity": 17280.1
    },
    {
      "time": "2026-02-14T20:38:05",
      "equity": 17181.85
    },
    {
      "time": "2026-02-14T15:26:35",
      "equity": 17079.41
    },
    {
      "time": "2026-02-15T14:18:29",
      "equity": 17297.72
    },
    {
      "time": "2026-02-17T09:37:11",
      "equity": 17478.35
    },
    {
      "time": "2026-02-19T04:57:46",
      "equity": 17423.23
    },
    {
      "time": "2026-02-18T07:14:25",
      "equity": 17555.06
    },
    {
      "time": "2026-02-20T00:01:52",
      "equity": 17502.48
    },
    {
      "time": "2026-02-20T11:42:26",
      "equity": 17658.43
    },
    {
      "time": "2026-02-21T06:37:05",
      "equity": 17570.32
    },
    {
      "time": "2026-02-21T18:17:24",
      "equity": 17707.52
    },
    {
      "time": "2026-02-23T22:58:50",
      "equity": 17914.77
    },
    {
      "time": "2026-02-26T11:07:52",
      "equity": 18092.83
    },
    {
      "time": "2026-02-27T19:21:14",
      "equity": 18225.93
    },
    {
      "time": "2026-03-01T16:36:09",
      "equity": 18507.39
    },
    {
      "time": "2026-02-28T23:27:13",
      "equity": 18401.29
    },
    {
      "time": "2026-03-02T11:10:49",
      "equity": 18319.49
    },
    {
      "time": "2026-03-02T19:21:26",
      "equity": 18607.57
    },
    {
      "time": "2026-03-02T20:17:57",
      "equity": 18802.53
    },
    {
      "time": "2026-03-05T18:50:42",
      "equity": 19016.77
    },
    {
      "time": "2026-03-05T20:26:55",
      "equity": 18954.48
    },
    {
      "time": "2026-03-07T11:18:29",
      "equity": 19115.45
    },
    {
      "time": "2026-03-09T20:29:32",
      "equity": 19329.39
    },
    {
      "time": "2026-03-10T17:08:46",
      "equity": 19258.86
    },
    {
      "time": "2026-03-11T10:27:34",
      "equity": 19552.6
    }
  ],
  "trades": [
    {
      "id": 24,
      "symbol": "USDCHF",
      "strategy": "momentum_pullback",
      "direction": "sell",
      "entry_time": "2025-11-01T08:31:12",
      "exit_time": "2025-11-01T23:34:18",
      "entry_price": 0.90469,
      "exit_price": 0.89304,
      "sl_price": 0.90791,
      "tp_price": 0.89304,
      "lots": 0.31,
      "pnl_usd": 187.66,
      "pnl_r": 1.877,
      "exit_reason": "tp",
      "duration_bars": 180
    },
    {
      "id": 67,
      "symbol": "AUDUSD",
      "strategy": "momentum_pullback",
      "direction": "buy",
      "entry_time": "2025-11-02T03:11:49",
      "exit_time": "2025-11-03T14:20:43",
      "entry_price": 0.64567,
      "exit_price": 0.64429,
      "sl_price": 0.6441,
      "tp_price": 0.65185,
      "lots": 0.64,
      "pnl_usd": -91.46,
      "pnl_r": -0.915,
      "exit_reason": "trailing",
      "duration_bars": 421
    },
    {
      "id": 107,
      "symbol": "USDCAD",
      "strategy": "macd_stochastic",
      "direction": "sell",
      "entry_time": "2025-11-04T18:57:19",
      "exit_time": "2025-11-06T14:00:33",
      "entry_price": 1.36022,
      "exit_price": 1.3514,
      "sl_price": 1.36408,
      "tp_price": 1.3514,
      "lots": 0.26,
      "pnl_usd": 279.14,
      "pnl_r": 2.791,
      "exit_reason": "tp",
      "duration_bars": 516
    },
    {
      "id": 36,
      "symbol": "EURJPY",
      "strategy": "momentum_pullback",
      "direction": "buy",
      "entry_time": "2025-11-07T19:46:01",
      "exit_time": "2025-11-08T10:10:04",
      "entry_price": 161.23071,
      "exit_price": 162.18599,
      "sl_price": 160.93687,
      "tp_price": 162.18599,
      "lots": 0.38,
      "pnl_usd": 125.16,
      "pnl_r": 1.252,
      "exit_reason": "tp",
      "duration_bars": 172
    },
    {
      "id": 1,
      "symbol": "GBPJPY",
      "strategy": "komjathy",
      "direction": "buy",
      "entry_time": "2025-11-09T08:44:31",
      "exit_time": "2025-11-10T13:38:51",
      "entry_price": 188.79032,
      "exit_price": 189.41275,
      "sl_price": 188.41501,
      "tp_price": 189.41275,
      "lots": 0.3,
      "pnl_usd": 172.87,
      "pnl_r": 1.729,
      "exit_reason": "tp",
      "duration_bars": 346
    },
    {
      "id": 15,
      "symbol": "GBPUSD",
      "strategy": "momentum_pullback",
      "direction": "sell",
      "entry_time": "2025-11-09T11:14:57",
      "exit_time": "2025-11-10T10:37:09",
      "entry_price": 1.26426,
      "exit_price": 1.2676,
      "sl_price": 1.2677,
      "tp_price": 1.25682,
      "lots": 0.29,
      "pnl_usd": -118.62,
      "pnl_r": -1.186,
      "exit_reason": "trailing",
      "duration_bars": 280
    },
    {
      "id": 21,
      "symbol": "GBPJPY",
      "strategy": "komjathy",
      "direction": "buy",
      "entry_time": "2025-11-11T19:26:11",
      "exit_time": "2025-11-12T23:20:43",
      "entry_price": 188.61938,
      "exit_price": 188.34461,
      "sl_price": 188.34946,
      "tp_price": 189.68859,
      "lots": 0.41,
      "pnl_usd": -80.1,
      "pnl_r": -0.801,
      "exit_reason": "sl",
      "duration_bars": 334
    },
    {
      "id": 47,
      "symbol": "GBPJPY",
      "strategy": "momentum_pullback",
      "direction": "sell",
      "entry_time": "2025-11-12T10:54:40",
      "exit_time": "2025-11-13T10:17:54",
      "entry_price": 188.78553,
      "exit_price": 187.92333,
      "sl_price": 189.03118,
      "tp_price": 187.92333,
      "lots": 0.45,
      "pnl_usd": 232.51,
      "pnl_r": 2.325,
      "exit_reason": "tp",
      "duration_bars": 280
    },
    {
      "id": 79,
      "symbol": "GBPUSD",
      "strategy": "macd_stochastic",
      "direction": "buy",
      "entry_time": "2025-11-12T20:02:24",
      "exit_time": "2025-11-13T11:22:07",
      "entry_price": 1.26428,
      "exit_price": 1.26159,
      "sl_price": 1.26176,
      "tp_price": 1.27243,
      "lots": 0.4,
      "pnl_usd": -51.05,
      "pnl_r": -0.51,
      "exit_reason": "trailing",
      "duration_bars": 183
    },
    {
      "id": 56,
      "symbol": "USDCAD",
      "strategy": "komjathy",
      "direction": "sell",
      "entry_time": "2025-11-12T20:05:05",
      "exit_time": "2025-11-14T15:44:24",
      "entry_price": 1.36086,
      "exit_price": 1.35372,
      "sl_price": 1.36452,
      "tp_price": 1.35372,
      "lots": 0.27,
      "pnl_usd": 203.51,
      "pnl_r": 2.035,
      "exit_reason": "tp",
      "duration_bars": 523
    },
    {
      "id": 84,
      "symbol": "XAUUSD",
      "strategy": "komjathy",
      "direction": "buy",
      "entry_time": "2025-11-13T03:58:23",
      "exit_time": "2025-11-15T00:34:39",
      "entry_price": 2320.34859,
      "exit_price": 2403.53125,
      "sl_price": 2293.2852,
      "tp_price": 2403.53125,
      "lots": 0.37,
      "pnl_usd": 148.75,
      "pnl_r": 1.488,
      "exit_reason": "tp",
      "duration_bars": 535
    },
    {
      "id": 63,
      "symbol": "AUDUSD",
      "strategy": "momentum_pullback",
      "direction": "buy",
      "entry_time": "2025-11-14T11:31:40",
      "exit_time": "2025-11-15T01:01:09",
      "entry_price": 0.64598,
      "exit_price": 0.65269,
      "sl_price": 0.64425,
      "tp_price": 0.65269,
      "lots": 0.58,
      "pnl_usd": 258.52,
      "pnl_r": 2.585,
      "exit_reason": "tp",
      "duration_bars": 161
    },
    {
      "id": 11,
      "symbol": "AUDUSD",
      "strategy": "momentum_pullback",
      "direction": "sell",
      "entry_time": "2025-11-16T04:40:14",
      "exit_time": "2025-11-18T01:12:47",
      "entry_price": 0.64441,
      "exit_price": 0.63446,
      "sl_price": 0.64811,
      "tp_price": 0.63446,
      "lots": 0.27,
      "pnl_usd": 282.95,
      "pnl_r": 2.83,
      "exit_reason": "tp",
      "duration_bars": 534
    },
    {
      "id": 43,
      "symbol": "USDCHF",
      "strategy": "macd_stochastic",
      "direction": "buy",
      "entry_time": "2025-11-16T16:05:21",
      "exit_time": "2025-11-18T06:49:25",
      "entry_price": 0.90424,
      "exit_price": 0.90889,
      "sl_price": 0.90267,
      "tp_price": 0.90889,
      "lots": 0.64,
      "pnl_usd": 291.03,
      "pnl_r": 2.91,
      "exit_reason": "tp",
      "duration_bars": 464
    },
    {
      "id": 114,
      "symbol": "AUDUSD",
      "strategy": "momentum_pullback",
      "direction": "buy",
      "entry_time": "2025-11-18T03:38:27",
      "exit_time": "2025-11-20T01:33:36",
      "entry_price": 0.64436,
      "exit_price": 0.64024,
      "sl_price": 0.64039,
      "tp_price": 0.6554,
      "lots": 0.25,
      "pnl_usd": -52.7,
      "pnl_r": -0.527,
      "exit_reason": "sl",
      "duration_bars": 551
    },
    {
      "id": 117,
      "symbol": "USDCAD",
      "strategy": "macd_stochastic",
      "direction": "buy",
      "entry_time": "2025-11-19T17:16:33",
      "exit_time": "2025-11-20T14:19:05",
      "entry_price": 1.3592,
      "exit_price": 1.3555,
      "sl_price": 1.35543,
      "tp_price": 1.3706,
      "lots": 0.27,
      "pnl_usd": -59.24,
      "pnl_r": -0.592,
      "exit_reason": "trailing",
      "duration_bars": 252
    },
    {
      "id": 119,
      "symbol": "EURJPY",
      "strategy": "momentum_pullback",
      "direction": "buy",
      "entry_time": "2025-11-19T19:02:52",
      "exit_time": "2025-11-21T08:09:25",
      "entry_price": 161.12077,
      "exit_price": 162.10875,
      "sl_price": 160.83499,
      "tp_price": 162.10875,
      "lots": 0.39,
      "pnl_usd": 235.96,
      "pnl_r": 2.36,
      "exit_reason": "tp",
      "duration_bars": 445
    },
    {
      "id": 61,
      "symbol": "GBPJPY",
      "strategy": "macd_stochastic",
      "direction": "sell",
      "entry_time": "2025-11-20T10:26:20",
      "exit_time": "2025-11-21T07:39:25",
      "entry_price": 188.71834,
      "exit_price": 188.86905,
      "sl_price": 188.88818,
      "tp_price": 188.06833,
      "lots": 0.65,
      "pnl_usd": -61.16,
      "pnl_r": -0.612,
      "exit_reason": "trailing",
      "duration_bars": 254
    },
    {
      "id": 5,
      "symbol": "EURUSD",
      "strategy": "momentum_pullback",
      "direction": "sell",
      "entry_time": "2025-11-23T01:14:11",
      "exit_time": "2025-11-23T14:54:26",
      "entry_price": 1.08473,
      "exit_price": 1.08784,
      "sl_price": 1.0879,
      "tp_price": 1.07738,
      "lots": 0.32,
      "pnl_usd": -84.48,
      "pnl_r": -0.845,
      "exit_reason": "trailing",
      "duration_bars": 164
    },
    {
      "id": 17,
      "symbol": "EURJPY",
      "strategy": "macd_stochastic",
      "direction": "sell",
      "entry_time": "2025-11-23T09:57:36",
      "exit_time": "2025-11-25T07:40:41",
      "entry_price": 161.14836,
      "exit_price": 161.35698,
      "sl_price": 161.3701,
      "tp_price": 160.77324,
      "lots": 0.5,
      "pnl_usd": -96.16,
      "pnl_r": -0.962,
      "exit_reason": "sl",
      "duration_bars": 548
    },
    {
      "id": 48,
      "symbol": "EURUSD",
      "strategy": "momentum_pullback",
      "direction": "buy",
      "entry_time": "2025-11-26T01:21:46",
      "exit_time": "2025-11-28T00:59:31",
      "entry_price": 1.08564,
      "exit_price": 1.09056,
      "sl_price": 1.08245,
      "tp_price": 1.09056,
      "lots": 0.31,
      "pnl_usd": 144.1,
      "pnl_r": 1.441,
      "exit_reason": "tp",
      "duration_bars": 571
    },
    {
      "id": 109,
      "symbol": "AUDUSD",
      "strategy": "macd_stochastic",
      "direction": "buy",
      "entry_time": "2025-11-26T20:35:40",
      "exit_time": "2025-11-28T13:35:55",
      "entry_price": 0.64571,
      "exit_price": 0.65211,
      "sl_price": 0.64243,
      "tp_price": 0.65211,
      "lots": 0.3,
      "pnl_usd": 156.68,
      "pnl_r": 1.567,
      "exit_reason": "tp",
      "duration_bars": 492
    },
    {
      "id": 46,
      "symbol": "USDCAD",
      "strategy": "komjathy",
      "direction": "sell",
      "entry_time": "2025-11-28T11:31:14",
      "exit_time": "2025-11-29T08:25:22",
      "entry_price": 1.36077,
      "exit_price": 1.35151,
      "sl_price": 1.36377,
      "tp_price": 1.35151,
      "lots": 0.33,
      "pnl_usd": 258.68,
      "pnl_r": 2.587,
      "exit_reason": "tp",
      "duration_bars": 250
    },
    {
      "id": 99,
      "symbol": "USDCAD",
      "strategy": "macd_stochastic",
      "direction": "buy",
      "entry_time": "2025-11-30T18:31:55",
      "exit_time": "2025-12-01T01:17:20",
      "entry_price": 1.35985,
      "exit_price": 1.36668,
      "sl_price": 1.35669,
      "tp_price": 1.36668,
      "lots": 0.32,
      "pnl_usd": 294.84,
      "pnl_r": 2.948,
      "exit_reason": "tp",
      "duration_bars": 81
    },
    {
      "id": 44,
      "symbol": "EURGBP",
      "strategy": "momentum_pullback",
      "direction": "sell",
      "entry_time": "2025-12-02T19:49:30",
      "exit_time": "2025-12-03T17:51:31",
      "entry_price": 0.85523,
      "exit_price": 0.84751,
      "sl_price": 0.85921,
      "tp_price": 0.84751,
      "lots": 0.25,
      "pnl_usd": 186.59,
      "pnl_r": 1.866,
      "exit_reason": "tp",
      "duration_bars": 264
    },
    {
      "id": 68,
      "symbol": "EURUSD",
      "strategy": "macd_stochastic",
      "direction": "buy",
      "entry_time": "2025-12-02T20:44:42",
      "exit_time": "2025-12-04T03:34:07",
      "entry_price": 1.08506,
      "exit_price": 1.09458,
      "sl_price": 1.08266,
      "tp_price": 1.09458,
      "lots": 0.42,
      "pnl_usd": 214.04,
      "pnl_r": 2.14,
      "exit_reason": "tp",
      "duration_bars": 369
    },
    {
      "id": 6,
      "symbol": "USDJPY",
      "strategy": "macd_stochastic",
      "direction": "sell",
      "entry_time": "2025-12-03T05:34:14",
      "exit_time": "2025-12-04T07:08:20",
      "entry_price": 148.48152,
      "exit_price": 148.82185,
      "sl_price": 148.83824,
      "tp_price": 147.38832,
      "lots": 0.31,
      "pnl_usd": -77.05,
      "pnl_r": -0.771,
      "exit_reason": "trailing",
      "duration_bars": 306
    },
    {
      "id": 31,
      "symbol": "AUDUSD",
      "strategy": "momentum_pullback",
      "direction": "sell",
      "entry_time": "2025-12-04T23:08:51",
      "exit_time": "2025-12-06T08:44:28",
      "entry_price": 0.64472,
      "exit_price": 0.63298,
      "sl_price": 0.64849,
      "tp_price": 0.63298,
      "lots": 0.27,
      "pnl_usd": 160.75,
      "pnl_r": 1.608,
      "exit_reason": "tp",
      "duration_bars": 403
    },
    {
      "id": 70,
      "symbol": "USDCAD",
      "strategy": "komjathy",
      "direction": "buy",
      "entry_time": "2025-12-08T06:39:40",
      "exit_time": "2025-12-09T04:15:55",
      "entry_price": 1.35996,
      "exit_price": 1.36698,
      "sl_price": 1.35671,
      "tp_price": 1.36698,
      "lots": 0.31,
      "pnl_usd": 262.47,
      "pnl_r": 2.625,
      "exit_reason": "tp",
      "duration_bars": 259
    },
    {
      "id": 73,
      "symbol": "GBPUSD",
      "strategy": "macd_stochastic",
      "direction": "sell",
      "entry_time": "2025-12-08T21:51:50",
      "exit_time": "2025-12-10T09:40:38",
      "entry_price": 1.26412,
      "exit_price": 1.25208,
      "sl_price": 1.26748,
      "tp_price": 1.25208,
      "lots": 0.3,
      "pnl_usd": 161.78,
      "pnl_r": 1.618,
      "exit_reason": "tp",
      "duration_bars": 429
    },
    {
      "id": 60,
      "symbol": "XAUUSD",
      "strategy": "momentum_pullback",
      "direction": "sell",
      "entry_time": "2025-12-09T17:43:59",
      "exit_time": "2025-12-10T00:44:04",
      "entry_price": 2324.14333,
      "exit_price": 2199.62126,
      "sl_price": 2357.06878,
      "tp_price": 2199.62126,
      "lots": 0.3,
      "pnl_usd": 187.94,
      "pnl_r": 1.879,
      "exit_reason": "tp",
      "duration_bars": 84
    },
    {
      "id": 102,
      "symbol": "XAUUSD",
      "strategy": "momentum_pullback",
      "direction": "sell",
      "entry_time": "2025-12-10T22:14:37",
      "exit_time": "2025-12-12T03:29:56",
      "entry_price": 2321.01951,
      "exit_price": 2225.54639,
      "sl_price": 2351.18704,
      "tp_price": 2225.54639,
      "lots": 0.33,
      "pnl_usd": 223.77,
      "pnl_r": 2.238,
      "exit_reason": "tp",
      "duration_bars": 351
    },
    {
      "id": 3,
      "symbol": "GBPUSD",
      "strategy": "macd_stochastic",
      "direction": "sell",
      "entry_time": "2025-12-11T14:29:27",
      "exit_time": "2025-12-13T09:59:03",
      "entry_price": 1.26506,
      "exit_price": 1.26735,
      "sl_price": 1.26725,
      "tp_price": 1.25729,
      "lots": 0.46,
      "pnl_usd": -53.8,
      "pnl_r": -0.538,
      "exit_reason": "trailing",
      "duration_bars": 521
    },
    {
      "id": 66,
      "symbol": "GBPUSD",
      "strategy": "macd_stochastic",
      "direction": "buy",
      "entry_time": "2025-12-13T17:36:43",
      "exit_time": "2025-12-13T21:37:38",
      "entry_price": 1.26532,
      "exit_price": 1.27564,
      "sl_price": 1.26218,
      "tp_price": 1.27564,
      "lots": 0.32,
      "pnl_usd": 188.37,
      "pnl_r": 1.884,
      "exit_reason": "tp",
      "duration_bars": 48
    },
    {
      "id": 113,
      "symbol": "XAUUSD",
      "strategy": "macd_stochastic",
      "direction": "sell",
      "entry_time": "2025-12-13T19:53:03",
      "exit_time": "2025-12-15T17:00:28",
      "entry_price": 2323.37324,
      "exit_price": 2358.62746,
      "sl_price": 2358.87798,
      "tp_price": 2220.70928,
      "lots": 0.28,
      "pnl_usd": -89.62,
      "pnl_r": -0.896,
      "exit_reason": "sl",
      "duration_bars": 541
    },
    {
      "id": 53,
      "symbol": "EURJPY",
      "strategy": "komjathy",
      "direction": "buy",
      "entry_time": "2025-12-14T04:53:43",
      "exit_time": "2025-12-15T09:36:56",
      "entry_price": 161.14201,
      "exit_price": 160.75241,
      "sl_price": 160.75192,
      "tp_price": 162.59494,
      "lots": 0.28,
      "pnl_usd": -119.18,
      "pnl_r": -1.192,
      "exit_reason": "sl",
      "duration_bars": 344
    },
    {
      "id": 110,
      "symbol": "XAUUSD",
      "strategy": "momentum_pullback",
      "direction": "buy",
      "entry_time": "2025-12-14T11:19:43",
      "exit_time": "2025-12-15T07:36:24",
      "entry_price": 2310.20707,
      "exit_price": 2294.98401,
      "sl_price": 2293.52925,
      "tp_price": 2337.51831,
      "lots": 0.6,
      "pnl_usd": -107.85,
      "pnl_r": -1.079,
      "exit_reason": "trailing",
      "duration_bars": 243
    },
    {
      "id": 32,
      "symbol": "EURJPY",
      "strategy": "macd_stochastic",
      "direction": "buy",
      "entry_time": "2025-12-14T18:56:32",
      "exit_time": "2025-12-15T17:13:28",
      "entry_price": 161.17761,
      "exit_price": 160.98537,
      "sl_price": 160.98974,
      "tp_price": 161.6335,
      "lots": 0.59,
      "pnl_usd": -93.35,
      "pnl_r": -0.933,
      "exit_reason": "sl",
      "duration_bars": 267
    },
    {
      "id": 26,
      "symbol": "GBPJPY",
      "strategy": "macd_stochastic",
      "direction": "buy",
      "entry_time": "2025-12-16T16:32:50",
      "exit_time": "2025-12-18T11:51:36",
      "entry_price": 188.71165,
      "exit_price": 188.36486,
      "sl_price": 188.37951,
      "tp_price": 189.60821,
      "lots": 0.33,
      "pnl_usd": -65.42,
      "pnl_r": -0.654,
      "exit_reason": "sl",
      "duration_bars": 519
    },
    {
      "id": 92,
      "symbol": "GBPUSD",
      "strategy": "momentum_pullback",
      "direction": "sell",
      "entry_time": "2025-12-17T05:45:36",
      "exit_time": "2025-12-18T13:19:30",
      "entry_price": 1.26528,
      "exit_price": 1.25273,
      "sl_price": 1.26911,
      "tp_price": 1.25273,
      "lots": 0.26,
      "pnl_usd": 106.59,
      "pnl_r": 1.066,
      "exit_reason": "tp",
      "duration_bars": 378
    },
    {
      "id": 88,
      "symbol": "AUDUSD",
      "strategy": "macd_stochastic",
      "direction": "buy",
      "entry_time": "2025-12-18T23:22:31",
      "exit_time": "2025-12-19T13:58:45",
      "entry_price": 0.64472,
      "exit_price": 0.64741,
      "sl_price": 0.64294,
      "tp_price": 0.64741,
      "lots": 0.56,
      "pnl_usd": 104.37,
      "pnl_r": 1.044,
      "exit_reason": "tp",
      "duration_bars": 175
    },
    {
      "id": 50,
      "symbol": "GBPUSD",
      "strategy": "momentum_pullback",
      "direction": "sell",
      "entry_time": "2025-12-20T20:38:05",
      "exit_time": "2025-12-22T01:27:53",
      "entry_price": 1.2656,
      "exit_price": 1.26795,
      "sl_price": 1.26798,
      "tp_price": 1.26028,
      "lots": 0.42,
      "pnl_usd": -117.47,
      "pnl_r": -1.175,
      "exit_reason": "trailing",
      "duration_bars": 345
    },
    {
      "id": 74,
      "symbol": "EURGBP",
      "strategy": "momentum_pullback",
      "direction": "buy",
      "entry_time": "2025-12-23T19:20:07",
      "exit_time": "2025-12-25T17:02:37",
      "entry_price": 0.85493,
      "exit_price": 0.86315,
      "sl_price": 0.85272,
      "tp_price": 0.86315,
      "lots": 0.45,
      "pnl_usd": 283.35,
      "pnl_r": 2.833,
      "exit_reason": "tp",
      "duration_bars": 548
    },
    {
      "id": 103,
      "symbol": "EURUSD",
      "strategy": "komjathy",
      "direction": "sell",
      "entry_time": "2025-12-23T19:25:07",
      "exit_time": "2025-12-24T08:07:04",
      "entry_price": 1.08444,
      "exit_price": 1.07837,
      "sl_price": 1.08668,
      "tp_price": 1.07837,
      "lots": 0.45,
      "pnl_usd": 207.95,
      "pnl_r": 2.079,
      "exit_reason": "tp",
      "duration_bars": 152
    },
    {
      "id": 59,
      "symbol": "USDCAD",
      "strategy": "momentum_pullback",
      "direction": "buy",
      "entry_time": "2025-12-24T08:18:06",
      "exit_time": "2025-12-24T16:48:06",
      "entry_price": 1.35975,
      "exit_price": 1.36837,
      "sl_price": 1.35645,
      "tp_price": 1.36837,
      "lots": 0.3,
      "pnl_usd": 235.02,
      "pnl_r": 2.35,
      "exit_reason": "tp",
      "duration_bars": 102
    },
    {
      "id": 78,
      "symbol": "GBPUSD",
      "strategy": "macd_stochastic",
      "direction": "buy",
      "entry_time": "2025-12-26T09:12:03",
      "exit_time": "2025-12-28T05:46:29",
      "entry_price": 1.26499,
      "exit_price": 1.27018,
      "sl_price": 1.26172,
      "tp_price": 1.27018,
      "lots": 0.31,
      "pnl_usd": 101.94,
      "pnl_r": 1.019,
      "exit_reason": "tp",
      "duration_bars": 534
    },
    {
      "id": 82,
      "symbol": "EURJPY",
      "strategy": "komjathy",
      "direction": "sell",
      "entry_time": "2025-12-26T20:25:30",
      "exit_time": "2025-12-27T03:15:14",
      "entry_price": 161.20809,
      "exit_price": 161.55407,
      "sl_price": 161.54831,
      "tp_price": 160.42917,
      "lots": 0.33,
      "pnl_usd": -54.73,
      "pnl_r": -0.547,
      "exit_reason": "trailing",
      "duration_bars": 81
    },
    {
      "id": 112,
      "symbol": "EURJPY",
      "strategy": "macd_stochastic",
      "direction": "sell",
      "entry_time": "2025-12-27T00:31:04",
      "exit_time": "2025-12-27T11:03:27",
      "entry_price": 161.18612,
      "exit_price": 160.60199,
      "sl_price": 161.5549,
      "tp_price": 160.60199,
      "lots": 0.3,
      "pnl_usd": 299.99,
      "pnl_r": 3.0,
      "exit_reason": "tp",
      "duration_bars": 126
    },
    {
      "id": 62,
      "symbol": "EURUSD",
      "strategy": "komjathy",
      "direction": "buy",
      "entry_time": "2025-12-27T19:49:23",
      "exit_time": "2025-12-29T07:53:50",
      "entry_price": 1.08515,
      "exit_price": 1.08363,
      "sl_price": 1.08352,
      "tp_price": 1.08827,
      "lots": 0.61,
      "pnl_usd": -58.6,
      "pnl_r": -0.586,
      "exit_reason": "trailing",
      "duration_bars": 432
    },
    {
      "id": 118,
      "symbol": "USDCHF",
      "strategy": "macd_stochastic",
      "direction": "buy",
      "entry_time": "2025-12-28T14:19:25",
      "exit_time": "2025-12-28T22:53:44",
      "entry_price": 0.90536,
      "exit_price": 0.91519,
      "sl_price": 0.90232,
      "tp_price": 0.91519,
      "lots": 0.33,
      "pnl_usd": 236.0,
      "pnl_r": 2.36,
      "exit_reason": "tp",
      "duration_bars": 102
    },
    {
      "id": 37,
      "symbol": "USDCHF",
      "strategy": "komjathy",
      "direction": "buy",
      "entry_time": "2025-12-31T09:51:52",
      "exit_time": "2026-01-01T11:49:24",
      "entry_price": 0.90475,
      "exit_price": 0.91302,
      "sl_price": 0.90095,
      "tp_price": 0.91302,
      "lots": 0.26,
      "pnl_usd": 144.18,
      "pnl_r": 1.442,
      "exit_reason": "tp",
      "duration_bars": 311
    },
    {
      "id": 22,
      "symbol": "EURUSD",
      "strategy": "komjathy",
      "direction": "sell",
      "entry_time": "2026-01-01T14:16:45",
      "exit_time": "2026-01-02T01:18:47",
      "entry_price": 1.08583,
      "exit_price": 1.08941,
      "sl_price": 1.08922,
      "tp_price": 1.07785,
      "lots": 0.29,
      "pnl_usd": -105.96,
      "pnl_r": -1.06,
      "exit_reason": "sl",
      "duration_bars": 132
    },
    {
      "id": 94,
      "symbol": "EURGBP",
      "strategy": "macd_stochastic",
      "direction": "buy",
      "entry_time": "2026-01-02T05:25:25",
      "exit_time": "2026-01-03T03:21:39",
      "entry_price": 0.85536,
      "exit_price": 0.85198,
      "sl_price": 0.85204,
      "tp_price": 0.86647,
      "lots": 0.3,
      "pnl_usd": -117.64,
      "pnl_r": -1.176,
      "exit_reason": "sl",
      "duration_bars": 263
    },
    {
      "id": 95,
      "symbol": "EURUSD",
      "strategy": "komjathy",
      "direction": "buy",
      "entry_time": "2026-01-03T16:42:13",
      "exit_time": "2026-01-04T11:14:56",
      "entry_price": 1.08516,
      "exit_price": 1.08275,
      "sl_price": 1.08267,
      "tp_price": 1.09404,
      "lots": 0.4,
      "pnl_usd": -52.37,
      "pnl_r": -0.524,
      "exit_reason": "trailing",
      "duration_bars": 222
    },
    {
      "id": 49,
      "symbol": "USDJPY",
      "strategy": "momentum_pullback",
      "direction": "buy",
      "entry_time": "2026-01-03T22:21:32",
      "exit_time": "2026-01-05T05:14:29",
      "entry_price": 148.58556,
      "exit_price": 148.2364,
      "sl_price": 148.22551,
      "tp_price": 149.33834,
      "lots": 0.31,
      "pnl_usd": -76.76,
      "pnl_r": -0.768,
      "exit_reason": "trailing",
      "duration_bars": 370
    },
    {
      "id": 41,
      "symbol": "EURGBP",
      "strategy": "momentum_pullback",
      "direction": "buy",
      "entry_time": "2026-01-04T05:38:15",
      "exit_time": "2026-01-04T12:59:11",
      "entry_price": 0.85539,
      "exit_price": 0.8518,
      "sl_price": 0.8519,
      "tp_price": 0.86761,
      "lots": 0.29,
      "pnl_usd": -107.87,
      "pnl_r": -1.079,
      "exit_reason": "sl",
      "duration_bars": 88
    },
    {
      "id": 39,
      "symbol": "USDJPY",
      "strategy": "komjathy",
      "direction": "sell",
      "entry_time": "2026-01-05T09:56:47",
      "exit_time": "2026-01-06T20:20:15",
      "entry_price": 148.51434,
      "exit_price": 148.85193,
      "sl_price": 148.87155,
      "tp_price": 147.91858,
      "lots": 0.31,
      "pnl_usd": -63.09,
      "pnl_r": -0.631,
      "exit_reason": "sl",
      "duration_bars": 412
    },
    {
      "id": 10,
      "symbol": "USDCAD",
      "strategy": "macd_stochastic",
      "direction": "buy",
      "entry_time": "2026-01-05T14:13:07",
      "exit_time": "2026-01-06T21:54:00",
      "entry_price": 1.3595,
      "exit_price": 1.36893,
      "sl_price": 1.35649,
      "tp_price": 1.36893,
      "lots": 0.33,
      "pnl_usd": 295.55,
      "pnl_r": 2.956,
      "exit_reason": "tp",
      "duration_bars": 380
    },
    {
      "id": 115,
      "symbol": "GBPUSD",
      "strategy": "macd_stochastic",
      "direction": "buy",
      "entry_time": "2026-01-07T15:17:11",
      "exit_time": "2026-01-09T02:36:35",
      "entry_price": 1.26411,
      "exit_price": 1.27399,
      "sl_price": 1.26143,
      "tp_price": 1.27399,
      "lots": 0.37,
      "pnl_usd": 188.48,
      "pnl_r": 1.885,
      "exit_reason": "tp",
      "duration_bars": 423
    },
    {
      "id": 75,
      "symbol": "USDCAD",
      "strategy": "komjathy",
      "direction": "sell",
      "entry_time": "2026-01-08T02:17:13",
      "exit_time": "2026-01-08T22:15:54",
      "entry_price": 1.35984,
      "exit_price": 1.36348,
      "sl_price": 1.36356,
      "tp_price": 1.34648,
      "lots": 0.27,
      "pnl_usd": -117.07,
      "pnl_r": -1.171,
      "exit_reason": "sl",
      "duration_bars": 239
    },
    {
      "id": 27,
      "symbol": "USDCHF",
      "strategy": "macd_stochastic",
      "direction": "sell",
      "entry_time": "2026-01-08T18:02:16",
      "exit_time": "2026-01-09T18:58:04",
      "entry_price": 0.90599,
      "exit_price": 0.90126,
      "sl_price": 0.90776,
      "tp_price": 0.90126,
      "lots": 0.57,
      "pnl_usd": 239.73,
      "pnl_r": 2.397,
      "exit_reason": "tp",
      "duration_bars": 299
    },
    {
      "id": 81,
      "symbol": "EURUSD",
      "strategy": "momentum_pullback",
      "direction": "sell",
      "entry_time": "2026-01-09T06:05:26",
      "exit_time": "2026-01-09T13:26:36",
      "entry_price": 1.08481,
      "exit_price": 1.08045,
      "sl_price": 1.08714,
      "tp_price": 1.08045,
      "lots": 0.43,
      "pnl_usd": 161.07,
      "pnl_r": 1.611,
      "exit_reason": "tp",
      "duration_bars": 88
    },
    {
      "id": 28,
      "symbol": "GBPJPY",
      "strategy": "komjathy",
      "direction": "buy",
      "entry_time": "2026-01-11T03:14:32",
      "exit_time": "2026-01-13T00:48:37",
      "entry_price": 188.69848,
      "exit_price": 188.49096,
      "sl_price": 188.47996,
      "tp_price": 189.48029,
      "lots": 0.51,
      "pnl_usd": -71.59,
      "pnl_r": -0.716,
      "exit_reason": "sl",
      "duration_bars": 546
    },
    {
      "id": 55,
      "symbol": "EURGBP",
      "strategy": "macd_stochastic",
      "direction": "buy",
      "entry_time": "2026-01-12T23:51:54",
      "exit_time": "2026-01-13T10:31:44",
      "entry_price": 0.85453,
      "exit_price": 0.86057,
      "sl_price": 0.85086,
      "tp_price": 0.86057,
      "lots": 0.27,
      "pnl_usd": 196.96,
      "pnl_r": 1.97,
      "exit_reason": "tp",
      "duration_bars": 127
    },
    {
      "id": 104,
      "symbol": "AUDUSD",
      "strategy": "komjathy",
      "direction": "sell",
      "entry_time": "2026-01-13T09:31:14",
      "exit_time": "2026-01-14T18:28:31",
      "entry_price": 0.64476,
      "exit_price": 0.64828,
      "sl_price": 0.64818,
      "tp_price": 0.63389,
      "lots": 0.29,
      "pnl_usd": -106.03,
      "pnl_r": -1.06,
      "exit_reason": "trailing",
      "duration_bars": 395
    },
    {
      "id": 90,
      "symbol": "EURGBP",
      "strategy": "momentum_pullback",
      "direction": "buy",
      "entry_time": "2026-01-13T13:40:18",
      "exit_time": "2026-01-14T13:07:42",
      "entry_price": 0.85539,
      "exit_price": 0.85265,
      "sl_price": 0.85266,
      "tp_price": 0.86491,
      "lots": 0.37,
      "pnl_usd": -118.8,
      "pnl_r": -1.188,
      "exit_reason": "sl",
      "duration_bars": 281
    },
    {
      "id": 23,
      "symbol": "EURUSD",
      "strategy": "komjathy",
      "direction": "sell",
      "entry_time": "2026-01-13T19:17:07",
      "exit_time": "2026-01-15T05:49:40",
      "entry_price": 1.08496,
      "exit_price": 1.08135,
      "sl_price": 1.08678,
      "tp_price": 1.08135,
      "lots": 0.55,
      "pnl_usd": 100.76,
      "pnl_r": 1.008,
      "exit_reason": "tp",
      "duration_bars": 414
    },
    {
      "id": 86,
      "symbol": "USDCHF",
      "strategy": "macd_stochastic",
      "direction": "buy",
      "entry_time": "2026-01-14T04:00:14",
      "exit_time": "2026-01-14T21:54:15",
      "entry_price": 0.90587,
      "exit_price": 0.90242,
      "sl_price": 0.90259,
      "tp_price": 0.91607,
      "lots": 0.3,
      "pnl_usd": -63.85,
      "pnl_r": -0.638,
      "exit_reason": "sl",
      "duration_bars": 214
    },
    {
      "id": 2,
      "symbol": "GBPJPY",
      "strategy": "komjathy",
      "direction": "sell",
      "entry_time": "2026-01-15T01:04:31",
      "exit_time": "2026-01-16T02:27:35",
      "entry_price": 188.65458,
      "exit_price": 189.00614,
      "sl_price": 188.98839,
      "tp_price": 187.96655,
      "lots": 0.33,
      "pnl_usd": -55.0,
      "pnl_r": -0.55,
      "exit_reason": "sl",
      "duration_bars": 304
    },
    {
      "id": 57,
      "symbol": "EURUSD",
      "strategy": "momentum_pullback",
      "direction": "buy",
      "entry_time": "2026-01-15T02:45:12",
      "exit_time": "2026-01-16T08:48:33",
      "entry_price": 1.08552,
      "exit_price": 1.09239,
      "sl_price": 1.08372,
      "tp_price": 1.09239,
      "lots": 0.56,
      "pnl_usd": 271.61,
      "pnl_r": 2.716,
      "exit_reason": "tp",
      "duration_bars": 360
    },
    {
      "id": 100,
      "symbol": "USDJPY",
      "strategy": "momentum_pullback",
      "direction": "buy",
      "entry_time": "2026-01-16T07:55:47",
      "exit_time": "2026-01-16T17:40:51",
      "entry_price": 148.54937,
      "exit_price": 148.15934,
      "sl_price": 148.17675,
      "tp_price": 149.16797,
      "lots": 0.3,
      "pnl_usd": -118.11,
      "pnl_r": -1.181,
      "exit_reason": "sl",
      "duration_bars": 117
    },
    {
      "id": 35,
      "symbol": "EURGBP",
      "strategy": "macd_stochastic",
      "direction": "buy",
      "entry_time": "2026-01-16T14:50:35",
      "exit_time": "2026-01-16T21:10:47",
      "entry_price": 0.85497,
      "exit_price": 0.86264,
      "sl_price": 0.85108,
      "tp_price": 0.86264,
      "lots": 0.26,
      "pnl_usd": 192.0,
      "pnl_r": 1.92,
      "exit_reason": "tp",
      "duration_bars": 76
    },
    {
      "id": 89,
      "symbol": "USDCAD",
      "strategy": "momentum_pullback",
      "direction": "sell",
      "entry_time": "2026-01-18T03:24:04",
      "exit_time": "2026-01-19T17:30:45",
      "entry_price": 1.35916,
      "exit_price": 1.36173,
      "sl_price": 1.36154,
      "tp_price": 1.35501,
      "lots": 0.42,
      "pnl_usd": -98.98,
      "pnl_r": -0.99,
      "exit_reason": "sl",
      "duration_bars": 457
    },
    {
      "id": 38,
      "symbol": "EURUSD",
      "strategy": "macd_stochastic",
      "direction": "buy",
      "entry_time": "2026-01-20T04:46:14",
      "exit_time": "2026-01-20T16:44:56",
      "entry_price": 1.08472,
      "exit_price": 1.08201,
      "sl_price": 1.0822,
      "tp_price": 1.09018,
      "lots": 0.4,
      "pnl_usd": -119.03,
      "pnl_r": -1.19,
      "exit_reason": "sl",
      "duration_bars": 143
    },
    {
      "id": 116,
      "symbol": "EURUSD",
      "strategy": "komjathy",
      "direction": "buy",
      "entry_time": "2026-01-20T14:32:42",
      "exit_time": "2026-01-21T22:54:34",
      "entry_price": 1.08488,
      "exit_price": 1.08169,
      "sl_price": 1.08156,
      "tp_price": 1.09639,
      "lots": 0.3,
      "pnl_usd": -119.3,
      "pnl_r": -1.193,
      "exit_reason": "sl",
      "duration_bars": 388
    },
    {
      "id": 71,
      "symbol": "GBPJPY",
      "strategy": "komjathy",
      "direction": "buy",
      "entry_time": "2026-01-21T02:24:08",
      "exit_time": "2026-01-21T22:51:27",
      "entry_price": 188.63224,
      "exit_price": 189.33047,
      "sl_price": 188.26756,
      "tp_price": 189.33047,
      "lots": 0.3,
      "pnl_usd": 205.41,
      "pnl_r": 2.054,
      "exit_reason": "tp",
      "duration_bars": 245
    },
    {
      "id": 4,
      "symbol": "EURUSD",
      "strategy": "momentum_pullback",
      "direction": "sell",
      "entry_time": "2026-01-21T08:01:33",
      "exit_time": "2026-01-21T12:10:03",
      "entry_price": 1.08436,
      "exit_price": 1.08681,
      "sl_price": 1.08689,
      "tp_price": 1.07517,
      "lots": 0.39,
      "pnl_usd": -111.07,
      "pnl_r": -1.111,
      "exit_reason": "sl",
      "duration_bars": 49
    },
    {
      "id": 20,
      "symbol": "EURJPY",
      "strategy": "macd_stochastic",
      "direction": "sell",
      "entry_time": "2026-01-22T09:20:15",
      "exit_time": "2026-01-23T09:59:25",
      "entry_price": 161.12799,
      "exit_price": 161.37918,
      "sl_price": 161.39686,
      "tp_price": 160.54325,
      "lots": 0.41,
      "pnl_usd": -50.94,
      "pnl_r": -0.509,
      "exit_reason": "trailing",
      "duration_bars": 295
    },
    {
      "id": 77,
      "symbol": "EURJPY",
      "strategy": "momentum_pullback",
      "direction": "buy",
      "entry_time": "2026-01-24T17:04:24",
      "exit_time": "2026-01-25T18:54:44",
      "entry_price": 161.17839,
      "exit_price": 161.60212,
      "sl_price": 160.90543,
      "tp_price": 161.60212,
      "lots": 0.41,
      "pnl_usd": 296.79,
      "pnl_r": 2.968,
      "exit_reason": "tp",
      "duration_bars": 310
    },
    {
      "id": 58,
      "symbol": "EURGBP",
      "strategy": "komjathy",
      "direction": "sell",
      "entry_time": "2026-01-25T00:06:05",
      "exit_time": "2026-01-26T13:53:44",
      "entry_price": 0.855,
      "exit_price": 0.8583,
      "sl_price": 0.85837,
      "tp_price": 0.84784,
      "lots": 0.3,
      "pnl_usd": -103.73,
      "pnl_r": -1.037,
      "exit_reason": "sl",
      "duration_bars": 453
    },
    {
      "id": 76,
      "symbol": "USDCHF",
      "strategy": "macd_stochastic",
      "direction": "sell",
      "entry_time": "2026-01-25T00:40:21",
      "exit_time": "2026-01-25T08:07:34",
      "entry_price": 0.9043,
      "exit_price": 0.89681,
      "sl_price": 0.90635,
      "tp_price": 0.89681,
      "lots": 0.49,
      "pnl_usd": 227.6,
      "pnl_r": 2.276,
      "exit_reason": "tp",
      "duration_bars": 89
    },
    {
      "id": 12,
      "symbol": "USDCHF",
      "strategy": "momentum_pullback",
      "direction": "buy",
      "entry_time": "2026-01-26T15:18:42",
      "exit_time": "2026-01-28T01:11:18",
      "entry_price": 0.90589,
      "exit_price": 0.91031,
      "sl_price": 0.90346,
      "tp_price": 0.91031,
      "lots": 0.41,
      "pnl_usd": 264.69,
      "pnl_r": 2.647,
      "exit_reason": "tp",
      "duration_bars": 406
    },
    {
      "id": 87,
      "symbol": "EURJPY",
      "strategy": "komjathy",
      "direction": "buy",
      "entry_time": "2026-01-27T13:25:05",
      "exit_time": "2026-01-28T08:41:34",
      "entry_price": 161.16182,
      "exit_price": 160.90917,
      "sl_price": 160.91703,
      "tp_price": 161.7829,
      "lots": 0.45,
      "pnl_usd": -62.66,
      "pnl_r": -0.627,
      "exit_reason": "sl",
      "duration_bars": 231
    },
    {
      "id": 65,
      "symbol": "AUDUSD",
      "strategy": "momentum_pullback",
      "direction": "sell",
      "entry_time": "2026-01-30T10:34:26",
      "exit_time": "2026-01-31T00:21:58",
      "entry_price": 0.64579,
      "exit_price": 0.64844,
      "sl_price": 0.64848,
      "tp_price": 0.64055,
      "lots": 0.37,
      "pnl_usd": -97.69,
      "pnl_r": -0.977,
      "exit_reason": "sl",
      "duration_bars": 165
    },
    {
      "id": 101,
      "symbol": "EURJPY",
      "strategy": "komjathy",
      "direction": "sell",
      "entry_time": "2026-01-30T15:49:29",
      "exit_time": "2026-02-01T01:17:14",
      "entry_price": 161.28084,
      "exit_price": 161.63926,
      "sl_price": 161.63428,
      "tp_price": 159.92957,
      "lots": 0.31,
      "pnl_usd": -85.99,
      "pnl_r": -0.86,
      "exit_reason": "trailing",
      "duration_bars": 401
    },
    {
      "id": 9,
      "symbol": "XAUUSD",
      "strategy": "komjathy",
      "direction": "buy",
      "entry_time": "2026-02-02T16:42:27",
      "exit_time": "2026-02-02T23:36:47",
      "entry_price": 2325.34437,
      "exit_price": 2303.5148,
      "sl_price": 2303.97351,
      "tp_price": 2395.22793,
      "lots": 0.47,
      "pnl_usd": -99.07,
      "pnl_r": -0.991,
      "exit_reason": "sl",
      "duration_bars": 82
    },
    {
      "id": 30,
      "symbol": "EURGBP",
      "strategy": "momentum_pullback",
      "direction": "buy",
      "entry_time": "2026-02-02T21:00:05",
      "exit_time": "2026-02-03T06:03:17",
      "entry_price": 0.8545,
      "exit_price": 0.86524,
      "sl_price": 0.85146,
      "tp_price": 0.86524,
      "lots": 0.33,
      "pnl_usd": 223.25,
      "pnl_r": 2.233,
      "exit_reason": "tp",
      "duration_bars": 108
    },
    {
      "id": 85,
      "symbol": "AUDUSD",
      "strategy": "komjathy",
      "direction": "sell",
      "entry_time": "2026-02-03T03:45:48",
      "exit_time": "2026-02-03T08:09:51",
      "entry_price": 0.64406,
      "exit_price": 0.63691,
      "sl_price": 0.64587,
      "tp_price": 0.63691,
      "lots": 0.55,
      "pnl_usd": 105.98,
      "pnl_r": 1.06,
      "exit_reason": "tp",
      "duration_bars": 52
    },
    {
      "id": 18,
      "symbol": "EURGBP",
      "strategy": "macd_stochastic",
      "direction": "sell",
      "entry_time": "2026-02-03T06:59:17",
      "exit_time": "2026-02-05T05:38:43",
      "entry_price": 0.85525,
      "exit_price": 0.85084,
      "sl_price": 0.85721,
      "tp_price": 0.85084,
      "lots": 0.51,
      "pnl_usd": 284.35,
      "pnl_r": 2.844,
      "exit_reason": "tp",
      "duration_bars": 559
    },
    {
      "id": 64,
      "symbol": "USDCHF",
      "strategy": "macd_stochastic",
      "direction": "buy",
      "entry_time": "2026-02-04T20:08:59",
      "exit_time": "2026-02-05T04:22:01",
      "entry_price": 0.90534,
      "exit_price": 0.91397,
      "sl_price": 0.90258,
      "tp_price": 0.91397,
      "lots": 0.36,
      "pnl_usd": 240.14,
      "pnl_r": 2.401,
      "exit_reason": "tp",
      "duration_bars": 98
    },
    {
      "id": 8,
      "symbol": "EURJPY",
      "strategy": "momentum_pullback",
      "direction": "buy",
      "entry_time": "2026-02-07T03:07:56",
      "exit_time": "2026-02-07T19:34:12",
      "entry_price": 161.1664,
      "exit_price": 161.48231,
      "sl_price": 160.98099,
      "tp_price": 161.48231,
      "lots": 0.6,
      "pnl_usd": 125.71,
      "pnl_r": 1.257,
      "exit_reason": "tp",
      "duration_bars": 197
    },
    {
      "id": 80,
      "symbol": "EURUSD",
      "strategy": "komjathy",
      "direction": "buy",
      "entry_time": "2026-02-08T06:33:22",
      "exit_time": "2026-02-08T13:13:18",
      "entry_price": 1.08476,
      "exit_price": 1.08995,
      "sl_price": 1.08169,
      "tp_price": 1.08995,
      "lots": 0.33,
      "pnl_usd": 164.53,
      "pnl_r": 1.645,
      "exit_reason": "tp",
      "duration_bars": 79
    },
    {
      "id": 91,
      "symbol": "EURGBP",
      "strategy": "macd_stochastic",
      "direction": "buy",
      "entry_time": "2026-02-09T17:07:10",
      "exit_time": "2026-02-11T16:38:51",
      "entry_price": 0.85563,
      "exit_price": 0.85885,
      "sl_price": 0.8541,
      "tp_price": 0.85885,
      "lots": 0.65,
      "pnl_usd": 122.51,
      "pnl_r": 1.225,
      "exit_reason": "tp",
      "duration_bars": 570
    },
    {
      "id": 29,
      "symbol": "EURUSD",
      "strategy": "momentum_pullback",
      "direction": "sell",
      "entry_time": "2026-02-09T21:47:21",
      "exit_time": "2026-02-10T00:08:46",
      "entry_price": 1.08516,
      "exit_price": 1.07771,
      "sl_price": 1.08704,
      "tp_price": 1.07771,
      "lots": 0.53,
      "pnl_usd": 177.02,
      "pnl_r": 1.77,
      "exit_reason": "tp",
      "duration_bars": 28
    },
    {
      "id": 98,
      "symbol": "AUDUSD",
      "strategy": "macd_stochastic",
      "direction": "sell",
      "entry_time": "2026-02-10T15:18:45",
      "exit_time": "2026-02-12T03:53:22",
      "entry_price": 0.64411,
      "exit_price": 0.63847,
      "sl_price": 0.64648,
      "tp_price": 0.63847,
      "lots": 0.42,
      "pnl_usd": 127.16,
      "pnl_r": 1.272,
      "exit_reason": "tp",
      "duration_bars": 438
    },
    {
      "id": 16,
      "symbol": "GBPUSD",
      "strategy": "komjathy",
      "direction": "buy",
      "entry_time": "2026-02-13T12:20:11",
      "exit_time": "2026-02-14T16:57:44",
      "entry_price": 1.26406,
      "exit_price": 1.26922,
      "sl_price": 1.26123,
      "tp_price": 1.26922,
      "lots": 0.35,
      "pnl_usd": 145.98,
      "pnl_r": 1.46,
      "exit_reason": "tp",
      "duration_bars": 343
    },
    {
      "id": 93,
      "symbol": "EURUSD",
      "strategy": "momentum_pullback",
      "direction": "sell",
      "entry_time": "2026-02-13T12:58:14",
      "exit_time": "2026-02-14T20:38:05",
      "entry_price": 1.08546,
      "exit_price": 1.08885,
      "sl_price": 1.08902,
      "tp_price": 1.077,
      "lots": 0.28,
      "pnl_usd": -98.25,
      "pnl_r": -0.983,
      "exit_reason": "sl",
      "duration_bars": 379
    },
    {
      "id": 72,
      "symbol": "GBPJPY",
      "strategy": "komjathy",
      "direction": "sell",
      "entry_time": "2026-02-13T15:08:28",
      "exit_time": "2026-02-14T15:26:35",
      "entry_price": 188.60587,
      "exit_price": 188.9978,
      "sl_price": 188.99489,
      "tp_price": 187.86504,
      "lots": 0.29,
      "pnl_usd": -102.44,
      "pnl_r": -1.024,
      "exit_reason": "sl",
      "duration_bars": 291
    },
    {
      "id": 96,
      "symbol": "EURJPY",
      "strategy": "macd_stochastic",
      "direction": "sell",
      "entry_time": "2026-02-14T19:43:27",
      "exit_time": "2026-02-15T14:18:29",
      "entry_price": 161.10309,
      "exit_price": 160.31151,
      "sl_price": 161.48517,
      "tp_price": 160.31151,
      "lots": 0.29,
      "pnl_usd": 218.31,
      "pnl_r": 2.183,
      "exit_reason": "tp",
      "duration_bars": 223
    },
    {
      "id": 105,
      "symbol": "GBPJPY",
      "strategy": "momentum_pullback",
      "direction": "sell",
      "entry_time": "2026-02-16T18:10:01",
      "exit_time": "2026-02-17T09:37:11",
      "entry_price": 188.7682,
      "exit_price": 188.39258,
      "sl_price": 189.01388,
      "tp_price": 188.39258,
      "lots": 0.45,
      "pnl_usd": 180.63,
      "pnl_r": 1.806,
      "exit_reason": "tp",
      "duration_bars": 185
    },
    {
      "id": 13,
      "symbol": "GBPJPY",
      "strategy": "momentum_pullback",
      "direction": "buy",
      "entry_time": "2026-02-17T07:52:48",
      "exit_time": "2026-02-19T04:57:46",
      "entry_price": 188.62152,
      "exit_price": 188.24469,
      "sl_price": 188.24958,
      "tp_price": 189.6787,
      "lots": 0.3,
      "pnl_usd": -55.12,
      "pnl_r": -0.551,
      "exit_reason": "trailing",
      "duration_bars": 540
    },
    {
      "id": 19,
      "symbol": "GBPJPY",
      "strategy": "macd_stochastic",
      "direction": "sell",
      "entry_time": "2026-02-17T15:33:04",
      "exit_time": "2026-02-18T07:14:25",
      "entry_price": 188.78289,
      "exit_price": 187.25077,
      "sl_price": 189.17743,
      "tp_price": 187.25077,
      "lots": 0.28,
      "pnl_usd": 131.83,
      "pnl_r": 1.318,
      "exit_reason": "tp",
      "duration_bars": 188
    },
    {
      "id": 111,
      "symbol": "GBPUSD",
      "strategy": "momentum_pullback",
      "direction": "sell",
      "entry_time": "2026-02-18T23:01:35",
      "exit_time": "2026-02-20T00:01:52",
      "entry_price": 1.26491,
      "exit_price": 1.26816,
      "sl_price": 1.26833,
      "tp_price": 1.25273,
      "lots": 0.29,
      "pnl_usd": -52.58,
      "pnl_r": -0.526,
      "exit_reason": "trailing",
      "duration_bars": 300
    },
    {
      "id": 106,
      "symbol": "EURJPY",
      "strategy": "momentum_pullback",
      "direction": "sell",
      "entry_time": "2026-02-19T08:14:20",
      "exit_time": "2026-02-20T11:42:26",
      "entry_price": 161.20218,
      "exit_price": 160.35129,
      "sl_price": 161.45833,
      "tp_price": 160.35129,
      "lots": 0.43,
      "pnl_usd": 155.95,
      "pnl_r": 1.56,
      "exit_reason": "tp",
      "duration_bars": 329
    },
    {
      "id": 54,
      "symbol": "EURGBP",
      "strategy": "komjathy",
      "direction": "sell",
      "entry_time": "2026-02-19T12:54:09",
      "exit_time": "2026-02-21T06:37:05",
      "entry_price": 0.85498,
      "exit_price": 0.85783,
      "sl_price": 0.85777,
      "tp_price": 0.84602,
      "lots": 0.36,
      "pnl_usd": -88.11,
      "pnl_r": -0.881,
      "exit_reason": "sl",
      "duration_bars": 500
    },
    {
      "id": 40,
      "symbol": "GBPJPY",
      "strategy": "macd_stochastic",
      "direction": "buy",
      "entry_time": "2026-02-20T01:45:45",
      "exit_time": "2026-02-21T18:17:24",
      "entry_price": 188.70837,
      "exit_price": 189.28645,
      "sl_price": 188.4322,
      "tp_price": 189.28645,
      "lots": 0.4,
      "pnl_usd": 137.2,
      "pnl_r": 1.372,
      "exit_reason": "tp",
      "duration_bars": 486
    },
    {
      "id": 45,
      "symbol": "EURGBP",
      "strategy": "momentum_pullback",
      "direction": "sell",
      "entry_time": "2026-02-23T02:06:19",
      "exit_time": "2026-02-23T22:58:50",
      "entry_price": 0.85404,
      "exit_price": 0.84411,
      "sl_price": 0.85789,
      "tp_price": 0.84411,
      "lots": 0.26,
      "pnl_usd": 207.25,
      "pnl_r": 2.072,
      "exit_reason": "tp",
      "duration_bars": 250
    },
    {
      "id": 51,
      "symbol": "GBPJPY",
      "strategy": "momentum_pullback",
      "direction": "buy",
      "entry_time": "2026-02-25T01:09:49",
      "exit_time": "2026-02-26T11:07:52",
      "entry_price": 188.6955,
      "exit_price": 189.28167,
      "sl_price": 188.50975,
      "tp_price": 189.28167,
      "lots": 0.6,
      "pnl_usd": 178.06,
      "pnl_r": 1.781,
      "exit_reason": "tp",
      "duration_bars": 407
    },
    {
      "id": 83,
      "symbol": "EURJPY",
      "strategy": "komjathy",
      "direction": "sell",
      "entry_time": "2026-02-27T13:27:11",
      "exit_time": "2026-02-27T19:21:14",
      "entry_price": 161.28622,
      "exit_price": 160.83966,
      "sl_price": 161.54802,
      "tp_price": 160.83966,
      "lots": 0.42,
      "pnl_usd": 133.1,
      "pnl_r": 1.331,
      "exit_reason": "tp",
      "duration_bars": 70
    },
    {
      "id": 120,
      "symbol": "GBPUSD",
      "strategy": "momentum_pullback",
      "direction": "buy",
      "entry_time": "2026-02-28T10:32:19",
      "exit_time": "2026-03-01T16:36:09",
      "entry_price": 1.26559,
      "exit_price": 1.27314,
      "sl_price": 1.26279,
      "tp_price": 1.27314,
      "lots": 0.36,
      "pnl_usd": 281.46,
      "pnl_r": 2.815,
      "exit_reason": "tp",
      "duration_bars": 360
    },
    {
      "id": 7,
      "symbol": "XAUUSD",
      "strategy": "komjathy",
      "direction": "sell",
      "entry_time": "2026-02-28T14:54:23",
      "exit_time": "2026-02-28T23:27:13",
      "entry_price": 2312.53882,
      "exit_price": 2338.99047,
      "sl_price": 2340.53702,
      "tp_price": 2254.24863,
      "lots": 0.36,
      "pnl_usd": -106.1,
      "pnl_r": -1.061,
      "exit_reason": "trailing",
      "duration_bars": 102
    },
    {
      "id": 97,
      "symbol": "XAUUSD",
      "strategy": "momentum_pullback",
      "direction": "buy",
      "entry_time": "2026-02-28T22:55:26",
      "exit_time": "2026-03-02T11:10:49",
      "entry_price": 2326.75372,
      "exit_price": 2292.58775,
      "sl_price": 2292.56336,
      "tp_price": 2422.2632,
      "lots": 0.29,
      "pnl_usd": -81.8,
      "pnl_r": -0.818,
      "exit_reason": "trailing",
      "duration_bars": 435
    },
    {
      "id": 52,
      "symbol": "USDCHF",
      "strategy": "macd_stochastic",
      "direction": "buy",
      "entry_time": "2026-03-01T00:12:37",
      "exit_time": "2026-03-02T19:21:26",
      "entry_price": 0.90563,
      "exit_price": 0.90982,
      "sl_price": 0.9029,
      "tp_price": 0.90982,
      "lots": 0.37,
      "pnl_usd": 288.08,
      "pnl_r": 2.881,
      "exit_reason": "tp",
      "duration_bars": 517
    },
    {
      "id": 25,
      "symbol": "GBPJPY",
      "strategy": "macd_stochastic",
      "direction": "sell",
      "entry_time": "2026-03-01T02:21:15",
      "exit_time": "2026-03-02T20:17:57",
      "entry_price": 188.77924,
      "exit_price": 187.90202,
      "sl_price": 189.10926,
      "tp_price": 187.90202,
      "lots": 0.34,
      "pnl_usd": 194.96,
      "pnl_r": 1.95,
      "exit_reason": "tp",
      "duration_bars": 503
    },
    {
      "id": 108,
      "symbol": "AUDUSD",
      "strategy": "macd_stochastic",
      "direction": "sell",
      "entry_time": "2026-03-03T20:51:38",
      "exit_time": "2026-03-05T18:50:42",
      "entry_price": 0.64471,
      "exit_price": 0.64076,
      "sl_price": 0.64642,
      "tp_price": 0.64076,
      "lots": 0.59,
      "pnl_usd": 214.24,
      "pnl_r": 2.142,
      "exit_reason": "tp",
      "duration_bars": 551
    },
    {
      "id": 14,
      "symbol": "GBPJPY",
      "strategy": "komjathy",
      "direction": "sell",
      "entry_time": "2026-03-05T02:35:33",
      "exit_time": "2026-03-05T20:26:55",
      "entry_price": 188.7433,
      "exit_price": 189.09124,
      "sl_price": 189.10422,
      "tp_price": 187.89732,
      "lots": 0.31,
      "pnl_usd": -62.29,
      "pnl_r": -0.623,
      "exit_reason": "sl",
      "duration_bars": 214
    },
    {
      "id": 33,
      "symbol": "GBPJPY",
      "strategy": "macd_stochastic",
      "direction": "buy",
      "entry_time": "2026-03-07T00:47:45",
      "exit_time": "2026-03-07T11:18:29",
      "entry_price": 188.65641,
      "exit_price": 189.59978,
      "sl_price": 188.37153,
      "tp_price": 189.59978,
      "lots": 0.39,
      "pnl_usd": 160.97,
      "pnl_r": 1.61,
      "exit_reason": "tp",
      "duration_bars": 126
    },
    {
      "id": 69,
      "symbol": "USDCHF",
      "strategy": "macd_stochastic",
      "direction": "buy",
      "entry_time": "2026-03-08T09:48:45",
      "exit_time": "2026-03-09T20:29:32",
      "entry_price": 0.90574,
      "exit_price": 0.91332,
      "sl_price": 0.90341,
      "tp_price": 0.91332,
      "lots": 0.43,
      "pnl_usd": 213.94,
      "pnl_r": 2.139,
      "exit_reason": "tp",
      "duration_bars": 416
    },
    {
      "id": 42,
      "symbol": "USDCAD",
      "strategy": "komjathy",
      "direction": "sell",
      "entry_time": "2026-03-09T12:06:19",
      "exit_time": "2026-03-10T17:08:46",
      "entry_price": 1.35927,
      "exit_price": 1.36145,
      "sl_price": 1.36138,
      "tp_price": 1.35103,
      "lots": 0.47,
      "pnl_usd": -70.53,
      "pnl_r": -0.705,
      "exit_reason": "trailing",
      "duration_bars": 348
    },
    {
      "id": 34,
      "symbol": "XAUUSD",
      "strategy": "komjathy",
      "direction": "sell",
      "entry_time": "2026-03-09T15:49:21",
      "exit_time": "2026-03-11T10:27:34",
      "entry_price": 2310.36419,
      "exit_price": 2207.40268,
      "sl_price": 2345.39802,
      "tp_price": 2207.40268,
      "lots": 0.29,
      "pnl_usd": 293.74,
      "pnl_r": 2.937,
      "exit_reason": "tp",
      "duration_bars": 511
    }
  ]
}