{
  "generated_at": "2026-03-31T17:20:16.710166Z",
  "mode": "dummy",
  "initial_equity": 10000.0,
  "period": {
    "start": "2025-11-01",
    "end": "2026-03-28"
  },
  "stats": {
    "total_trades": 120,
    "winning_trades": 58,
    "losing_trades": 62,
    "win_rate_pct": 48.3,
    "total_pnl_usd": 6113.25,
    "total_r": 61.134,
    "r_per_day": 0.746,
    "avg_win_usd": 196.58,
    "avg_loss_usd": -85.3,
    "profit_factor": 2.156,
    "max_drawdown_pct": 3.99,
    "initial_equity": 10000.0,
    "final_equity": 16113.25,
    "return_pct": 61.13,
    "avg_duration_bars": 315.1,
    "daily_pnl": {
      "2025-11-02": -106.86,
      "2025-11-04": 47.329999999999984,
      "2025-11-03": 237.25,
      "2025-11-05": 444.4,
      "2025-11-06": -110.85,
      "2025-11-07": -110.0,
      "2025-11-08": 22.400000000000006,
      "2025-11-09": -85.4,
      "2025-11-10": 93.57999999999998,
      "2025-11-11": -115.0,
      "2025-11-12": 54.82000000000001,
      "2025-11-13": 128.34,
      "2025-11-14": -229.44,
      "2025-11-15": -115.31,
      "2025-11-16": 86.23000000000002,
      "2025-11-17": 251.14,
      "2025-11-19": 120.99,
      "2025-11-18": 190.64,
      "2025-11-20": 394.24,
      "2025-11-21": -75.79,
      "2025-11-23": -65.2,
      "2025-11-27": -119.73,
      "2025-12-02": 280.8,
      "2025-12-01": 159.58,
      "2025-12-03": 139.68,
      "2025-12-06": 404.89,
      "2025-12-07": -75.48,
      "2025-12-09": -15.840000000000003,
      "2025-12-10": 261.9,
      "2025-12-11": -114.33,
      "2025-12-12": 218.91,
      "2025-12-13": 279.72,
      "2025-12-14": 100.17,
      "2025-12-15": -77.61,
      "2025-12-17": -263.55999999999995,
      "2025-12-19": 150.84000000000003,
      "2025-12-18": 228.42000000000002,
      "2025-12-20": 338.48,
      "2025-12-23": 160.33999999999997,
      "2025-12-25": 154.78,
      "2025-12-24": 171.46,
      "2025-12-26": 372.08000000000004,
      "2025-12-29": -73.78,
      "2025-12-28": -95.72,
      "2025-12-31": 35.69,
      "2026-01-02": -73.09,
      "2026-01-01": 117.41,
      "2026-01-05": -56.61,
      "2026-01-07": -87.61,
      "2026-01-06": 234.13,
      "2026-01-09": 99.69999999999999,
      "2026-01-10": 168.27,
      "2026-01-14": 101.74,
      "2026-01-17": 96.44,
      "2026-01-18": 267.3,
      "2026-01-22": -68.69,
      "2026-01-23": -212.47,
      "2026-01-24": 152.45,
      "2026-01-26": 110.84,
      "2026-01-27": -74.79,
      "2026-01-28": -101.34,
      "2026-01-29": -82.45,
      "2026-01-31": 147.13,
      "2026-02-01": -88.43,
      "2026-02-02": 160.61,
      "2026-02-04": 101.41000000000001,
      "2026-02-05": 237.6,
      "2026-02-10": 397.32,
      "2026-02-09": 231.34,
      "2026-02-11": 270.03,
      "2026-02-12": 181.32999999999998,
      "2026-02-15": 126.39,
      "2026-02-20": 611.54,
      "2026-02-22": -74.73,
      "2026-02-26": -73.65,
      "2026-02-28": 117.04,
      "2026-03-02": -83.38,
      "2026-03-03": -74.21,
      "2026-03-04": 200.25000000000003,
      "2026-03-06": -277.51,
      "2026-03-09": -110.32,
      "2026-03-10": -156.94
    },
    "weekly_pnl": {
      "2025-W44": -106.86,
      "2025-W45": 445.13,
      "2025-W46": -96.78,
      "2025-W47": 816.02,
      "2025-W48": -119.73,
      "2025-W49": 909.47,
      "2025-W50": 730.53,
      "2025-W51": 376.57,
      "2025-W52": 762.94,
      "2025-W01": -38.09,
      "2026-W01": 44.32,
      "2026-W02": 357.88,
      "2026-W03": 465.48,
      "2026-W04": -128.71,
      "2026-W05": -89.04,
      "2026-W06": 499.62,
      "2026-W07": 1206.41,
      "2026-W08": 536.81,
      "2026-W09": 43.39,
      "2026-W10": -234.85,
      "2026-W11": -267.26
    },
    "weekly_r": {
      "2025-W44": -1.069,
      "2025-W45": 4.452,
      "2025-W46": -0.968,
      "2025-W47": 8.159,
      "2025-W48": -1.197,
      "2025-W49": 9.095,
      "2025-W50": 7.306,
      "2025-W51": 3.766,
      "2025-W52": 7.631,
      "2025-W01": -0.381,
      "2026-W01": 0.443,
      "2026-W02": 3.579,
      "2026-W03": 4.654,
      "2026-W04": -1.288,
      "2026-W05": -0.89,
      "2026-W06": 4.996,
      "2026-W07": 12.063,
      "2026-W08": 5.369,
      "2026-W09": 0.433,
      "2026-W10": -2.347,
      "2026-W11": -2.672
    },
    "by_symbol": {
      "EURUSD": {
        "trades": 16,
        "win_rate": 43.8,
        "total_pnl": 658.65,
        "total_r": 6.587
      },
      "GBPUSD": {
        "trades": 17,
        "win_rate": 47.1,
        "total_pnl": 551.4,
        "total_r": 5.514
      },
      "USDJPY": {
        "trades": 11,
        "win_rate": 45.5,
        "total_pnl": 657.88,
        "total_r": 6.58
      },
      "AUDUSD": {
        "trades": 11,
        "win_rate": 54.5,
        "total_pnl": 855.48,
        "total_r": 8.554
      },
      "USDCAD": {
        "trades": 8,
        "win_rate": 25.0,
        "total_pnl": -196.27,
        "total_r": -1.962
      },
      "USDCHF": {
        "trades": 15,
        "win_rate": 60.0,
        "total_pnl": 1198.23,
        "total_r": 11.981
      },
      "EURGBP": {
        "trades": 9,
        "win_rate": 33.3,
        "total_pnl": 190.42,
        "total_r": 1.905
      },
      "EURJPY": {
        "trades": 10,
        "win_rate": 50.0,
        "total_pnl": 407.85,
        "total_r": 4.078
      },
      "GBPJPY": {
        "trades": 14,
        "win_rate": 57.1,
        "total_pnl": 927.41,
        "total_r": 9.275
      },
      "XAUUSD": {
        "trades": 9,
        "win_rate": 55.6,
        "total_pnl": 862.2,
        "total_r": 8.622
      }
    }
  },
  "equity_curve": [
    {
      "time": "2025-11-01T13:30:23",
      "equity": 10000.0
    },
    {
      "time": "2025-11-02T21:45:11",
      "equity": 9893.14
    },
    {
      "time": "2025-11-04T06:01:03",
      "equity": 9812.01
    },
    {
      "time": "2025-11-03T22:13:34",
      "equity": 10049.26
    },
    {
      "time": "2025-11-04T17:51:46",
      "equity": 9951.09
    },
    {
      "time": "2025-11-04T14:59:29",
      "equity": 10177.72
    },
    {
      "time": "2025-11-05T11:25:33",
      "equity": 10439.86
    },
    {
      "time": "2025-11-06T08:53:58",
      "equity": 10329.01
    },
    {
      "time": "2025-11-05T18:45:45",
      "equity": 10511.27
    },
    {
      "time": "2025-11-07T12:26:45",
      "equity": 10401.27
    },
    {
      "time": "2025-11-08T23:47:18",
      "equity": 10306.64
    },
    {
      "time": "2025-11-09T01:17:13",
      "equity": 10221.24
    },
    {
      "time": "2025-11-08T16:17:27",
      "equity": 10338.27
    },
    {
      "time": "2025-11-10T04:54:56",
      "equity": 10511.5
    },
    {
      "time": "2025-11-11T09:50:51",
      "equity": 10396.5
    },
    {
      "time": "2025-11-10T16:04:19",
      "equity": 10316.85
    },
    {
      "time": "2025-11-12T01:13:50",
      "equity": 10204.31
    },
    {
      "time": "2025-11-12T10:18:44",
      "equity": 10371.67
    },
    {
      "time": "2025-11-13T06:10:22",
      "equity": 10500.01
    },
    {
      "time": "2025-11-14T10:01:56",
      "equity": 10387.74
    },
    {
      "time": "2025-11-15T05:03:55",
      "equity": 10327.38
    },
    {
      "time": "2025-11-14T10:23:24",
      "equity": 10210.21
    },
    {
      "time": "2025-11-16T07:03:43",
      "equity": 10103.61
    },
    {
      "time": "2025-11-16T17:50:37",
      "equity": 10296.44
    },
    {
      "time": "2025-11-15T11:36:28",
      "equity": 10241.49
    },
    {
      "time": "2025-11-17T02:50:25",
      "equity": 10492.63
    },
    {
      "time": "2025-11-19T03:29:20",
      "equity": 10613.62
    },
    {
      "time": "2025-11-18T21:46:24",
      "equity": 10804.26
    },
    {
      "time": "2025-11-20T08:35:07",
      "equity": 10957.68
    },
    {
      "time": "2025-11-20T23:52:52",
      "equity": 11198.5
    },
    {
      "time": "2025-11-21T12:02:29",
      "equity": 11122.71
    },
    {
      "time": "2025-11-23T12:23:40",
      "equity": 11057.51
    },
    {
      "time": "2025-11-27T03:00:06",
      "equity": 10937.78
    },
    {
      "time": "2025-12-02T11:21:05",
      "equity": 11218.58
    },
    {
      "time": "2025-12-01T06:22:48",
      "equity": 11378.16
    },
    {
      "time": "2025-12-03T14:30:31",
      "equity": 11517.84
    },
    {
      "time": "2025-12-06T16:53:06",
      "equity": 11659.15
    },
    {
      "time": "2025-12-06T10:42:58",
      "equity": 11922.73
    },
    {
      "time": "2025-12-07T21:36:00",
      "equity": 11847.25
    },
    {
      "time": "2025-12-09T06:33:02",
      "equity": 11749.88
    },
    {
      "time": "2025-12-09T07:44:23",
      "equity": 11656.06
    },
    {
      "time": "2025-12-09T14:23:50",
      "equity": 11831.41
    },
    {
      "time": "2025-12-10T22:08:56",
      "equity": 12093.31
    },
    {
      "time": "2025-12-11T08:32:01",
      "equity": 11978.98
    },
    {
      "time": "2025-12-12T03:58:59",
      "equity": 12197.89
    },
    {
      "time": "2025-12-13T14:52:52",
      "equity": 12477.61
    },
    {
      "time": "2025-12-14T20:08:41",
      "equity": 12577.78
    },
    {
      "time": "2025-12-15T06:56:59",
      "equity": 12500.17
    },
    {
      "time": "2025-12-17T01:02:58",
      "equity": 12402.04
    },
    {
      "time": "2025-12-17T21:56:44",
      "equity": 12332.77
    },
    {
      "time": "2025-12-17T03:08:42",
      "equity": 12236.61
    },
    {
      "time": "2025-12-19T14:59:34",
      "equity": 12132.87
    },
    {
      "time": "2025-12-18T12:52:41",
      "equity": 12076.38
    },
    {
      "time": "2025-12-20T09:10:16",
      "equity": 12241.81
    },
    {
      "time": "2025-12-18T18:06:00",
      "equity": 12526.72
    },
    {
      "time": "2025-12-20T07:01:08",
      "equity": 12699.77
    },
    {
      "time": "2025-12-19T13:12:13",
      "equity": 12954.35
    },
    {
      "time": "2025-12-23T19:52:41",
      "equity": 12855.73
    },
    {
      "time": "2025-12-23T00:08:37",
      "equity": 13114.69
    },
    {
      "time": "2025-12-25T14:25:31",
      "equity": 13269.47
    },
    {
      "time": "2025-12-24T06:56:07",
      "equity": 13440.93
    },
    {
      "time": "2025-12-26T16:24:29",
      "equity": 13592.73
    },
    {
      "time": "2025-12-26T01:25:20",
      "equity": 13813.01
    },
    {
      "time": "2025-12-29T06:24:16",
      "equity": 13739.23
    },
    {
      "time": "2025-12-28T16:17:57",
      "equity": 13643.51
    },
    {
      "time": "2025-12-31T00:56:24",
      "equity": 13586.7
    },
    {
      "time": "2025-12-31T05:54:16",
      "equity": 13523.34
    },
    {
      "time": "2025-12-31T01:15:52",
      "equity": 13766.43
    },
    {
      "time": "2026-01-02T03:46:42",
      "equity": 13693.34
    },
    {
      "time": "2026-01-01T10:14:31",
      "equity": 13810.75
    },
    {
      "time": "2025-12-31T16:34:25",
      "equity": 13723.52
    },
    {
      "time": "2026-01-05T07:28:30",
      "equity": 13666.91
    },
    {
      "time": "2026-01-07T00:29:10",
      "equity": 13579.3
    },
    {
      "time": "2026-01-06T17:18:35",
      "equity": 13813.43
    },
    {
      "time": "2026-01-09T10:37:36",
      "equity": 13698.75
    },
    {
      "time": "2026-01-10T05:41:52",
      "equity": 13867.02
    },
    {
      "time": "2026-01-09T17:26:10",
      "equity": 14081.4
    },
    {
      "time": "2026-01-14T20:41:38",
      "equity": 14183.14
    },
    {
      "time": "2026-01-17T12:14:22",
      "equity": 14330.68
    },
    {
      "time": "2026-01-17T17:02:30",
      "equity": 14279.58
    },
    {
      "time": "2026-01-18T21:31:38",
      "equity": 14546.88
    },
    {
      "time": "2026-01-22T12:05:00",
      "equity": 14478.19
    },
    {
      "time": "2026-01-23T03:22:12",
      "equity": 14378.68
    },
    {
      "time": "2026-01-23T22:02:49",
      "equity": 14265.72
    },
    {
      "time": "2026-01-24T12:26:33",
      "equity": 14198.76
    },
    {
      "time": "2026-01-24T23:05:45",
      "equity": 14418.17
    },
    {
      "time": "2026-01-26T01:55:36",
      "equity": 14529.01
    },
    {
      "time": "2026-01-27T18:25:56",
      "equity": 14454.22
    },
    {
      "time": "2026-01-28T09:09:35",
      "equity": 14352.88
    },
    {
      "time": "2026-01-29T15:46:15",
      "equity": 14270.43
    },
    {
      "time": "2026-01-31T01:53:05",
      "equity": 14215.16
    },
    {
      "time": "2026-01-31T09:23:19",
      "equity": 14417.56
    },
    {
      "time": "2026-02-01T14:35:19",
      "equity": 14329.13
    },
    {
      "time": "2026-02-02T23:57:49",
      "equity": 14489.74
    },
    {
      "time": "2026-02-04T18:38:00",
      "equity": 14657.51
    },
    {
      "time": "2026-02-04T03:57:56",
      "equity": 14591.15
    },
    {
      "time": "2026-02-05T12:02:24",
      "equity": 14828.75
    },
    {
      "time": "2026-02-10T11:29:04",
      "equity": 15089.04
    },
    {
      "time": "2026-02-09T17:53:46",
      "equity": 15320.38
    },
    {
      "time": "2026-02-10T01:45:13",
      "equity": 15515.27
    },
    {
      "time": "2026-02-10T14:09:50",
      "equity": 15457.41
    },
    {
      "time": "2026-02-11T13:29:10",
      "equity": 15727.44
    },
    {
      "time": "2026-02-12T19:26:45",
      "equity": 15961.47
    },
    {
      "time": "2026-02-12T19:25:01",
      "equity": 15908.77
    },
    {
      "time": "2026-02-15T13:53:38",
      "equity": 16035.16
    },
    {
      "time": "2026-02-20T12:51:18",
      "equity": 16176.85
    },
    {
      "time": "2026-02-20T23:38:33",
      "equity": 16444.03
    },
    {
      "time": "2026-02-20T00:56:42",
      "equity": 16646.7
    },
    {
      "time": "2026-02-22T14:31:08",
      "equity": 16571.97
    },
    {
      "time": "2026-02-26T06:14:23",
      "equity": 16498.32
    },
    {
      "time": "2026-02-28T03:47:09",
      "equity": 16615.36
    },
    {
      "time": "2026-03-02T03:56:03",
      "equity": 16531.98
    },
    {
      "time": "2026-03-03T23:05:47",
      "equity": 16457.77
    },
    {
      "time": "2026-03-04T14:58:08",
      "equity": 16721.25
    },
    {
      "time": "2026-03-04T09:40:17",
      "equity": 16658.02
    },
    {
      "time": "2026-03-06T07:02:27",
      "equity": 16550.57
    },
    {
      "time": "2026-03-06T21:24:37",
      "equity": 16493.42
    },
    {
      "time": "2026-03-06T15:43:20",
      "equity": 16380.51
    },
    {
      "time": "2026-03-09T04:52:54",
      "equity": 16270.19
    },
    {
      "time": "2026-03-10T10:55:27",
      "equity": 16172.75
    },
    {
      "time": "2026-03-10T20:57:33",
      "equity": 16113.25
    }
  ],
  "trades": [
    {
      "id": 120,
      "symbol": "USDCHF",
      "strategy": "macd_stochastic",
      "direction": "sell",
      "entry_time": "2025-11-01T13:30:23",
      "exit_time": "2025-11-02T21:45:11",
      "entry_price": 0.90467,
      "exit_price": 0.9076,
      "sl_price": 0.9076,
      "tp_price": 0.89482,
      "lots": 0.34,
      "pnl_usd": -106.86,
      "pnl_r": -1.069,
      "exit_reason": "sl",
      "duration_bars": 386
    },
    {
      "id": 33,
      "symbol": "USDJPY",
      "strategy": "momentum_pullback",
      "direction": "sell",
      "entry_time": "2025-11-02T22:31:28",
      "exit_time": "2025-11-04T06:01:03",
      "entry_price": 148.59334,
      "exit_price": 148.7775,
      "sl_price": 148.75933,
      "tp_price": 148.00589,
      "lots": 0.67,
      "pnl_usd": -81.13,
      "pnl_r": -0.811,
      "exit_reason": "sl",
      "duration_bars": 377
    },
    {
      "id": 20,
      "symbol": "USDJPY",
      "strategy": "macd_stochastic",
      "direction": "buy",
      "entry_time": "2025-11-03T12:29:50",
      "exit_time": "2025-11-03T22:13:34",
      "entry_price": 148.51041,
      "exit_price": 149.20956,
      "sl_price": 148.25456,
      "tp_price": 149.20956,
      "lots": 0.43,
      "pnl_usd": 237.25,
      "pnl_r": 2.373,
      "exit_reason": "tp",
      "duration_bars": 116
    },
    {
      "id": 71,
      "symbol": "USDCHF",
      "strategy": "komjathy",
      "direction": "sell",
      "entry_time": "2025-11-03T15:16:14",
      "exit_time": "2025-11-04T17:51:46",
      "entry_price": 0.90567,
      "exit_price": 0.90796,
      "sl_price": 0.90797,
      "tp_price": 0.89714,
      "lots": 0.43,
      "pnl_usd": -98.17,
      "pnl_r": -0.982,
      "exit_reason": "sl",
      "duration_bars": 319
    },
    {
      "id": 90,
      "symbol": "AUDUSD",
      "strategy": "momentum_pullback",
      "direction": "sell",
      "entry_time": "2025-11-04T11:07:42",
      "exit_time": "2025-11-04T14:59:29",
      "entry_price": 0.64524,
      "exit_price": 0.63978,
      "sl_price": 0.64708,
      "tp_price": 0.63978,
      "lots": 0.54,
      "pnl_usd": 226.63,
      "pnl_r": 2.266,
      "exit_reason": "tp",
      "duration_bars": 46
    },
    {
      "id": 79,
      "symbol": "USDCHF",
      "strategy": "komjathy",
      "direction": "sell",
      "entry_time": "2025-11-04T15:56:58",
      "exit_time": "2025-11-05T11:25:33",
      "entry_price": 0.90581,
      "exit_price": 0.9009,
      "sl_price": 0.90746,
      "tp_price": 0.9009,
      "lots": 0.6,
      "pnl_usd": 262.14,
      "pnl_r": 2.621,
      "exit_reason": "tp",
      "duration_bars": 233
    },
    {
      "id": 114,
      "symbol": "GBPJPY",
      "strategy": "macd_stochastic",
      "direction": "buy",
      "entry_time": "2025-11-05T00:54:53",
      "exit_time": "2025-11-06T08:53:58",
      "entry_price": 188.75077,
      "exit_price": 188.49678,
      "sl_price": 188.48516,
      "tp_price": 189.73839,
      "lots": 0.42,
      "pnl_usd": -110.85,
      "pnl_r": -1.108,
      "exit_reason": "sl",
      "duration_bars": 383
    },
    {
      "id": 57,
      "symbol": "GBPUSD",
      "strategy": "macd_stochastic",
      "direction": "sell",
      "entry_time": "2025-11-05T09:08:17",
      "exit_time": "2025-11-05T18:45:45",
      "entry_price": 1.26426,
      "exit_price": 1.25445,
      "sl_price": 1.26743,
      "tp_price": 1.25445,
      "lots": 0.32,
      "pnl_usd": 182.26,
      "pnl_r": 1.823,
      "exit_reason": "tp",
      "duration_bars": 115
    },
    {
      "id": 78,
      "symbol": "EURGBP",
      "strategy": "komjathy",
      "direction": "buy",
      "entry_time": "2025-11-06T06:23:33",
      "exit_time": "2025-11-07T12:26:45",
      "entry_price": 0.85499,
      "exit_price": 0.85288,
      "sl_price": 0.85283,
      "tp_price": 0.86313,
      "lots": 0.46,
      "pnl_usd": -110.0,
      "pnl_r": -1.1,
      "exit_reason": "sl",
      "duration_bars": 360
    },
    {
      "id": 36,
      "symbol": "EURGBP",
      "strategy": "macd_stochastic",
      "direction": "buy",
      "entry_time": "2025-11-07T15:09:09",
      "exit_time": "2025-11-08T23:47:18",
      "entry_price": 0.85481,
      "exit_price": 0.85214,
      "sl_price": 0.8523,
      "tp_price": 0.85858,
      "lots": 0.4,
      "pnl_usd": -94.63,
      "pnl_r": -0.946,
      "exit_reason": "sl",
      "duration_bars": 391
    },
    {
      "id": 9,
      "symbol": "EURGBP",
      "strategy": "macd_stochastic",
      "direction": "sell",
      "entry_time": "2025-11-07T17:00:44",
      "exit_time": "2025-11-09T01:17:13",
      "entry_price": 0.85501,
      "exit_price": 0.857,
      "sl_price": 0.85714,
      "tp_price": 0.84735,
      "lots": 0.47,
      "pnl_usd": -85.4,
      "pnl_r": -0.854,
      "exit_reason": "sl",
      "duration_bars": 387
    },
    {
      "id": 38,
      "symbol": "EURJPY",
      "strategy": "komjathy",
      "direction": "sell",
      "entry_time": "2025-11-08T08:11:16",
      "exit_time": "2025-11-08T16:17:27",
      "entry_price": 161.11657,
      "exit_price": 159.76082,
      "sl_price": 161.47371,
      "tp_price": 159.76082,
      "lots": 0.31,
      "pnl_usd": 117.03,
      "pnl_r": 1.17,
      "exit_reason": "tp",
      "duration_bars": 97
    },
    {
      "id": 85,
      "symbol": "GBPJPY",
      "strategy": "momentum_pullback",
      "direction": "buy",
      "entry_time": "2025-11-09T08:28:13",
      "exit_time": "2025-11-10T04:54:56",
      "entry_price": 188.76265,
      "exit_price": 189.32503,
      "sl_price": 188.43926,
      "tp_price": 189.32503,
      "lots": 0.34,
      "pnl_usd": 173.23,
      "pnl_r": 1.732,
      "exit_reason": "tp",
      "duration_bars": 245
    },
    {
      "id": 82,
      "symbol": "GBPUSD",
      "strategy": "komjathy",
      "direction": "sell",
      "entry_time": "2025-11-09T14:06:39",
      "exit_time": "2025-11-11T09:50:51",
      "entry_price": 1.2651,
      "exit_price": 1.26907,
      "sl_price": 1.26906,
      "tp_price": 1.25382,
      "lots": 0.25,
      "pnl_usd": -115.0,
      "pnl_r": -1.15,
      "exit_reason": "sl",
      "duration_bars": 524
    },
    {
      "id": 26,
      "symbol": "GBPJPY",
      "strategy": "macd_stochastic",
      "direction": "buy",
      "entry_time": "2025-11-10T07:24:25",
      "exit_time": "2025-11-10T16:04:19",
      "entry_price": 188.68561,
      "exit_price": 188.43583,
      "sl_price": 188.43718,
      "tp_price": 189.47442,
      "lots": 0.45,
      "pnl_usd": -79.65,
      "pnl_r": -0.796,
      "exit_reason": "sl",
      "duration_bars": 103
    },
    {
      "id": 56,
      "symbol": "USDCAD",
      "strategy": "momentum_pullback",
      "direction": "sell",
      "entry_time": "2025-11-10T20:32:57",
      "exit_time": "2025-11-12T01:13:50",
      "entry_price": 1.35942,
      "exit_price": 1.3624,
      "sl_price": 1.36253,
      "tp_price": 1.34786,
      "lots": 0.32,
      "pnl_usd": -112.54,
      "pnl_r": -1.125,
      "exit_reason": "trailing",
      "duration_bars": 344
    },
    {
      "id": 92,
      "symbol": "GBPUSD",
      "strategy": "komjathy",
      "direction": "buy",
      "entry_time": "2025-11-11T08:17:07",
      "exit_time": "2025-11-12T10:18:44",
      "entry_price": 1.26409,
      "exit_price": 1.2722,
      "sl_price": 1.26114,
      "tp_price": 1.2722,
      "lots": 0.34,
      "pnl_usd": 167.36,
      "pnl_r": 1.674,
      "exit_reason": "tp",
      "duration_bars": 312
    },
    {
      "id": 1,
      "symbol": "GBPJPY",
      "strategy": "momentum_pullback",
      "direction": "sell",
      "entry_time": "2025-11-11T16:54:13",
      "exit_time": "2025-11-13T06:10:22",
      "entry_price": 188.73486,
      "exit_price": 187.46406,
      "sl_price": 189.12246,
      "tp_price": 187.46406,
      "lots": 0.29,
      "pnl_usd": 128.34,
      "pnl_r": 1.283,
      "exit_reason": "tp",
      "duration_bars": 447
    },
    {
      "id": 34,
      "symbol": "EURUSD",
      "strategy": "momentum_pullback",
      "direction": "sell",
      "entry_time": "2025-11-13T03:21:22",
      "exit_time": "2025-11-14T10:01:56",
      "entry_price": 1.08534,
      "exit_price": 1.08879,
      "sl_price": 1.08869,
      "tp_price": 1.07909,
      "lots": 0.3,
      "pnl_usd": -112.27,
      "pnl_r": -1.123,
      "exit_reason": "sl",
      "duration_bars": 368
    },
    {
      "id": 60,
      "symbol": "GBPUSD",
      "strategy": "macd_stochastic",
      "direction": "sell",
      "entry_time": "2025-11-13T10:27:24",
      "exit_time": "2025-11-15T05:03:55",
      "entry_price": 1.26493,
      "exit_price": 1.26767,
      "sl_price": 1.26773,
      "tp_price": 1.2595,
      "lots": 0.36,
      "pnl_usd": -60.36,
      "pnl_r": -0.604,
      "exit_reason": "sl",
      "duration_bars": 511
    },
    {
      "id": 105,
      "symbol": "USDCHF",
      "strategy": "macd_stochastic",
      "direction": "buy",
      "entry_time": "2025-11-13T23:06:02",
      "exit_time": "2025-11-14T10:23:24",
      "entry_price": 0.90401,
      "exit_price": 0.90008,
      "sl_price": 0.90022,
      "tp_price": 0.91884,
      "lots": 0.26,
      "pnl_usd": -117.17,
      "pnl_r": -1.172,
      "exit_reason": "sl",
      "duration_bars": 135
    },
    {
      "id": 83,
      "symbol": "AUDUSD",
      "strategy": "momentum_pullback",
      "direction": "sell",
      "entry_time": "2025-11-14T08:46:41",
      "exit_time": "2025-11-16T07:03:43",
      "entry_price": 0.6451,
      "exit_price": 0.649,
      "sl_price": 0.64894,
      "tp_price": 0.63883,
      "lots": 0.26,
      "pnl_usd": -106.6,
      "pnl_r": -1.066,
      "exit_reason": "trailing",
      "duration_bars": 555
    },
    {
      "id": 109,
      "symbol": "USDCHF",
      "strategy": "macd_stochastic",
      "direction": "sell",
      "entry_time": "2025-11-15T00:54:14",
      "exit_time": "2025-11-16T17:50:37",
      "entry_price": 0.90591,
      "exit_price": 0.89777,
      "sl_price": 0.90861,
      "tp_price": 0.89777,
      "lots": 0.37,
      "pnl_usd": 192.83,
      "pnl_r": 1.928,
      "exit_reason": "tp",
      "duration_bars": 491
    },
    {
      "id": 3,
      "symbol": "AUDUSD",
      "strategy": "momentum_pullback",
      "direction": "sell",
      "entry_time": "2025-11-15T05:11:45",
      "exit_time": "2025-11-15T11:36:28",
      "entry_price": 0.64488,
      "exit_price": 0.64729,
      "sl_price": 0.64731,
      "tp_price": 0.63586,
      "lots": 0.41,
      "pnl_usd": -54.95,
      "pnl_r": -0.549,
      "exit_reason": "sl",
      "duration_bars": 76
    },
    {
      "id": 19,
      "symbol": "XAUUSD",
      "strategy": "momentum_pullback",
      "direction": "sell",
      "entry_time": "2025-11-15T12:32:53",
      "exit_time": "2025-11-17T02:50:25",
      "entry_price": 2328.20741,
      "exit_price": 2285.55569,
      "sl_price": 2349.5958,
      "tp_price": 2285.55569,
      "lots": 0.47,
      "pnl_usd": 251.14,
      "pnl_r": 2.511,
      "exit_reason": "tp",
      "duration_bars": 459
    },
    {
      "id": 81,
      "symbol": "GBPUSD",
      "strategy": "momentum_pullback",
      "direction": "sell",
      "entry_time": "2025-11-18T05:07:15",
      "exit_time": "2025-11-19T03:29:20",
      "entry_price": 1.26496,
      "exit_price": 1.25731,
      "sl_price": 1.26862,
      "tp_price": 1.25731,
      "lots": 0.27,
      "pnl_usd": 120.99,
      "pnl_r": 1.21,
      "exit_reason": "tp",
      "duration_bars": 268
    },
    {
      "id": 18,
      "symbol": "GBPUSD",
      "strategy": "komjathy",
      "direction": "sell",
      "entry_time": "2025-11-18T10:19:56",
      "exit_time": "2025-11-18T21:46:24",
      "entry_price": 1.26572,
      "exit_price": 1.25705,
      "sl_price": 1.26843,
      "tp_price": 1.25705,
      "lots": 0.37,
      "pnl_usd": 190.64,
      "pnl_r": 1.906,
      "exit_reason": "tp",
      "duration_bars": 137
    },
    {
      "id": 35,
      "symbol": "GBPUSD",
      "strategy": "macd_stochastic",
      "direction": "sell",
      "entry_time": "2025-11-18T14:38:23",
      "exit_time": "2025-11-20T08:35:07",
      "entry_price": 1.26461,
      "exit_price": 1.25837,
      "sl_price": 1.26676,
      "tp_price": 1.25837,
      "lots": 0.46,
      "pnl_usd": 153.42,
      "pnl_r": 1.534,
      "exit_reason": "tp",
      "duration_bars": 503
    },
    {
      "id": 25,
      "symbol": "AUDUSD",
      "strategy": "komjathy",
      "direction": "sell",
      "entry_time": "2025-11-20T07:24:37",
      "exit_time": "2025-11-20T23:52:52",
      "entry_price": 0.64432,
      "exit_price": 0.63614,
      "sl_price": 0.64739,
      "tp_price": 0.63614,
      "lots": 0.33,
      "pnl_usd": 240.82,
      "pnl_r": 2.408,
      "exit_reason": "tp",
      "duration_bars": 197
    },
    {
      "id": 100,
      "symbol": "EURJPY",
      "strategy": "macd_stochastic",
      "direction": "sell",
      "entry_time": "2025-11-20T15:51:06",
      "exit_time": "2025-11-21T12:02:29",
      "entry_price": 161.27328,
      "exit_price": 161.42287,
      "sl_price": 161.43218,
      "tp_price": 161.01951,
      "lots": 0.7,
      "pnl_usd": -75.79,
      "pnl_r": -0.758,
      "exit_reason": "sl",
      "duration_bars": 242
    },
    {
      "id": 106,
      "symbol": "EURUSD",
      "strategy": "komjathy",
      "direction": "sell",
      "entry_time": "2025-11-21T23:40:00",
      "exit_time": "2025-11-23T12:23:40",
      "entry_price": 1.08549,
      "exit_price": 1.08835,
      "sl_price": 1.08852,
      "tp_price": 1.07769,
      "lots": 0.33,
      "pnl_usd": -65.2,
      "pnl_r": -0.652,
      "exit_reason": "sl",
      "duration_bars": 440
    },
    {
      "id": 117,
      "symbol": "AUDUSD",
      "strategy": "momentum_pullback",
      "direction": "sell",
      "entry_time": "2025-11-26T13:35:41",
      "exit_time": "2025-11-27T03:00:06",
      "entry_price": 0.64508,
      "exit_price": 0.64798,
      "sl_price": 0.64813,
      "tp_price": 0.63929,
      "lots": 0.33,
      "pnl_usd": -119.73,
      "pnl_r": -1.197,
      "exit_reason": "sl",
      "duration_bars": 160
    },
    {
      "id": 104,
      "symbol": "EURGBP",
      "strategy": "komjathy",
      "direction": "buy",
      "entry_time": "2025-11-30T13:15:11",
      "exit_time": "2025-12-02T11:21:05",
      "entry_price": 0.85413,
      "exit_price": 0.85981,
      "sl_price": 0.85234,
      "tp_price": 0.85981,
      "lots": 0.56,
      "pnl_usd": 280.8,
      "pnl_r": 2.808,
      "exit_reason": "tp",
      "duration_bars": 553
    },
    {
      "id": 50,
      "symbol": "USDCHF",
      "strategy": "momentum_pullback",
      "direction": "buy",
      "entry_time": "2025-12-01T01:54:48",
      "exit_time": "2025-12-01T06:22:48",
      "entry_price": 0.90446,
      "exit_price": 0.9112,
      "sl_price": 0.90064,
      "tp_price": 0.9112,
      "lots": 0.26,
      "pnl_usd": 159.58,
      "pnl_r": 1.596,
      "exit_reason": "tp",
      "duration_bars": 53
    },
    {
      "id": 31,
      "symbol": "GBPUSD",
      "strategy": "macd_stochastic",
      "direction": "buy",
      "entry_time": "2025-12-03T09:07:42",
      "exit_time": "2025-12-03T14:30:31",
      "entry_price": 1.2651,
      "exit_price": 1.27044,
      "sl_price": 1.26265,
      "tp_price": 1.27044,
      "lots": 0.41,
      "pnl_usd": 139.68,
      "pnl_r": 1.397,
      "exit_reason": "tp",
      "duration_bars": 64
    },
    {
      "id": 94,
      "symbol": "USDCAD",
      "strategy": "momentum_pullback",
      "direction": "sell",
      "entry_time": "2025-12-05T13:36:06",
      "exit_time": "2025-12-06T16:53:06",
      "entry_price": 1.35997,
      "exit_price": 1.35649,
      "sl_price": 1.36218,
      "tp_price": 1.35649,
      "lots": 0.45,
      "pnl_usd": 141.31,
      "pnl_r": 1.413,
      "exit_reason": "tp",
      "duration_bars": 327
    },
    {
      "id": 72,
      "symbol": "GBPJPY",
      "strategy": "macd_stochastic",
      "direction": "sell",
      "entry_time": "2025-12-05T20:07:06",
      "exit_time": "2025-12-06T10:42:58",
      "entry_price": 188.61071,
      "exit_price": 188.01851,
      "sl_price": 188.77009,
      "tp_price": 188.01851,
      "lots": 0.7,
      "pnl_usd": 263.58,
      "pnl_r": 2.636,
      "exit_reason": "tp",
      "duration_bars": 175
    },
    {
      "id": 27,
      "symbol": "GBPUSD",
      "strategy": "momentum_pullback",
      "direction": "sell",
      "entry_time": "2025-12-06T05:19:53",
      "exit_time": "2025-12-07T21:36:00",
      "entry_price": 1.26483,
      "exit_price": 1.26843,
      "sl_price": 1.26843,
      "tp_price": 1.25307,
      "lots": 0.28,
      "pnl_usd": -75.48,
      "pnl_r": -0.755,
      "exit_reason": "trailing",
      "duration_bars": 483
    },
    {
      "id": 13,
      "symbol": "GBPUSD",
      "strategy": "komjathy",
      "direction": "buy",
      "entry_time": "2025-12-07T07:41:06",
      "exit_time": "2025-12-09T06:33:02",
      "entry_price": 1.26409,
      "exit_price": 1.26106,
      "sl_price": 1.2611,
      "tp_price": 1.2719,
      "lots": 0.33,
      "pnl_usd": -97.37,
      "pnl_r": -0.974,
      "exit_reason": "sl",
      "duration_bars": 562
    },
    {
      "id": 101,
      "symbol": "GBPUSD",
      "strategy": "momentum_pullback",
      "direction": "sell",
      "entry_time": "2025-12-07T15:22:39",
      "exit_time": "2025-12-09T07:44:23",
      "entry_price": 1.26593,
      "exit_price": 1.26774,
      "sl_price": 1.26758,
      "tp_price": 1.26003,
      "lots": 0.61,
      "pnl_usd": -93.82,
      "pnl_r": -0.938,
      "exit_reason": "trailing",
      "duration_bars": 484
    },
    {
      "id": 93,
      "symbol": "EURGBP",
      "strategy": "macd_stochastic",
      "direction": "buy",
      "entry_time": "2025-12-08T02:20:28",
      "exit_time": "2025-12-09T14:23:50",
      "entry_price": 0.85537,
      "exit_price": 0.86175,
      "sl_price": 0.85228,
      "tp_price": 0.86175,
      "lots": 0.32,
      "pnl_usd": 175.35,
      "pnl_r": 1.754,
      "exit_reason": "tp",
      "duration_bars": 432
    },
    {
      "id": 49,
      "symbol": "AUDUSD",
      "strategy": "macd_stochastic",
      "direction": "buy",
      "entry_time": "2025-12-09T04:33:16",
      "exit_time": "2025-12-10T22:08:56",
      "entry_price": 0.64557,
      "exit_price": 0.64863,
      "sl_price": 0.64406,
      "tp_price": 0.64863,
      "lots": 0.66,
      "pnl_usd": 261.9,
      "pnl_r": 2.619,
      "exit_reason": "tp",
      "duration_bars": 499
    },
    {
      "id": 58,
      "symbol": "EURUSD",
      "strategy": "macd_stochastic",
      "direction": "buy",
      "entry_time": "2025-12-09T12:19:27",
      "exit_time": "2025-12-11T08:32:01",
      "entry_price": 1.08494,
      "exit_price": 1.08326,
      "sl_price": 1.08336,
      "tp_price": 1.089,
      "lots": 0.63,
      "pnl_usd": -114.33,
      "pnl_r": -1.143,
      "exit_reason": "sl",
      "duration_bars": 530
    },
    {
      "id": 66,
      "symbol": "EURUSD",
      "strategy": "komjathy",
      "direction": "sell",
      "entry_time": "2025-12-10T06:45:03",
      "exit_time": "2025-12-12T03:58:59",
      "entry_price": 1.08507,
      "exit_price": 1.07989,
      "sl_price": 1.08694,
      "tp_price": 1.07989,
      "lots": 0.54,
      "pnl_usd": 218.91,
      "pnl_r": 2.189,
      "exit_reason": "tp",
      "duration_bars": 542
    },
    {
      "id": 28,
      "symbol": "AUDUSD",
      "strategy": "momentum_pullback",
      "direction": "sell",
      "entry_time": "2025-12-12T01:53:07",
      "exit_time": "2025-12-13T14:52:52",
      "entry_price": 0.64468,
      "exit_price": 0.64032,
      "sl_price": 0.64618,
      "tp_price": 0.64032,
      "lots": 0.67,
      "pnl_usd": 279.72,
      "pnl_r": 2.797,
      "exit_reason": "tp",
      "duration_bars": 443
    },
    {
      "id": 115,
      "symbol": "USDJPY",
      "strategy": "momentum_pullback",
      "direction": "sell",
      "entry_time": "2025-12-14T00:26:13",
      "exit_time": "2025-12-14T20:08:41",
      "entry_price": 148.444,
      "exit_price": 147.59303,
      "sl_price": 148.68208,
      "tp_price": 147.59303,
      "lots": 0.47,
      "pnl_usd": 100.17,
      "pnl_r": 1.002,
      "exit_reason": "tp",
      "duration_bars": 236
    },
    {
      "id": 89,
      "symbol": "EURJPY",
      "strategy": "macd_stochastic",
      "direction": "buy",
      "entry_time": "2025-12-14T19:58:52",
      "exit_time": "2025-12-15T06:56:59",
      "entry_price": 161.28812,
      "exit_price": 160.93492,
      "sl_price": 160.92223,
      "tp_price": 162.3269,
      "lots": 0.3,
      "pnl_usd": -77.61,
      "pnl_r": -0.776,
      "exit_reason": "sl",
      "duration_bars": 131
    },
    {
      "id": 110,
      "symbol": "USDCHF",
      "strategy": "momentum_pullback",
      "direction": "sell",
      "entry_time": "2025-12-15T09:05:11",
      "exit_time": "2025-12-17T01:02:58",
      "entry_price": 0.905,
      "exit_price": 0.90891,
      "sl_price": 0.90891,
      "tp_price": 0.89765,
      "lots": 0.26,
      "pnl_usd": -98.13,
      "pnl_r": -0.981,
      "exit_reason": "sl",
      "duration_bars": 479
    },
    {
      "id": 8,
      "symbol": "EURGBP",
      "strategy": "komjathy",
      "direction": "buy",
      "entry_time": "2025-12-16T13:18:41",
      "exit_time": "2025-12-17T21:56:44",
      "entry_price": 0.85568,
      "exit_price": 0.85195,
      "sl_price": 0.85202,
      "tp_price": 0.86132,
      "lots": 0.27,
      "pnl_usd": -69.27,
      "pnl_r": -0.693,
      "exit_reason": "sl",
      "duration_bars": 391
    },
    {
      "id": 59,
      "symbol": "USDJPY",
      "strategy": "momentum_pullback",
      "direction": "sell",
      "entry_time": "2025-12-17T00:27:47",
      "exit_time": "2025-12-17T03:08:42",
      "entry_price": 148.54993,
      "exit_price": 148.81738,
      "sl_price": 148.82074,
      "tp_price": 147.96698,
      "lots": 0.41,
      "pnl_usd": -96.16,
      "pnl_r": -0.962,
      "exit_reason": "sl",
      "duration_bars": 32
    },
    {
      "id": 75,
      "symbol": "EURUSD",
      "strategy": "momentum_pullback",
      "direction": "sell",
      "entry_time": "2025-12-17T19:52:48",
      "exit_time": "2025-12-19T14:59:34",
      "entry_price": 1.08453,
      "exit_price": 1.08702,
      "sl_price": 1.08703,
      "tp_price": 1.07613,
      "lots": 0.4,
      "pnl_usd": -103.74,
      "pnl_r": -1.037,
      "exit_reason": "sl",
      "duration_bars": 517
    },
    {
      "id": 47,
      "symbol": "GBPJPY",
      "strategy": "komjathy",
      "direction": "buy",
      "entry_time": "2025-12-18T05:51:43",
      "exit_time": "2025-12-18T12:52:41",
      "entry_price": 188.78592,
      "exit_price": 188.54843,
      "sl_price": 188.53258,
      "tp_price": 189.45692,
      "lots": 0.44,
      "pnl_usd": -56.49,
      "pnl_r": -0.565,
      "exit_reason": "trailing",
      "duration_bars": 84
    },
    {
      "id": 24,
      "symbol": "AUDUSD",
      "strategy": "komjathy",
      "direction": "sell",
      "entry_time": "2025-12-18T15:06:52",
      "exit_time": "2025-12-20T09:10:16",
      "entry_price": 0.64533,
      "exit_price": 0.63959,
      "sl_price": 0.64826,
      "tp_price": 0.63959,
      "lots": 0.34,
      "pnl_usd": 165.43,
      "pnl_r": 1.654,
      "exit_reason": "tp",
      "duration_bars": 504
    },
    {
      "id": 11,
      "symbol": "USDJPY",
      "strategy": "komjathy",
      "direction": "buy",
      "entry_time": "2025-12-18T15:50:49",
      "exit_time": "2025-12-18T18:06:00",
      "entry_price": 148.54456,
      "exit_price": 148.9668,
      "sl_price": 148.39227,
      "tp_price": 148.9668,
      "lots": 0.73,
      "pnl_usd": 284.91,
      "pnl_r": 2.849,
      "exit_reason": "tp",
      "duration_bars": 27
    },
    {
      "id": 4,
      "symbol": "USDCHF",
      "strategy": "komjathy",
      "direction": "sell",
      "entry_time": "2025-12-18T17:36:10",
      "exit_time": "2025-12-20T07:01:08",
      "entry_price": 0.90469,
      "exit_price": 0.89549,
      "sl_price": 0.90722,
      "tp_price": 0.89549,
      "lots": 0.4,
      "pnl_usd": 173.05,
      "pnl_r": 1.731,
      "exit_reason": "tp",
      "duration_bars": 448
    },
    {
      "id": 55,
      "symbol": "EURUSD",
      "strategy": "momentum_pullback",
      "direction": "sell",
      "entry_time": "2025-12-19T10:57:27",
      "exit_time": "2025-12-19T13:12:13",
      "entry_price": 1.08545,
      "exit_price": 1.08162,
      "sl_price": 1.08792,
      "tp_price": 1.08162,
      "lots": 0.41,
      "pnl_usd": 254.58,
      "pnl_r": 2.546,
      "exit_reason": "tp",
      "duration_bars": 26
    },
    {
      "id": 116,
      "symbol": "USDCHF",
      "strategy": "macd_stochastic",
      "direction": "buy",
      "entry_time": "2025-12-22T00:40:09",
      "exit_time": "2025-12-23T19:52:41",
      "entry_price": 0.9045,
      "exit_price": 0.90282,
      "sl_price": 0.90286,
      "tp_price": 0.90908,
      "lots": 0.61,
      "pnl_usd": -98.62,
      "pnl_r": -0.986,
      "exit_reason": "trailing",
      "duration_bars": 518
    },
    {
      "id": 113,
      "symbol": "XAUUSD",
      "strategy": "momentum_pullback",
      "direction": "buy",
      "entry_time": "2025-12-22T15:29:11",
      "exit_time": "2025-12-23T00:08:37",
      "entry_price": 2325.23999,
      "exit_price": 2373.40659,
      "sl_price": 2295.12329,
      "tp_price": 2373.40659,
      "lots": 0.33,
      "pnl_usd": 258.96,
      "pnl_r": 2.59,
      "exit_reason": "tp",
      "duration_bars": 103
    },
    {
      "id": 42,
      "symbol": "GBPJPY",
      "strategy": "macd_stochastic",
      "direction": "sell",
      "entry_time": "2025-12-23T16:11:05",
      "exit_time": "2025-12-25T14:25:31",
      "entry_price": 188.63721,
      "exit_price": 187.9271,
      "sl_price": 188.86766,
      "tp_price": 187.9271,
      "lots": 0.48,
      "pnl_usd": 154.78,
      "pnl_r": 1.548,
      "exit_reason": "tp",
      "duration_bars": 554
    },
    {
      "id": 61,
      "symbol": "EURUSD",
      "strategy": "momentum_pullback",
      "direction": "buy",
      "entry_time": "2025-12-24T00:23:38",
      "exit_time": "2025-12-24T06:56:07",
      "entry_price": 1.08485,
      "exit_price": 1.09747,
      "sl_price": 1.08126,
      "tp_price": 1.09747,
      "lots": 0.28,
      "pnl_usd": 171.46,
      "pnl_r": 1.715,
      "exit_reason": "tp",
      "duration_bars": 78
    },
    {
      "id": 30,
      "symbol": "USDCAD",
      "strategy": "komjathy",
      "direction": "buy",
      "entry_time": "2025-12-24T23:25:57",
      "exit_time": "2025-12-26T16:24:29",
      "entry_price": 1.36074,
      "exit_price": 1.36389,
      "sl_price": 1.35917,
      "tp_price": 1.36389,
      "lots": 0.64,
      "pnl_usd": 151.8,
      "pnl_r": 1.518,
      "exit_reason": "tp",
      "duration_bars": 491
    },
    {
      "id": 32,
      "symbol": "EURUSD",
      "strategy": "momentum_pullback",
      "direction": "sell",
      "entry_time": "2025-12-25T10:41:11",
      "exit_time": "2025-12-26T01:25:20",
      "entry_price": 1.08508,
      "exit_price": 1.07458,
      "sl_price": 1.08811,
      "tp_price": 1.07458,
      "lots": 0.33,
      "pnl_usd": 220.28,
      "pnl_r": 2.203,
      "exit_reason": "tp",
      "duration_bars": 176
    },
    {
      "id": 46,
      "symbol": "GBPJPY",
      "strategy": "komjathy",
      "direction": "buy",
      "entry_time": "2025-12-28T05:33:09",
      "exit_time": "2025-12-29T06:24:16",
      "entry_price": 188.67957,
      "exit_price": 188.41439,
      "sl_price": 188.41461,
      "tp_price": 189.18643,
      "lots": 0.42,
      "pnl_usd": -73.78,
      "pnl_r": -0.738,
      "exit_reason": "sl",
      "duration_bars": 298
    },
    {
      "id": 91,
      "symbol": "USDJPY",
      "strategy": "macd_stochastic",
      "direction": "sell",
      "entry_time": "2025-12-28T12:46:42",
      "exit_time": "2025-12-28T16:17:57",
      "entry_price": 148.49486,
      "exit_price": 148.65568,
      "sl_price": 148.64908,
      "tp_price": 148.26007,
      "lots": 0.72,
      "pnl_usd": -95.72,
      "pnl_r": -0.957,
      "exit_reason": "sl",
      "duration_bars": 42
    },
    {
      "id": 43,
      "symbol": "EURJPY",
      "strategy": "komjathy",
      "direction": "buy",
      "entry_time": "2025-12-29T11:24:50",
      "exit_time": "2025-12-31T00:56:24",
      "entry_price": 161.17459,
      "exit_price": 160.92618,
      "sl_price": 160.93104,
      "tp_price": 161.96165,
      "lots": 0.46,
      "pnl_usd": -56.81,
      "pnl_r": -0.568,
      "exit_reason": "sl",
      "duration_bars": 450
    },
    {
      "id": 64,
      "symbol": "EURUSD",
      "strategy": "macd_stochastic",
      "direction": "sell",
      "entry_time": "2025-12-29T13:10:26",
      "exit_time": "2025-12-31T05:54:16",
      "entry_price": 1.08588,
      "exit_price": 1.08966,
      "sl_price": 1.0897,
      "tp_price": 1.07169,
      "lots": 0.26,
      "pnl_usd": -63.36,
      "pnl_r": -0.634,
      "exit_reason": "trailing",
      "duration_bars": 488
    },
    {
      "id": 10,
      "symbol": "EURGBP",
      "strategy": "momentum_pullback",
      "direction": "buy",
      "entry_time": "2025-12-30T01:52:59",
      "exit_time": "2025-12-31T01:15:52",
      "entry_price": 0.85451,
      "exit_price": 0.85835,
      "sl_price": 0.85277,
      "tp_price": 0.85835,
      "lots": 0.57,
      "pnl_usd": 243.09,
      "pnl_r": 2.431,
      "exit_reason": "tp",
      "duration_bars": 280
    },
    {
      "id": 45,
      "symbol": "XAUUSD",
      "strategy": "momentum_pullback",
      "direction": "buy",
      "entry_time": "2025-12-31T06:21:17",
      "exit_time": "2026-01-02T03:46:42",
      "entry_price": 2324.363,
      "exit_price": 2292.25684,
      "sl_price": 2290.96427,
      "tp_price": 2431.57026,
      "lots": 0.3,
      "pnl_usd": -73.09,
      "pnl_r": -0.731,
      "exit_reason": "sl",
      "duration_bars": 545
    },
    {
      "id": 62,
      "symbol": "GBPJPY",
      "strategy": "macd_stochastic",
      "direction": "buy",
      "entry_time": "2025-12-31T06:53:22",
      "exit_time": "2026-01-01T10:14:31",
      "entry_price": 188.63925,
      "exit_price": 189.30427,
      "sl_price": 188.28832,
      "tp_price": 189.30427,
      "lots": 0.32,
      "pnl_usd": 117.41,
      "pnl_r": 1.174,
      "exit_reason": "tp",
      "duration_bars": 328
    },
    {
      "id": 98,
      "symbol": "USDCAD",
      "strategy": "momentum_pullback",
      "direction": "buy",
      "entry_time": "2025-12-31T08:20:18",
      "exit_time": "2025-12-31T16:34:25",
      "entry_price": 1.3604,
      "exit_price": 1.35809,
      "sl_price": 1.35797,
      "tp_price": 1.36507,
      "lots": 0.41,
      "pnl_usd": -87.23,
      "pnl_r": -0.872,
      "exit_reason": "trailing",
      "duration_bars": 98
    },
    {
      "id": 39,
      "symbol": "USDJPY",
      "strategy": "momentum_pullback",
      "direction": "buy",
      "entry_time": "2026-01-04T06:46:00",
      "exit_time": "2026-01-05T07:28:30",
      "entry_price": 148.4935,
      "exit_price": 148.13072,
      "sl_price": 148.12044,
      "tp_price": 149.35161,
      "lots": 0.3,
      "pnl_usd": -56.61,
      "pnl_r": -0.566,
      "exit_reason": "trailing",
      "duration_bars": 296
    },
    {
      "id": 70,
      "symbol": "EURUSD",
      "strategy": "macd_stochastic",
      "direction": "sell",
      "entry_time": "2026-01-05T20:51:34",
      "exit_time": "2026-01-07T00:29:10",
      "entry_price": 1.08544,
      "exit_price": 1.08947,
      "sl_price": 1.08931,
      "tp_price": 1.07361,
      "lots": 0.26,
      "pnl_usd": -87.61,
      "pnl_r": -0.876,
      "exit_reason": "sl",
      "duration_bars": 331
    },
    {
      "id": 5,
      "symbol": "USDCHF",
      "strategy": "komjathy",
      "direction": "buy",
      "entry_time": "2026-01-06T01:33:01",
      "exit_time": "2026-01-06T17:18:35",
      "entry_price": 0.90498,
      "exit_price": 0.91075,
      "sl_price": 0.90279,
      "tp_price": 0.91075,
      "lots": 0.46,
      "pnl_usd": 234.13,
      "pnl_r": 2.341,
      "exit_reason": "tp",
      "duration_bars": 189
    },
    {
      "id": 21,
      "symbol": "USDCHF",
      "strategy": "macd_stochastic",
      "direction": "buy",
      "entry_time": "2026-01-07T22:47:50",
      "exit_time": "2026-01-09T10:37:36",
      "entry_price": 0.90433,
      "exit_price": 0.90146,
      "sl_price": 0.90151,
      "tp_price": 0.91436,
      "lots": 0.35,
      "pnl_usd": -114.68,
      "pnl_r": -1.147,
      "exit_reason": "sl",
      "duration_bars": 429
    },
    {
      "id": 96,
      "symbol": "USDCHF",
      "strategy": "macd_stochastic",
      "direction": "buy",
      "entry_time": "2026-01-09T08:54:04",
      "exit_time": "2026-01-10T05:41:52",
      "entry_price": 0.90575,
      "exit_price": 0.91081,
      "sl_price": 0.90394,
      "tp_price": 0.91081,
      "lots": 0.55,
      "pnl_usd": 168.27,
      "pnl_r": 1.683,
      "exit_reason": "tp",
      "duration_bars": 249
    },
    {
      "id": 107,
      "symbol": "EURJPY",
      "strategy": "komjathy",
      "direction": "sell",
      "entry_time": "2026-01-09T13:02:42",
      "exit_time": "2026-01-09T17:26:10",
      "entry_price": 161.20083,
      "exit_price": 160.56037,
      "sl_price": 161.57886,
      "tp_price": 160.56037,
      "lots": 0.29,
      "pnl_usd": 214.38,
      "pnl_r": 2.144,
      "exit_reason": "tp",
      "duration_bars": 52
    },
    {
      "id": 67,
      "symbol": "EURJPY",
      "strategy": "komjathy",
      "direction": "buy",
      "entry_time": "2026-01-13T01:21:37",
      "exit_time": "2026-01-14T20:41:38",
      "entry_price": 161.13314,
      "exit_price": 161.50557,
      "sl_price": 160.98085,
      "tp_price": 161.50557,
      "lots": 0.73,
      "pnl_usd": 101.74,
      "pnl_r": 1.017,
      "exit_reason": "tp",
      "duration_bars": 520
    },
    {
      "id": 44,
      "symbol": "USDCHF",
      "strategy": "macd_stochastic",
      "direction": "sell",
      "entry_time": "2026-01-15T19:01:25",
      "exit_time": "2026-01-17T12:14:22",
      "entry_price": 0.90515,
      "exit_price": 0.89317,
      "sl_price": 0.90826,
      "tp_price": 0.89317,
      "lots": 0.32,
      "pnl_usd": 147.54,
      "pnl_r": 1.475,
      "exit_reason": "tp",
      "duration_bars": 494
    },
    {
      "id": 119,
      "symbol": "USDCAD",
      "strategy": "komjathy",
      "direction": "sell",
      "entry_time": "2026-01-17T04:44:45",
      "exit_time": "2026-01-17T17:02:30",
      "entry_price": 1.3592,
      "exit_price": 1.36091,
      "sl_price": 1.36086,
      "tp_price": 1.35316,
      "lots": 0.6,
      "pnl_usd": -51.1,
      "pnl_r": -0.511,
      "exit_reason": "sl",
      "duration_bars": 147
    },
    {
      "id": 68,
      "symbol": "USDJPY",
      "strategy": "komjathy",
      "direction": "sell",
      "entry_time": "2026-01-17T16:22:54",
      "exit_time": "2026-01-18T21:31:38",
      "entry_price": 148.52961,
      "exit_price": 147.57421,
      "sl_price": 148.78012,
      "tp_price": 147.57421,
      "lots": 0.44,
      "pnl_usd": 267.3,
      "pnl_r": 2.673,
      "exit_reason": "tp",
      "duration_bars": 349
    },
    {
      "id": 23,
      "symbol": "USDCAD",
      "strategy": "komjathy",
      "direction": "sell",
      "entry_time": "2026-01-21T04:21:52",
      "exit_time": "2026-01-22T12:05:00",
      "entry_price": 1.35972,
      "exit_price": 1.36326,
      "sl_price": 1.36336,
      "tp_price": 1.35416,
      "lots": 0.27,
      "pnl_usd": -68.69,
      "pnl_r": -0.687,
      "exit_reason": "sl",
      "duration_bars": 380
    },
    {
      "id": 73,
      "symbol": "AUDUSD",
      "strategy": "momentum_pullback",
      "direction": "sell",
      "entry_time": "2026-01-22T09:57:07",
      "exit_time": "2026-01-23T03:22:12",
      "entry_price": 0.6455,
      "exit_price": 0.64749,
      "sl_price": 0.64765,
      "tp_price": 0.63982,
      "lots": 0.46,
      "pnl_usd": -99.51,
      "pnl_r": -0.995,
      "exit_reason": "trailing",
      "duration_bars": 209
    },
    {
      "id": 51,
      "symbol": "EURJPY",
      "strategy": "macd_stochastic",
      "direction": "sell",
      "entry_time": "2026-01-22T23:02:14",
      "exit_time": "2026-01-23T22:02:49",
      "entry_price": 161.22027,
      "exit_price": 161.35256,
      "sl_price": 161.37037,
      "tp_price": 160.80184,
      "lots": 0.74,
      "pnl_usd": -112.96,
      "pnl_r": -1.13,
      "exit_reason": "sl",
      "duration_bars": 276
    },
    {
      "id": 111,
      "symbol": "GBPUSD",
      "strategy": "macd_stochastic",
      "direction": "sell",
      "entry_time": "2026-01-23T00:30:01",
      "exit_time": "2026-01-24T12:26:33",
      "entry_price": 1.26562,
      "exit_price": 1.269,
      "sl_price": 1.26901,
      "tp_price": 1.25793,
      "lots": 0.3,
      "pnl_usd": -66.96,
      "pnl_r": -0.67,
      "exit_reason": "sl",
      "duration_bars": 431
    },
    {
      "id": 76,
      "symbol": "EURJPY",
      "strategy": "momentum_pullback",
      "direction": "buy",
      "entry_time": "2026-01-23T14:42:43",
      "exit_time": "2026-01-24T23:05:45",
      "entry_price": 161.13375,
      "exit_price": 161.50953,
      "sl_price": 160.92987,
      "tp_price": 161.50953,
      "lots": 0.54,
      "pnl_usd": 219.41,
      "pnl_r": 2.194,
      "exit_reason": "tp",
      "duration_bars": 388
    },
    {
      "id": 108,
      "symbol": "EURUSD",
      "strategy": "momentum_pullback",
      "direction": "buy",
      "entry_time": "2026-01-24T05:46:56",
      "exit_time": "2026-01-26T01:55:36",
      "entry_price": 1.08402,
      "exit_price": 1.08949,
      "sl_price": 1.08194,
      "tp_price": 1.08949,
      "lots": 0.48,
      "pnl_usd": 110.84,
      "pnl_r": 1.108,
      "exit_reason": "tp",
      "duration_bars": 529
    },
    {
      "id": 63,
      "symbol": "EURGBP",
      "strategy": "komjathy",
      "direction": "sell",
      "entry_time": "2026-01-26T21:34:13",
      "exit_time": "2026-01-27T18:25:56",
      "entry_price": 0.85462,
      "exit_price": 0.85657,
      "sl_price": 0.8567,
      "tp_price": 0.84906,
      "lots": 0.48,
      "pnl_usd": -74.79,
      "pnl_r": -0.748,
      "exit_reason": "trailing",
      "duration_bars": 250
    },
    {
      "id": 17,
      "symbol": "GBPJPY",
      "strategy": "macd_stochastic",
      "direction": "sell",
      "entry_time": "2026-01-27T19:40:49",
      "exit_time": "2026-01-28T09:09:35",
      "entry_price": 188.79311,
      "exit_price": 188.94055,
      "sl_price": 188.94758,
      "tp_price": 188.48019,
      "lots": 0.72,
      "pnl_usd": -101.34,
      "pnl_r": -1.013,
      "exit_reason": "sl",
      "duration_bars": 161
    },
    {
      "id": 2,
      "symbol": "GBPUSD",
      "strategy": "macd_stochastic",
      "direction": "sell",
      "entry_time": "2026-01-28T12:57:58",
      "exit_time": "2026-01-29T15:46:15",
      "entry_price": 1.26429,
      "exit_price": 1.26627,
      "sl_price": 1.26643,
      "tp_price": 1.25847,
      "lots": 0.47,
      "pnl_usd": -82.45,
      "pnl_r": -0.824,
      "exit_reason": "sl",
      "duration_bars": 321
    },
    {
      "id": 41,
      "symbol": "AUDUSD",
      "strategy": "komjathy",
      "direction": "sell",
      "entry_time": "2026-01-29T12:08:44",
      "exit_time": "2026-01-31T01:53:05",
      "entry_price": 0.64478,
      "exit_price": 0.6468,
      "sl_price": 0.64671,
      "tp_price": 0.63855,
      "lots": 0.52,
      "pnl_usd": -55.27,
      "pnl_r": -0.553,
      "exit_reason": "sl",
      "duration_bars": 452
    },
    {
      "id": 69,
      "symbol": "XAUUSD",
      "strategy": "momentum_pullback",
      "direction": "buy",
      "entry_time": "2026-01-29T20:26:16",
      "exit_time": "2026-01-31T09:23:19",
      "entry_price": 2325.60431,
      "exit_price": 2371.52525,
      "sl_price": 2302.03275,
      "tp_price": 2371.52525,
      "lots": 0.42,
      "pnl_usd": 202.4,
      "pnl_r": 2.024,
      "exit_reason": "tp",
      "duration_bars": 443
    },
    {
      "id": 65,
      "symbol": "XAUUSD",
      "strategy": "momentum_pullback",
      "direction": "buy",
      "entry_time": "2026-01-31T01:29:50",
      "exit_time": "2026-02-01T14:35:19",
      "entry_price": 2322.39242,
      "exit_price": 2295.06595,
      "sl_price": 2296.5465,
      "tp_price": 2409.90594,
      "lots": 0.39,
      "pnl_usd": -88.43,
      "pnl_r": -0.884,
      "exit_reason": "sl",
      "duration_bars": 445
    },
    {
      "id": 97,
      "symbol": "GBPJPY",
      "strategy": "macd_stochastic",
      "direction": "sell",
      "entry_time": "2026-02-01T08:02:16",
      "exit_time": "2026-02-02T23:57:49",
      "entry_price": 188.66803,
      "exit_price": 187.38663,
      "sl_price": 188.99361,
      "tp_price": 187.38663,
      "lots": 0.34,
      "pnl_usd": 160.61,
      "pnl_r": 1.606,
      "exit_reason": "tp",
      "duration_bars": 479
    },
    {
      "id": 102,
      "symbol": "GBPJPY",
      "strategy": "macd_stochastic",
      "direction": "sell",
      "entry_time": "2026-02-03T02:45:17",
      "exit_time": "2026-02-04T18:38:00",
      "entry_price": 188.67951,
      "exit_price": 188.34014,
      "sl_price": 188.86965,
      "tp_price": 188.34014,
      "lots": 0.58,
      "pnl_usd": 167.77,
      "pnl_r": 1.678,
      "exit_reason": "tp",
      "duration_bars": 478
    },
    {
      "id": 103,
      "symbol": "GBPUSD",
      "strategy": "momentum_pullback",
      "direction": "buy",
      "entry_time": "2026-02-03T20:58:19",
      "exit_time": "2026-02-04T03:57:56",
      "entry_price": 1.26597,
      "exit_price": 1.26297,
      "sl_price": 1.26313,
      "tp_price": 1.27467,
      "lots": 0.35,
      "pnl_usd": -66.36,
      "pnl_r": -0.664,
      "exit_reason": "trailing",
      "duration_bars": 83
    },
    {
      "id": 22,
      "symbol": "EURUSD",
      "strategy": "komjathy",
      "direction": "buy",
      "entry_time": "2026-02-05T04:04:33",
      "exit_time": "2026-02-05T12:02:24",
      "entry_price": 1.08444,
      "exit_price": 1.09557,
      "sl_price": 1.08102,
      "tp_price": 1.09557,
      "lots": 0.29,
      "pnl_usd": 237.6,
      "pnl_r": 2.376,
      "exit_reason": "tp",
      "duration_bars": 95
    },
    {
      "id": 88,
      "symbol": "USDCHF",
      "strategy": "macd_stochastic",
      "direction": "sell",
      "entry_time": "2026-02-08T12:16:24",
      "exit_time": "2026-02-10T11:29:04",
      "entry_price": 0.90544,
      "exit_price": 0.90176,
      "sl_price": 0.90771,
      "tp_price": 0.90176,
      "lots": 0.44,
      "pnl_usd": 260.29,
      "pnl_r": 2.603,
      "exit_reason": "tp",
      "duration_bars": 566
    },
    {
      "id": 77,
      "symbol": "XAUUSD",
      "strategy": "momentum_pullback",
      "direction": "buy",
      "entry_time": "2026-02-09T02:04:13",
      "exit_time": "2026-02-09T17:53:46",
      "entry_price": 2310.19464,
      "exit_price": 2397.8461,
      "sl_price": 2281.91739,
      "tp_price": 2397.8461,
      "lots": 0.35,
      "pnl_usd": 231.34,
      "pnl_r": 2.313,
      "exit_reason": "tp",
      "duration_bars": 189
    },
    {
      "id": 37,
      "symbol": "XAUUSD",
      "strategy": "momentum_pullback",
      "direction": "sell",
      "entry_time": "2026-02-09T03:58:09",
      "exit_time": "2026-02-10T01:45:13",
      "entry_price": 2322.54408,
      "exit_price": 2264.57618,
      "sl_price": 2344.12939,
      "tp_price": 2264.57618,
      "lots": 0.46,
      "pnl_usd": 194.89,
      "pnl_r": 1.949,
      "exit_reason": "tp",
      "duration_bars": 261
    },
    {
      "id": 54,
      "symbol": "XAUUSD",
      "strategy": "momentum_pullback",
      "direction": "sell",
      "entry_time": "2026-02-09T11:01:50",
      "exit_time": "2026-02-10T14:09:50",
      "entry_price": 2320.39204,
      "exit_price": 2344.63785,
      "sl_price": 2344.43124,
      "tp_price": 2260.77739,
      "lots": 0.42,
      "pnl_usd": -57.86,
      "pnl_r": -0.579,
      "exit_reason": "trailing",
      "duration_bars": 325
    },
    {
      "id": 15,
      "symbol": "EURUSD",
      "strategy": "macd_stochastic",
      "direction": "sell",
      "entry_time": "2026-02-11T02:59:53",
      "exit_time": "2026-02-11T13:29:10",
      "entry_price": 1.08428,
      "exit_price": 1.08025,
      "sl_price": 1.08649,
      "tp_price": 1.08025,
      "lots": 0.45,
      "pnl_usd": 270.03,
      "pnl_r": 2.7,
      "exit_reason": "tp",
      "duration_bars": 125
    },
    {
      "id": 80,
      "symbol": "USDCHF",
      "strategy": "macd_stochastic",
      "direction": "buy",
      "entry_time": "2026-02-11T11:27:48",
      "exit_time": "2026-02-12T19:26:45",
      "entry_price": 0.90452,
      "exit_price": 0.91258,
      "sl_price": 0.90142,
      "tp_price": 0.91258,
      "lots": 0.32,
      "pnl_usd": 234.03,
      "pnl_r": 2.34,
      "exit_reason": "tp",
      "duration_bars": 383
    },
    {
      "id": 74,
      "symbol": "USDJPY",
      "strategy": "momentum_pullback",
      "direction": "buy",
      "entry_time": "2026-02-11T19:01:32",
      "exit_time": "2026-02-12T19:25:01",
      "entry_price": 148.56354,
      "exit_price": 148.31942,
      "sl_price": 148.33047,
      "tp_price": 149.09201,
      "lots": 0.48,
      "pnl_usd": -52.7,
      "pnl_r": -0.527,
      "exit_reason": "sl",
      "duration_bars": 292
    },
    {
      "id": 53,
      "symbol": "GBPUSD",
      "strategy": "komjathy",
      "direction": "sell",
      "entry_time": "2026-02-15T01:20:22",
      "exit_time": "2026-02-15T13:53:38",
      "entry_price": 1.26508,
      "exit_price": 1.2587,
      "sl_price": 1.26693,
      "tp_price": 1.2587,
      "lots": 0.54,
      "pnl_usd": 126.39,
      "pnl_r": 1.264,
      "exit_reason": "tp",
      "duration_bars": 150
    },
    {
      "id": 84,
      "symbol": "EURJPY",
      "strategy": "komjathy",
      "direction": "buy",
      "entry_time": "2026-02-18T15:55:30",
      "exit_time": "2026-02-20T12:51:18",
      "entry_price": 161.18126,
      "exit_price": 161.83647,
      "sl_price": 160.79265,
      "tp_price": 161.83647,
      "lots": 0.29,
      "pnl_usd": 141.69,
      "pnl_r": 1.417,
      "exit_reason": "tp",
      "duration_bars": 539
    },
    {
      "id": 52,
      "symbol": "GBPJPY",
      "strategy": "momentum_pullback",
      "direction": "buy",
      "entry_time": "2026-02-19T16:26:28",
      "exit_time": "2026-02-20T23:38:33",
      "entry_price": 188.73155,
      "exit_price": 189.23277,
      "sl_price": 188.44595,
      "tp_price": 189.23277,
      "lots": 0.39,
      "pnl_usd": 267.18,
      "pnl_r": 2.672,
      "exit_reason": "tp",
      "duration_bars": 374
    },
    {
      "id": 14,
      "symbol": "GBPUSD",
      "strategy": "macd_stochastic",
      "direction": "sell",
      "entry_time": "2026-02-19T18:10:44",
      "exit_time": "2026-02-20T00:56:42",
      "entry_price": 1.26475,
      "exit_price": 1.25462,
      "sl_price": 1.26765,
      "tp_price": 1.25462,
      "lots": 0.34,
      "pnl_usd": 202.67,
      "pnl_r": 2.027,
      "exit_reason": "tp",
      "duration_bars": 81
    },
    {
      "id": 29,
      "symbol": "EURGBP",
      "strategy": "macd_stochastic",
      "direction": "buy",
      "entry_time": "2026-02-22T03:58:39",
      "exit_time": "2026-02-22T14:31:08",
      "entry_price": 0.85587,
      "exit_price": 0.85245,
      "sl_price": 0.85249,
      "tp_price": 0.86674,
      "lots": 0.3,
      "pnl_usd": -74.73,
      "pnl_r": -0.747,
      "exit_reason": "trailing",
      "duration_bars": 126
    },
    {
      "id": 40,
      "symbol": "EURUSD",
      "strategy": "momentum_pullback",
      "direction": "sell",
      "entry_time": "2026-02-25T15:17:59",
      "exit_time": "2026-02-26T06:14:23",
      "entry_price": 1.08471,
      "exit_price": 1.08663,
      "sl_price": 1.08681,
      "tp_price": 1.07865,
      "lots": 0.48,
      "pnl_usd": -73.65,
      "pnl_r": -0.737,
      "exit_reason": "sl",
      "duration_bars": 179
    },
    {
      "id": 6,
      "symbol": "AUDUSD",
      "strategy": "macd_stochastic",
      "direction": "buy",
      "entry_time": "2026-02-26T16:13:32",
      "exit_time": "2026-02-28T03:47:09",
      "entry_price": 0.64411,
      "exit_price": 0.65154,
      "sl_price": 0.64067,
      "tp_price": 0.65154,
      "lots": 0.29,
      "pnl_usd": 117.04,
      "pnl_r": 1.17,
      "exit_reason": "tp",
      "duration_bars": 426
    },
    {
      "id": 118,
      "symbol": "GBPJPY",
      "strategy": "momentum_pullback",
      "direction": "buy",
      "entry_time": "2026-03-02T00:18:15",
      "exit_time": "2026-03-02T03:56:03",
      "entry_price": 188.68078,
      "exit_price": 188.34457,
      "sl_price": 188.35402,
      "tp_price": 189.2194,
      "lots": 0.34,
      "pnl_usd": -83.38,
      "pnl_r": -0.834,
      "exit_reason": "sl",
      "duration_bars": 43
    },
    {
      "id": 99,
      "symbol": "GBPUSD",
      "strategy": "komjathy",
      "direction": "sell",
      "entry_time": "2026-03-02T11:13:06",
      "exit_time": "2026-03-03T23:05:47",
      "entry_price": 1.26588,
      "exit_price": 1.26837,
      "sl_price": 1.2682,
      "tp_price": 1.26156,
      "lots": 0.43,
      "pnl_usd": -74.21,
      "pnl_r": -0.742,
      "exit_reason": "sl",
      "duration_bars": 430
    },
    {
      "id": 16,
      "symbol": "USDJPY",
      "strategy": "macd_stochastic",
      "direction": "sell",
      "entry_time": "2026-03-03T14:41:13",
      "exit_time": "2026-03-04T14:58:08",
      "entry_price": 148.4021,
      "exit_price": 147.86184,
      "sl_price": 148.59957,
      "tp_price": 147.86184,
      "lots": 0.56,
      "pnl_usd": 263.48,
      "pnl_r": 2.635,
      "exit_reason": "tp",
      "duration_bars": 291
    },
    {
      "id": 95,
      "symbol": "EURJPY",
      "strategy": "komjathy",
      "direction": "sell",
      "entry_time": "2026-03-03T20:52:32",
      "exit_time": "2026-03-04T09:40:17",
      "entry_price": 161.11322,
      "exit_price": 161.38836,
      "sl_price": 161.39817,
      "tp_price": 160.21639,
      "lots": 0.39,
      "pnl_usd": -63.23,
      "pnl_r": -0.632,
      "exit_reason": "sl",
      "duration_bars": 153
    },
    {
      "id": 112,
      "symbol": "EURUSD",
      "strategy": "komjathy",
      "direction": "buy",
      "entry_time": "2026-03-04T10:55:54",
      "exit_time": "2026-03-06T07:02:27",
      "entry_price": 1.08587,
      "exit_price": 1.08244,
      "sl_price": 1.08255,
      "tp_price": 1.09215,
      "lots": 0.3,
      "pnl_usd": -107.45,
      "pnl_r": -1.074,
      "exit_reason": "sl",
      "duration_bars": 529
    },
    {
      "id": 12,
      "symbol": "XAUUSD",
      "strategy": "macd_stochastic",
      "direction": "buy",
      "entry_time": "2026-03-05T06:17:14",
      "exit_time": "2026-03-06T21:24:37",
      "entry_price": 2318.46992,
      "exit_price": 2288.25245,
      "sl_price": 2288.47485,
      "tp_price": 2389.55085,
      "lots": 0.33,
      "pnl_usd": -57.15,
      "pnl_r": -0.571,
      "exit_reason": "trailing",
      "duration_bars": 469
    },
    {
      "id": 7,
      "symbol": "USDJPY",
      "strategy": "momentum_pullback",
      "direction": "sell",
      "entry_time": "2026-03-05T21:45:34",
      "exit_time": "2026-03-06T15:43:20",
      "entry_price": 148.55257,
      "exit_price": 148.89588,
      "sl_price": 148.90331,
      "tp_price": 147.77217,
      "lots": 0.32,
      "pnl_usd": -112.91,
      "pnl_r": -1.129,
      "exit_reason": "sl",
      "duration_bars": 215
    },
    {
      "id": 86,
      "symbol": "USDCAD",
      "strategy": "momentum_pullback",
      "direction": "buy",
      "entry_time": "2026-03-08T07:41:42",
      "exit_time": "2026-03-09T04:52:54",
      "entry_price": 1.3597,
      "exit_price": 1.35623,
      "sl_price": 1.35627,
      "tp_price": 1.36824,
      "lots": 0.29,
      "pnl_usd": -110.32,
      "pnl_r": -1.103,
      "exit_reason": "sl",
      "duration_bars": 254
    },
    {
      "id": 48,
      "symbol": "EURUSD",
      "strategy": "komjathy",
      "direction": "buy",
      "entry_time": "2026-03-09T00:50:34",
      "exit_time": "2026-03-10T10:55:27",
      "entry_price": 1.08539,
      "exit_price": 1.08321,
      "sl_price": 1.08323,
      "tp_price": 1.0939,
      "lots": 0.46,
      "pnl_usd": -97.44,
      "pnl_r": -0.974,
      "exit_reason": "sl",
      "duration_bars": 408
    },
    {
      "id": 87,
      "symbol": "USDCAD",
      "strategy": "komjathy",
      "direction": "sell",
      "entry_time": "2026-03-09T17:17:54",
      "exit_time": "2026-03-10T20:57:33",
      "entry_price": 1.36086,
      "exit_price": 1.36343,
      "sl_price": 1.36358,
      "tp_price": 1.35648,
      "lots": 0.37,
      "pnl_usd": -59.5,
      "pnl_r": -0.595,
      "exit_reason": "sl",
      "duration_bars": 331
    }
  ]
}