{
  "generated_at": "2026-04-03T08:37:25.444539Z",
  "mode": "dummy",
  "initial_equity": 10000.0,
  "period": {
    "start": "2025-11-01",
    "end": "2026-03-28"
  },
  "stats": {
    "total_trades": 120,
    "winning_trades": 61,
    "losing_trades": 59,
    "win_rate_pct": 50.8,
    "total_pnl_usd": 7196.01,
    "total_r": 71.958,
    "r_per_day": 0.935,
    "avg_win_usd": 198.22,
    "avg_loss_usd": -82.97,
    "profit_factor": 2.47,
    "max_drawdown_pct": 4.63,
    "initial_equity": 10000.0,
    "final_equity": 17196.01,
    "return_pct": 71.96,
    "avg_duration_bars": 294.9,
    "daily_pnl": {
      "2025-11-03": -145.23,
      "2025-11-06": -99.67,
      "2025-11-09": 453.1,
      "2025-11-11": 409.79,
      "2025-11-13": 175.04,
      "2025-11-12": 128.84,
      "2025-11-15": 142.48000000000002,
      "2025-11-17": 236.47000000000003,
      "2025-11-19": 1.3799999999999955,
      "2025-11-20": 154.1,
      "2025-11-21": -81.06,
      "2025-11-23": 299.61,
      "2025-11-24": 369.81,
      "2025-11-25": 177.67,
      "2025-11-26": 302.82,
      "2025-11-27": -102.31,
      "2025-11-28": -116.77,
      "2025-11-30": -96.1,
      "2025-12-02": 157.6,
      "2025-12-03": 374.82,
      "2025-12-04": 131.46,
      "2025-12-05": -2.0900000000000034,
      "2025-12-09": -169.55,
      "2025-12-11": -84.18,
      "2025-12-12": -165.10000000000002,
      "2025-12-13": 344.54999999999995,
      "2025-12-15": -110.59,
      "2025-12-16": 194.6,
      "2025-12-17": -73.12,
      "2025-12-19": -77.35,
      "2025-12-21": 69.91999999999999,
      "2025-12-22": 545.4200000000001,
      "2025-12-23": -56.21,
      "2025-12-25": 552.0699999999999,
      "2025-12-26": 251.51000000000002,
      "2025-12-28": 267.82,
      "2025-12-30": -112.57,
      "2025-12-29": 130.64,
      "2026-01-03": 173.76,
      "2026-01-04": -116.45,
      "2026-01-05": 66.49000000000001,
      "2026-01-08": -36.670000000000016,
      "2026-01-09": -73.51,
      "2026-01-13": -87.55,
      "2026-01-14": 176.61,
      "2026-01-17": -53.29,
      "2026-01-20": 41.75000000000001,
      "2026-01-21": 297.22,
      "2026-01-22": 163.97,
      "2026-01-23": 227.31,
      "2026-01-24": -73.81,
      "2026-01-25": -95.49,
      "2026-01-26": -85.93,
      "2026-01-29": -102.57,
      "2026-01-30": 213.63,
      "2026-01-31": 45.28999999999999,
      "2026-02-01": 179.44,
      "2026-02-03": 132.44,
      "2026-02-07": -53.4,
      "2026-02-08": 276.46,
      "2026-02-11": -82.86,
      "2026-02-12": 191.10000000000002,
      "2026-02-14": -107.06,
      "2026-02-20": -148.04999999999998,
      "2026-02-21": -257.97,
      "2026-02-26": 56.06000000000002,
      "2026-02-27": 405.62,
      "2026-02-28": 336.96000000000004,
      "2026-03-01": -165.54,
      "2026-03-02": -85.87,
      "2026-03-04": 159.11,
      "2026-03-06": -60.21,
      "2026-03-08": 243.94000000000003,
      "2026-03-09": 140.98,
      "2026-03-11": 559.0999999999999,
      "2026-03-10": 129.62,
      "2026-03-12": 285.76
    },
    "weekly_pnl": {
      "2025-W45": 208.2,
      "2025-W46": 856.15,
      "2025-W47": 610.5,
      "2025-W48": 535.12,
      "2025-W49": 661.79,
      "2025-W50": -74.28,
      "2025-W51": 3.46,
      "2025-W52": 1560.61,
      "2025-W01": 18.07,
      "2026-W01": 57.31,
      "2026-W02": -43.69,
      "2026-W03": 35.77,
      "2026-W04": 560.95,
      "2026-W05": 249.86,
      "2026-W06": 355.5,
      "2026-W07": 1.18,
      "2026-W08": -406.02,
      "2026-W09": 633.1,
      "2026-W10": 256.97,
      "2026-W11": 1115.46
    },
    "weekly_r": {
      "2025-W45": 2.081,
      "2025-W46": 8.562,
      "2025-W47": 6.104,
      "2025-W48": 5.352,
      "2025-W49": 6.618,
      "2025-W50": -0.743,
      "2025-W51": 0.035,
      "2025-W52": 15.607,
      "2025-W01": 0.18,
      "2026-W01": 0.573,
      "2026-W02": -0.436,
      "2026-W03": 0.358,
      "2026-W04": 5.61,
      "2026-W05": 2.499,
      "2026-W06": 3.555,
      "2026-W07": 0.011,
      "2026-W08": -4.061,
      "2026-W09": 6.329,
      "2026-W10": 2.57,
      "2026-W11": 11.154
    },
    "by_symbol": {
      "EURUSD": {
        "trades": 15,
        "win_rate": 33.3,
        "total_pnl": 119.9,
        "total_r": 1.199
      },
      "GBPUSD": {
        "trades": 16,
        "win_rate": 37.5,
        "total_pnl": 424.58,
        "total_r": 4.245
      },
      "USDJPY": {
        "trades": 13,
        "win_rate": 69.2,
        "total_pnl": 1575.37,
        "total_r": 15.755
      },
      "AUDUSD": {
        "trades": 15,
        "win_rate": 60.0,
        "total_pnl": 1263.11,
        "total_r": 12.629
      },
      "USDCAD": {
        "trades": 13,
        "win_rate": 46.2,
        "total_pnl": 341.14,
        "total_r": 3.412
      },
      "USDCHF": {
        "trades": 9,
        "win_rate": 44.4,
        "total_pnl": 327.91,
        "total_r": 3.279
      },
      "EURGBP": {
        "trades": 9,
        "win_rate": 55.6,
        "total_pnl": 699.38,
        "total_r": 6.993
      },
      "EURJPY": {
        "trades": 12,
        "win_rate": 83.3,
        "total_pnl": 1883.6,
        "total_r": 18.837
      },
      "GBPJPY": {
        "trades": 9,
        "win_rate": 33.3,
        "total_pnl": 165.12,
        "total_r": 1.651
      },
      "XAUUSD": {
        "trades": 9,
        "win_rate": 44.4,
        "total_pnl": 395.9,
        "total_r": 3.958
      }
    }
  },
  "equity_curve": [
    {
      "time": "2025-11-02T06:41:17",
      "equity": 10000.0
    },
    {
      "time": "2025-11-03T12:17:24",
      "equity": 9911.34
    },
    {
      "time": "2025-11-03T10:23:07",
      "equity": 9854.77
    },
    {
      "time": "2025-11-06T04:42:40",
      "equity": 9755.1
    },
    {
      "time": "2025-11-09T02:04:48",
      "equity": 9990.28
    },
    {
      "time": "2025-11-09T04:02:24",
      "equity": 10208.2
    },
    {
      "time": "2025-11-11T00:50:34",
      "equity": 10348.76
    },
    {
      "time": "2025-11-11T01:39:59",
      "equity": 10617.99
    },
    {
      "time": "2025-11-13T01:17:43",
      "equity": 10552.96
    },
    {
      "time": "2025-11-12T10:54:48",
      "equity": 10681.8
    },
    {
      "time": "2025-11-13T18:34:25",
      "equity": 10921.87
    },
    {
      "time": "2025-11-15T20:18:26",
      "equity": 10832.49
    },
    {
      "time": "2025-11-15T05:56:38",
      "equity": 11064.35
    },
    {
      "time": "2025-11-17T03:35:55",
      "equity": 10972.14
    },
    {
      "time": "2025-11-17T07:55:14",
      "equity": 11188.73
    },
    {
      "time": "2025-11-17T12:47:37",
      "equity": 11300.82
    },
    {
      "time": "2025-11-19T17:43:57",
      "equity": 11410.06
    },
    {
      "time": "2025-11-19T09:12:14",
      "equity": 11302.2
    },
    {
      "time": "2025-11-20T03:32:51",
      "equity": 11456.3
    },
    {
      "time": "2025-11-21T02:11:56",
      "equity": 11375.24
    },
    {
      "time": "2025-11-23T06:46:36",
      "equity": 11674.85
    },
    {
      "time": "2025-11-24T14:18:38",
      "equity": 11936.41
    },
    {
      "time": "2025-11-25T03:44:33",
      "equity": 12114.08
    },
    {
      "time": "2025-11-24T19:44:34",
      "equity": 12222.33
    },
    {
      "time": "2025-11-26T02:57:16",
      "equity": 12458.92
    },
    {
      "time": "2025-11-26T01:38:31",
      "equity": 12391.14
    },
    {
      "time": "2025-11-26T16:03:25",
      "equity": 12525.15
    },
    {
      "time": "2025-11-27T00:22:06",
      "equity": 12422.84
    },
    {
      "time": "2025-11-28T18:22:20",
      "equity": 12361.48
    },
    {
      "time": "2025-11-28T08:24:41",
      "equity": 12306.07
    },
    {
      "time": "2025-11-30T15:37:23",
      "equity": 12209.97
    },
    {
      "time": "2025-12-02T06:08:24",
      "equity": 12367.57
    },
    {
      "time": "2025-12-03T03:28:37",
      "equity": 12567.1
    },
    {
      "time": "2025-12-03T11:21:59",
      "equity": 12742.39
    },
    {
      "time": "2025-12-04T11:12:32",
      "equity": 12873.85
    },
    {
      "time": "2025-12-05T06:37:21",
      "equity": 12979.74
    },
    {
      "time": "2025-12-05T09:42:22",
      "equity": 12871.76
    },
    {
      "time": "2025-12-09T12:40:51",
      "equity": 12799.12
    },
    {
      "time": "2025-12-09T10:35:29",
      "equity": 12702.21
    },
    {
      "time": "2025-12-11T08:26:30",
      "equity": 12618.03
    },
    {
      "time": "2025-12-12T08:04:07",
      "equity": 12513.74
    },
    {
      "time": "2025-12-13T14:17:04",
      "equity": 12703.16
    },
    {
      "time": "2025-12-13T12:47:00",
      "equity": 12858.29
    },
    {
      "time": "2025-12-12T20:59:55",
      "equity": 12797.48
    },
    {
      "time": "2025-12-15T02:47:43",
      "equity": 12686.89
    },
    {
      "time": "2025-12-16T12:00:21",
      "equity": 12881.49
    },
    {
      "time": "2025-12-17T19:06:31",
      "equity": 12808.37
    },
    {
      "time": "2025-12-19T17:45:05",
      "equity": 12731.02
    },
    {
      "time": "2025-12-21T09:15:38",
      "equity": 12650.3
    },
    {
      "time": "2025-12-21T07:29:31",
      "equity": 12800.94
    },
    {
      "time": "2025-12-22T19:08:35",
      "equity": 13089.7
    },
    {
      "time": "2025-12-23T05:10:45",
      "equity": 13033.49
    },
    {
      "time": "2025-12-22T17:03:52",
      "equity": 13290.15
    },
    {
      "time": "2025-12-25T01:06:18",
      "equity": 13588.58
    },
    {
      "time": "2025-12-26T08:51:57",
      "equity": 13737.94
    },
    {
      "time": "2025-12-26T01:41:59",
      "equity": 13840.09
    },
    {
      "time": "2025-12-25T12:09:26",
      "equity": 14093.73
    },
    {
      "time": "2025-12-28T02:03:07",
      "equity": 14361.55
    },
    {
      "time": "2025-12-30T11:35:51",
      "equity": 14248.98
    },
    {
      "time": "2025-12-29T17:39:32",
      "equity": 14379.62
    },
    {
      "time": "2026-01-03T06:42:33",
      "equity": 14553.38
    },
    {
      "time": "2026-01-04T02:17:31",
      "equity": 14436.93
    },
    {
      "time": "2026-01-05T13:13:32",
      "equity": 14646.0
    },
    {
      "time": "2026-01-05T02:59:25",
      "equity": 14576.79
    },
    {
      "time": "2026-01-05T23:49:16",
      "equity": 14503.42
    },
    {
      "time": "2026-01-08T06:44:10",
      "equity": 14416.41
    },
    {
      "time": "2026-01-08T18:59:32",
      "equity": 14345.38
    },
    {
      "time": "2026-01-09T14:20:47",
      "equity": 14271.87
    },
    {
      "time": "2026-01-08T22:45:21",
      "equity": 14393.24
    },
    {
      "time": "2026-01-13T00:50:47",
      "equity": 14305.69
    },
    {
      "time": "2026-01-14T15:15:49",
      "equity": 14482.3
    },
    {
      "time": "2026-01-17T08:26:04",
      "equity": 14429.01
    },
    {
      "time": "2026-01-20T10:57:58",
      "equity": 14532.66
    },
    {
      "time": "2026-01-20T23:32:50",
      "equity": 14470.76
    },
    {
      "time": "2026-01-21T03:41:27",
      "equity": 14767.98
    },
    {
      "time": "2026-01-22T16:47:49",
      "equity": 15009.39
    },
    {
      "time": "2026-01-22T15:00:53",
      "equity": 14931.95
    },
    {
      "time": "2026-01-23T14:31:56",
      "equity": 15159.26
    },
    {
      "time": "2026-01-24T03:06:54",
      "equity": 15085.45
    },
    {
      "time": "2026-01-25T07:41:13",
      "equity": 14989.96
    },
    {
      "time": "2026-01-26T09:22:36",
      "equity": 14904.03
    },
    {
      "time": "2026-01-29T01:41:49",
      "equity": 14801.46
    },
    {
      "time": "2026-01-30T13:35:58",
      "equity": 15015.09
    },
    {
      "time": "2026-01-31T08:25:22",
      "equity": 15138.97
    },
    {
      "time": "2026-01-31T08:22:17",
      "equity": 15060.38
    },
    {
      "time": "2026-02-01T03:55:07",
      "equity": 14972.96
    },
    {
      "time": "2026-02-01T18:28:22",
      "equity": 15239.82
    },
    {
      "time": "2026-02-03T07:11:36",
      "equity": 15145.72
    },
    {
      "time": "2026-02-03T16:50:30",
      "equity": 15372.26
    },
    {
      "time": "2026-02-07T21:14:35",
      "equity": 15318.86
    },
    {
      "time": "2026-02-08T11:25:29",
      "equity": 15595.32
    },
    {
      "time": "2026-02-11T11:08:14",
      "equity": 15512.46
    },
    {
      "time": "2026-02-12T09:14:28",
      "equity": 15811.45
    },
    {
      "time": "2026-02-12T18:51:31",
      "equity": 15703.56
    },
    {
      "time": "2026-02-14T10:00:13",
      "equity": 15596.5
    },
    {
      "time": "2026-02-20T00:02:26",
      "equity": 15501.93
    },
    {
      "time": "2026-02-20T16:59:34",
      "equity": 15448.45
    },
    {
      "time": "2026-02-21T14:14:41",
      "equity": 15359.66
    },
    {
      "time": "2026-02-21T08:22:03",
      "equity": 15259.47
    },
    {
      "time": "2026-02-21T10:31:26",
      "equity": 15190.48
    },
    {
      "time": "2026-02-26T10:38:21",
      "equity": 15079.71
    },
    {
      "time": "2026-02-27T06:35:48",
      "equity": 15330.78
    },
    {
      "time": "2026-02-26T13:54:19",
      "equity": 15497.61
    },
    {
      "time": "2026-02-27T08:08:41",
      "equity": 15652.16
    },
    {
      "time": "2026-02-28T15:28:46",
      "equity": 15827.19
    },
    {
      "time": "2026-02-28T21:57:37",
      "equity": 15989.12
    },
    {
      "time": "2026-03-01T03:23:27",
      "equity": 15895.16
    },
    {
      "time": "2026-03-02T10:35:40",
      "equity": 15809.29
    },
    {
      "time": "2026-03-01T19:47:02",
      "equity": 15737.71
    },
    {
      "time": "2026-03-04T02:53:31",
      "equity": 15990.61
    },
    {
      "time": "2026-03-04T22:28:04",
      "equity": 15896.82
    },
    {
      "time": "2026-03-06T11:37:51",
      "equity": 15836.61
    },
    {
      "time": "2026-03-08T16:09:49",
      "equity": 15784.89
    },
    {
      "time": "2026-03-08T06:33:03",
      "equity": 16080.55
    },
    {
      "time": "2026-03-09T18:45:52",
      "equity": 15999.68
    },
    {
      "time": "2026-03-09T11:04:05",
      "equity": 16221.53
    },
    {
      "time": "2026-03-11T16:18:41",
      "equity": 16483.43
    },
    {
      "time": "2026-03-10T19:46:19",
      "equity": 16613.05
    },
    {
      "time": "2026-03-11T18:50:40",
      "equity": 16910.25
    },
    {
      "time": "2026-03-12T05:45:33",
      "equity": 17011.91
    },
    {
      "time": "2026-03-12T03:36:13",
      "equity": 17196.01
    }
  ],
  "trades": [
    {
      "id": 111,
      "symbol": "EURUSD",
      "strategy": "macd_stochastic",
      "direction": "sell",
      "entry_time": "2025-11-02T06:41:17",
      "exit_time": "2025-11-03T12:17:24",
      "entry_price": 1.08523,
      "exit_price": 1.08694,
      "sl_price": 1.08704,
      "tp_price": 1.08057,
      "lots": 0.55,
      "pnl_usd": -88.66,
      "pnl_r": -0.887,
      "exit_reason": "sl",
      "duration_bars": 355
    },
    {
      "id": 35,
      "symbol": "AUDUSD",
      "strategy": "komjathy",
      "direction": "sell",
      "entry_time": "2025-11-03T03:13:02",
      "exit_time": "2025-11-03T10:23:07",
      "entry_price": 0.64588,
      "exit_price": 0.64881,
      "sl_price": 0.6488,
      "tp_price": 0.64007,
      "lots": 0.34,
      "pnl_usd": -56.57,
      "pnl_r": -0.566,
      "exit_reason": "sl",
      "duration_bars": 86
    },
    {
      "id": 104,
      "symbol": "XAUUSD",
      "strategy": "momentum_pullback",
      "direction": "buy",
      "entry_time": "2025-11-05T10:34:22",
      "exit_time": "2025-11-06T04:42:40",
      "entry_price": 2323.19075,
      "exit_price": 2299.55171,
      "sl_price": 2300.40137,
      "tp_price": 2410.58117,
      "lots": 0.44,
      "pnl_usd": -99.67,
      "pnl_r": -0.997,
      "exit_reason": "sl",
      "duration_bars": 217
    },
    {
      "id": 34,
      "symbol": "USDCHF",
      "strategy": "macd_stochastic",
      "direction": "buy",
      "entry_time": "2025-11-08T09:05:09",
      "exit_time": "2025-11-09T02:04:48",
      "entry_price": 0.90431,
      "exit_price": 0.91577,
      "sl_price": 0.90084,
      "tp_price": 0.91577,
      "lots": 0.29,
      "pnl_usd": 235.18,
      "pnl_r": 2.352,
      "exit_reason": "tp",
      "duration_bars": 203
    },
    {
      "id": 98,
      "symbol": "EURJPY",
      "strategy": "macd_stochastic",
      "direction": "buy",
      "entry_time": "2025-11-08T12:26:41",
      "exit_time": "2025-11-09T04:02:24",
      "entry_price": 161.25888,
      "exit_price": 161.78023,
      "sl_price": 161.10694,
      "tp_price": 161.78023,
      "lots": 0.73,
      "pnl_usd": 217.92,
      "pnl_r": 2.179,
      "exit_reason": "tp",
      "duration_bars": 187
    },
    {
      "id": 85,
      "symbol": "USDJPY",
      "strategy": "momentum_pullback",
      "direction": "sell",
      "entry_time": "2025-11-09T15:08:44",
      "exit_time": "2025-11-11T00:50:34",
      "entry_price": 148.4967,
      "exit_price": 147.50828,
      "sl_price": 148.84974,
      "tp_price": 147.50828,
      "lots": 0.31,
      "pnl_usd": 140.56,
      "pnl_r": 1.406,
      "exit_reason": "tp",
      "duration_bars": 404
    },
    {
      "id": 87,
      "symbol": "EURGBP",
      "strategy": "komjathy",
      "direction": "sell",
      "entry_time": "2025-11-10T22:54:54",
      "exit_time": "2025-11-11T01:39:59",
      "entry_price": 0.8552,
      "exit_price": 0.85105,
      "sl_price": 0.85738,
      "tp_price": 0.85105,
      "lots": 0.46,
      "pnl_usd": 269.23,
      "pnl_r": 2.692,
      "exit_reason": "tp",
      "duration_bars": 33
    },
    {
      "id": 27,
      "symbol": "GBPJPY",
      "strategy": "momentum_pullback",
      "direction": "buy",
      "entry_time": "2025-11-11T13:18:01",
      "exit_time": "2025-11-13T01:17:43",
      "entry_price": 188.6121,
      "exit_price": 188.31252,
      "sl_price": 188.29628,
      "tp_price": 189.59245,
      "lots": 0.35,
      "pnl_usd": -65.03,
      "pnl_r": -0.65,
      "exit_reason": "sl",
      "duration_bars": 431
    },
    {
      "id": 22,
      "symbol": "USDCHF",
      "strategy": "macd_stochastic",
      "direction": "buy",
      "entry_time": "2025-11-11T20:35:46",
      "exit_time": "2025-11-12T10:54:48",
      "entry_price": 0.90476,
      "exit_price": 0.90863,
      "sl_price": 0.90282,
      "tp_price": 0.90863,
      "lots": 0.52,
      "pnl_usd": 128.84,
      "pnl_r": 1.288,
      "exit_reason": "tp",
      "duration_bars": 171
    },
    {
      "id": 97,
      "symbol": "AUDUSD",
      "strategy": "momentum_pullback",
      "direction": "buy",
      "entry_time": "2025-11-12T01:10:22",
      "exit_time": "2025-11-13T18:34:25",
      "entry_price": 0.64554,
      "exit_price": 0.65103,
      "sl_price": 0.64397,
      "tp_price": 0.65103,
      "lots": 0.64,
      "pnl_usd": 240.07,
      "pnl_r": 2.401,
      "exit_reason": "tp",
      "duration_bars": 496
    },
    {
      "id": 12,
      "symbol": "USDJPY",
      "strategy": "macd_stochastic",
      "direction": "sell",
      "entry_time": "2025-11-14T14:05:21",
      "exit_time": "2025-11-15T20:18:26",
      "entry_price": 148.47367,
      "exit_price": 148.75724,
      "sl_price": 148.76721,
      "tp_price": 147.79276,
      "lots": 0.38,
      "pnl_usd": -89.38,
      "pnl_r": -0.894,
      "exit_reason": "sl",
      "duration_bars": 362
    },
    {
      "id": 105,
      "symbol": "EURGBP",
      "strategy": "momentum_pullback",
      "direction": "sell",
      "entry_time": "2025-11-14T17:15:29",
      "exit_time": "2025-11-15T05:56:38",
      "entry_price": 0.85543,
      "exit_price": 0.8497,
      "sl_price": 0.85716,
      "tp_price": 0.8497,
      "lots": 0.58,
      "pnl_usd": 231.86,
      "pnl_r": 2.319,
      "exit_reason": "tp",
      "duration_bars": 152
    },
    {
      "id": 75,
      "symbol": "USDJPY",
      "strategy": "komjathy",
      "direction": "buy",
      "entry_time": "2025-11-16T09:25:33",
      "exit_time": "2025-11-17T03:35:55",
      "entry_price": 148.56296,
      "exit_price": 148.16514,
      "sl_price": 148.17814,
      "tp_price": 149.53807,
      "lots": 0.29,
      "pnl_usd": -92.21,
      "pnl_r": -0.922,
      "exit_reason": "sl",
      "duration_bars": 218
    },
    {
      "id": 65,
      "symbol": "GBPUSD",
      "strategy": "komjathy",
      "direction": "buy",
      "entry_time": "2025-11-16T11:55:23",
      "exit_time": "2025-11-17T07:55:14",
      "entry_price": 1.26476,
      "exit_price": 1.27285,
      "sl_price": 1.26263,
      "tp_price": 1.27285,
      "lots": 0.47,
      "pnl_usd": 216.59,
      "pnl_r": 2.166,
      "exit_reason": "tp",
      "duration_bars": 239
    },
    {
      "id": 56,
      "symbol": "USDCAD",
      "strategy": "komjathy",
      "direction": "sell",
      "entry_time": "2025-11-17T07:22:23",
      "exit_time": "2025-11-17T12:47:37",
      "entry_price": 1.361,
      "exit_price": 1.3523,
      "sl_price": 1.36356,
      "tp_price": 1.3523,
      "lots": 0.39,
      "pnl_usd": 112.09,
      "pnl_r": 1.121,
      "exit_reason": "tp",
      "duration_bars": 65
    },
    {
      "id": 52,
      "symbol": "AUDUSD",
      "strategy": "momentum_pullback",
      "direction": "sell",
      "entry_time": "2025-11-18T00:09:27",
      "exit_time": "2025-11-19T17:43:57",
      "entry_price": 0.64564,
      "exit_price": 0.63696,
      "sl_price": 0.64914,
      "tp_price": 0.63696,
      "lots": 0.29,
      "pnl_usd": 109.24,
      "pnl_r": 1.092,
      "exit_reason": "tp",
      "duration_bars": 498
    },
    {
      "id": 91,
      "symbol": "GBPUSD",
      "strategy": "momentum_pullback",
      "direction": "sell",
      "entry_time": "2025-11-18T08:20:46",
      "exit_time": "2025-11-19T09:12:14",
      "entry_price": 1.26579,
      "exit_price": 1.26853,
      "sl_price": 1.26851,
      "tp_price": 1.25986,
      "lots": 0.37,
      "pnl_usd": -107.86,
      "pnl_r": -1.079,
      "exit_reason": "trailing",
      "duration_bars": 298
    },
    {
      "id": 60,
      "symbol": "XAUUSD",
      "strategy": "macd_stochastic",
      "direction": "buy",
      "entry_time": "2025-11-19T03:35:19",
      "exit_time": "2025-11-20T03:32:51",
      "entry_price": 2312.46819,
      "exit_price": 2390.88731,
      "sl_price": 2280.06093,
      "tp_price": 2390.88731,
      "lots": 0.31,
      "pnl_usd": 154.1,
      "pnl_r": 1.541,
      "exit_reason": "tp",
      "duration_bars": 287
    },
    {
      "id": 6,
      "symbol": "GBPUSD",
      "strategy": "macd_stochastic",
      "direction": "buy",
      "entry_time": "2025-11-19T11:51:16",
      "exit_time": "2025-11-21T02:11:56",
      "entry_price": 1.2654,
      "exit_price": 1.26299,
      "sl_price": 1.26292,
      "tp_price": 1.26922,
      "lots": 0.4,
      "pnl_usd": -81.06,
      "pnl_r": -0.811,
      "exit_reason": "sl",
      "duration_bars": 460
    },
    {
      "id": 50,
      "symbol": "EURUSD",
      "strategy": "komjathy",
      "direction": "sell",
      "entry_time": "2025-11-22T07:14:23",
      "exit_time": "2025-11-23T06:46:36",
      "entry_price": 1.08424,
      "exit_price": 1.07679,
      "sl_price": 1.08721,
      "tp_price": 1.07679,
      "lots": 0.34,
      "pnl_usd": 299.61,
      "pnl_r": 2.996,
      "exit_reason": "tp",
      "duration_bars": 282
    },
    {
      "id": 4,
      "symbol": "USDJPY",
      "strategy": "macd_stochastic",
      "direction": "sell",
      "entry_time": "2025-11-23T03:51:27",
      "exit_time": "2025-11-24T14:18:38",
      "entry_price": 148.46936,
      "exit_price": 147.28053,
      "sl_price": 148.80702,
      "tp_price": 147.28053,
      "lots": 0.33,
      "pnl_usd": 261.56,
      "pnl_r": 2.616,
      "exit_reason": "tp",
      "duration_bars": 413
    },
    {
      "id": 21,
      "symbol": "USDCHF",
      "strategy": "momentum_pullback",
      "direction": "buy",
      "entry_time": "2025-11-23T21:00:30",
      "exit_time": "2025-11-25T03:44:33",
      "entry_price": 0.90413,
      "exit_price": 0.91227,
      "sl_price": 0.90143,
      "tp_price": 0.91227,
      "lots": 0.37,
      "pnl_usd": 177.67,
      "pnl_r": 1.777,
      "exit_reason": "tp",
      "duration_bars": 368
    },
    {
      "id": 89,
      "symbol": "EURUSD",
      "strategy": "komjathy",
      "direction": "buy",
      "entry_time": "2025-11-24T02:14:02",
      "exit_time": "2025-11-24T19:44:34",
      "entry_price": 1.08519,
      "exit_price": 1.0893,
      "sl_price": 1.08348,
      "tp_price": 1.0893,
      "lots": 0.58,
      "pnl_usd": 108.25,
      "pnl_r": 1.083,
      "exit_reason": "tp",
      "duration_bars": 210
    },
    {
      "id": 109,
      "symbol": "GBPUSD",
      "strategy": "momentum_pullback",
      "direction": "buy",
      "entry_time": "2025-11-25T02:13:48",
      "exit_time": "2025-11-26T02:57:16",
      "entry_price": 1.26523,
      "exit_price": 1.27572,
      "sl_price": 1.26247,
      "tp_price": 1.27572,
      "lots": 0.36,
      "pnl_usd": 236.59,
      "pnl_r": 2.366,
      "exit_reason": "tp",
      "duration_bars": 296
    },
    {
      "id": 61,
      "symbol": "USDCAD",
      "strategy": "macd_stochastic",
      "direction": "sell",
      "entry_time": "2025-11-25T21:47:29",
      "exit_time": "2025-11-26T01:38:31",
      "entry_price": 1.35935,
      "exit_price": 1.36215,
      "sl_price": 1.36231,
      "tp_price": 1.35017,
      "lots": 0.34,
      "pnl_usd": -67.78,
      "pnl_r": -0.678,
      "exit_reason": "trailing",
      "duration_bars": 46
    },
    {
      "id": 92,
      "symbol": "EURJPY",
      "strategy": "komjathy",
      "direction": "buy",
      "entry_time": "2025-11-26T04:32:18",
      "exit_time": "2025-11-26T16:03:25",
      "entry_price": 161.19728,
      "exit_price": 162.0952,
      "sl_price": 160.85123,
      "tp_price": 162.0952,
      "lots": 0.32,
      "pnl_usd": 134.01,
      "pnl_r": 1.34,
      "exit_reason": "tp",
      "duration_bars": 138
    },
    {
      "id": 24,
      "symbol": "USDCAD",
      "strategy": "momentum_pullback",
      "direction": "sell",
      "entry_time": "2025-11-26T05:05:21",
      "exit_time": "2025-11-27T00:22:06",
      "entry_price": 1.35979,
      "exit_price": 1.36196,
      "sl_price": 1.36198,
      "tp_price": 1.3546,
      "lots": 0.46,
      "pnl_usd": -102.31,
      "pnl_r": -1.023,
      "exit_reason": "sl",
      "duration_bars": 231
    },
    {
      "id": 69,
      "symbol": "AUDUSD",
      "strategy": "macd_stochastic",
      "direction": "buy",
      "entry_time": "2025-11-27T06:55:09",
      "exit_time": "2025-11-28T18:22:20",
      "entry_price": 0.64449,
      "exit_price": 0.64252,
      "sl_price": 0.64244,
      "tp_price": 0.65107,
      "lots": 0.49,
      "pnl_usd": -61.36,
      "pnl_r": -0.614,
      "exit_reason": "sl",
      "duration_bars": 425
    },
    {
      "id": 70,
      "symbol": "XAUUSD",
      "strategy": "komjathy",
      "direction": "sell",
      "entry_time": "2025-11-27T20:59:16",
      "exit_time": "2025-11-28T08:24:41",
      "entry_price": 2325.53835,
      "exit_price": 2352.22854,
      "sl_price": 2351.87269,
      "tp_price": 2256.17514,
      "lots": 0.38,
      "pnl_usd": -55.41,
      "pnl_r": -0.554,
      "exit_reason": "sl",
      "duration_bars": 137
    },
    {
      "id": 45,
      "symbol": "GBPJPY",
      "strategy": "macd_stochastic",
      "direction": "sell",
      "entry_time": "2025-11-30T03:15:58",
      "exit_time": "2025-11-30T15:37:23",
      "entry_price": 188.65261,
      "exit_price": 188.89544,
      "sl_price": 188.88616,
      "tp_price": 188.00825,
      "lots": 0.48,
      "pnl_usd": -96.1,
      "pnl_r": -0.961,
      "exit_reason": "trailing",
      "duration_bars": 148
    },
    {
      "id": 51,
      "symbol": "EURJPY",
      "strategy": "momentum_pullback",
      "direction": "buy",
      "entry_time": "2025-11-30T19:22:00",
      "exit_time": "2025-12-02T06:08:24",
      "entry_price": 161.28513,
      "exit_price": 162.39119,
      "sl_price": 160.93483,
      "tp_price": 162.39119,
      "lots": 0.32,
      "pnl_usd": 157.6,
      "pnl_r": 1.576,
      "exit_reason": "tp",
      "duration_bars": 417
    },
    {
      "id": 108,
      "symbol": "AUDUSD",
      "strategy": "momentum_pullback",
      "direction": "sell",
      "entry_time": "2025-12-01T09:53:53",
      "exit_time": "2025-12-03T03:28:37",
      "entry_price": 0.64481,
      "exit_price": 0.64013,
      "sl_price": 0.64729,
      "tp_price": 0.64013,
      "lots": 0.4,
      "pnl_usd": 199.53,
      "pnl_r": 1.995,
      "exit_reason": "tp",
      "duration_bars": 498
    },
    {
      "id": 30,
      "symbol": "GBPJPY",
      "strategy": "komjathy",
      "direction": "buy",
      "entry_time": "2025-12-01T22:13:29",
      "exit_time": "2025-12-03T11:21:59",
      "entry_price": 188.70687,
      "exit_price": 189.02131,
      "sl_price": 188.52826,
      "tp_price": 189.02131,
      "lots": 0.62,
      "pnl_usd": 175.29,
      "pnl_r": 1.753,
      "exit_reason": "tp",
      "duration_bars": 445
    },
    {
      "id": 84,
      "symbol": "USDJPY",
      "strategy": "komjathy",
      "direction": "buy",
      "entry_time": "2025-12-03T02:50:44",
      "exit_time": "2025-12-04T11:12:32",
      "entry_price": 148.42015,
      "exit_price": 149.32231,
      "sl_price": 148.10614,
      "tp_price": 149.32231,
      "lots": 0.35,
      "pnl_usd": 131.46,
      "pnl_r": 1.315,
      "exit_reason": "tp",
      "duration_bars": 388
    },
    {
      "id": 86,
      "symbol": "EURGBP",
      "strategy": "komjathy",
      "direction": "sell",
      "entry_time": "2025-12-03T11:19:59",
      "exit_time": "2025-12-05T06:37:21",
      "entry_price": 0.85445,
      "exit_price": 0.84729,
      "sl_price": 0.85814,
      "tp_price": 0.84729,
      "lots": 0.27,
      "pnl_usd": 105.89,
      "pnl_r": 1.059,
      "exit_reason": "tp",
      "duration_bars": 519
    },
    {
      "id": 55,
      "symbol": "USDCHF",
      "strategy": "komjathy",
      "direction": "sell",
      "entry_time": "2025-12-04T17:22:28",
      "exit_time": "2025-12-05T09:42:22",
      "entry_price": 0.90424,
      "exit_price": 0.90627,
      "sl_price": 0.90639,
      "tp_price": 0.89653,
      "lots": 0.46,
      "pnl_usd": -107.98,
      "pnl_r": -1.08,
      "exit_reason": "sl",
      "duration_bars": 195
    },
    {
      "id": 78,
      "symbol": "EURUSD",
      "strategy": "macd_stochastic",
      "direction": "sell",
      "entry_time": "2025-12-08T04:50:34",
      "exit_time": "2025-12-09T12:40:51",
      "entry_price": 1.08539,
      "exit_price": 1.08916,
      "sl_price": 1.08924,
      "tp_price": 1.07001,
      "lots": 0.26,
      "pnl_usd": -72.64,
      "pnl_r": -0.726,
      "exit_reason": "sl",
      "duration_bars": 382
    },
    {
      "id": 112,
      "symbol": "AUDUSD",
      "strategy": "komjathy",
      "direction": "buy",
      "entry_time": "2025-12-09T08:34:29",
      "exit_time": "2025-12-09T10:35:29",
      "entry_price": 0.6446,
      "exit_price": 0.64167,
      "sl_price": 0.64186,
      "tp_price": 0.655,
      "lots": 0.37,
      "pnl_usd": -96.91,
      "pnl_r": -0.969,
      "exit_reason": "trailing",
      "duration_bars": 24
    },
    {
      "id": 7,
      "symbol": "USDCAD",
      "strategy": "momentum_pullback",
      "direction": "buy",
      "entry_time": "2025-12-10T05:25:39",
      "exit_time": "2025-12-11T08:26:30",
      "entry_price": 1.36059,
      "exit_price": 1.35841,
      "sl_price": 1.35861,
      "tp_price": 1.36366,
      "lots": 0.5,
      "pnl_usd": -84.18,
      "pnl_r": -0.842,
      "exit_reason": "sl",
      "duration_bars": 324
    },
    {
      "id": 107,
      "symbol": "USDCHF",
      "strategy": "momentum_pullback",
      "direction": "buy",
      "entry_time": "2025-12-10T18:30:16",
      "exit_time": "2025-12-12T08:04:07",
      "entry_price": 0.90562,
      "exit_price": 0.90322,
      "sl_price": 0.90318,
      "tp_price": 0.91376,
      "lots": 0.41,
      "pnl_usd": -104.29,
      "pnl_r": -1.043,
      "exit_reason": "sl",
      "duration_bars": 450
    },
    {
      "id": 23,
      "symbol": "USDCAD",
      "strategy": "momentum_pullback",
      "direction": "sell",
      "entry_time": "2025-12-11T16:03:01",
      "exit_time": "2025-12-13T14:17:04",
      "entry_price": 1.35931,
      "exit_price": 1.35375,
      "sl_price": 1.36085,
      "tp_price": 1.35375,
      "lots": 0.65,
      "pnl_usd": 189.42,
      "pnl_r": 1.894,
      "exit_reason": "tp",
      "duration_bars": 554
    },
    {
      "id": 8,
      "symbol": "AUDUSD",
      "strategy": "momentum_pullback",
      "direction": "sell",
      "entry_time": "2025-12-11T20:08:53",
      "exit_time": "2025-12-13T12:47:00",
      "entry_price": 0.64521,
      "exit_price": 0.63385,
      "sl_price": 0.64847,
      "tp_price": 0.63385,
      "lots": 0.31,
      "pnl_usd": 155.13,
      "pnl_r": 1.551,
      "exit_reason": "tp",
      "duration_bars": 487
    },
    {
      "id": 88,
      "symbol": "USDJPY",
      "strategy": "momentum_pullback",
      "direction": "buy",
      "entry_time": "2025-12-12T08:08:55",
      "exit_time": "2025-12-12T20:59:55",
      "entry_price": 148.51675,
      "exit_price": 148.22566,
      "sl_price": 148.21933,
      "tp_price": 149.56115,
      "lots": 0.37,
      "pnl_usd": -60.81,
      "pnl_r": -0.608,
      "exit_reason": "sl",
      "duration_bars": 154
    },
    {
      "id": 59,
      "symbol": "EURUSD",
      "strategy": "macd_stochastic",
      "direction": "buy",
      "entry_time": "2025-12-13T07:09:01",
      "exit_time": "2025-12-15T02:47:43",
      "entry_price": 1.08482,
      "exit_price": 1.08083,
      "sl_price": 1.08093,
      "tp_price": 1.09496,
      "lots": 0.26,
      "pnl_usd": -110.59,
      "pnl_r": -1.106,
      "exit_reason": "sl",
      "duration_bars": 523
    },
    {
      "id": 116,
      "symbol": "XAUUSD",
      "strategy": "komjathy",
      "direction": "sell",
      "entry_time": "2025-12-15T10:17:25",
      "exit_time": "2025-12-16T12:00:21",
      "entry_price": 2324.80954,
      "exit_price": 2237.39814,
      "sl_price": 2357.03121,
      "tp_price": 2237.39814,
      "lots": 0.31,
      "pnl_usd": 194.6,
      "pnl_r": 1.946,
      "exit_reason": "tp",
      "duration_bars": 308
    },
    {
      "id": 120,
      "symbol": "XAUUSD",
      "strategy": "komjathy",
      "direction": "buy",
      "entry_time": "2025-12-17T14:17:01",
      "exit_time": "2025-12-17T19:06:31",
      "entry_price": 2312.28516,
      "exit_price": 2280.00221,
      "sl_price": 2281.90531,
      "tp_price": 2413.45438,
      "lots": 0.33,
      "pnl_usd": -73.12,
      "pnl_r": -0.731,
      "exit_reason": "sl",
      "duration_bars": 57
    },
    {
      "id": 63,
      "symbol": "USDCAD",
      "strategy": "macd_stochastic",
      "direction": "sell",
      "entry_time": "2025-12-17T21:15:23",
      "exit_time": "2025-12-19T17:45:05",
      "entry_price": 1.36096,
      "exit_price": 1.3649,
      "sl_price": 1.36489,
      "tp_price": 1.34908,
      "lots": 0.25,
      "pnl_usd": -77.35,
      "pnl_r": -0.773,
      "exit_reason": "sl",
      "duration_bars": 533
    },
    {
      "id": 43,
      "symbol": "USDCHF",
      "strategy": "komjathy",
      "direction": "buy",
      "entry_time": "2025-12-20T13:11:02",
      "exit_time": "2025-12-21T09:15:38",
      "entry_price": 0.90494,
      "exit_price": 0.90113,
      "sl_price": 0.9012,
      "tp_price": 0.91763,
      "lots": 0.27,
      "pnl_usd": -80.72,
      "pnl_r": -0.807,
      "exit_reason": "trailing",
      "duration_bars": 240
    },
    {
      "id": 79,
      "symbol": "AUDUSD",
      "strategy": "komjathy",
      "direction": "sell",
      "entry_time": "2025-12-21T02:15:20",
      "exit_time": "2025-12-21T07:29:31",
      "entry_price": 0.64538,
      "exit_price": 0.63071,
      "sl_price": 0.6493,
      "tp_price": 0.63071,
      "lots": 0.25,
      "pnl_usd": 150.64,
      "pnl_r": 1.506,
      "exit_reason": "tp",
      "duration_bars": 62
    },
    {
      "id": 38,
      "symbol": "USDJPY",
      "strategy": "komjathy",
      "direction": "sell",
      "entry_time": "2025-12-21T20:18:57",
      "exit_time": "2025-12-22T19:08:35",
      "entry_price": 148.43902,
      "exit_price": 147.90348,
      "sl_price": 148.729,
      "tp_price": 147.90348,
      "lots": 0.38,
      "pnl_usd": 288.76,
      "pnl_r": 2.888,
      "exit_reason": "tp",
      "duration_bars": 273
    },
    {
      "id": 96,
      "symbol": "GBPUSD",
      "strategy": "komjathy",
      "direction": "buy",
      "entry_time": "2025-12-22T06:47:02",
      "exit_time": "2025-12-23T05:10:45",
      "entry_price": 1.26534,
      "exit_price": 1.26288,
      "sl_price": 1.26271,
      "tp_price": 1.27552,
      "lots": 0.38,
      "pnl_usd": -56.21,
      "pnl_r": -0.562,
      "exit_reason": "trailing",
      "duration_bars": 268
    },
    {
      "id": 64,
      "symbol": "USDCAD",
      "strategy": "momentum_pullback",
      "direction": "buy",
      "entry_time": "2025-12-22T14:55:45",
      "exit_time": "2025-12-22T17:03:52",
      "entry_price": 1.3608,
      "exit_price": 1.366,
      "sl_price": 1.35737,
      "tp_price": 1.366,
      "lots": 0.29,
      "pnl_usd": 256.66,
      "pnl_r": 2.567,
      "exit_reason": "tp",
      "duration_bars": 25
    },
    {
      "id": 29,
      "symbol": "AUDUSD",
      "strategy": "komjathy",
      "direction": "sell",
      "entry_time": "2025-12-23T19:14:12",
      "exit_time": "2025-12-25T01:06:18",
      "entry_price": 0.64548,
      "exit_price": 0.63326,
      "sl_price": 0.64881,
      "tp_price": 0.63326,
      "lots": 0.3,
      "pnl_usd": 298.43,
      "pnl_r": 2.984,
      "exit_reason": "tp",
      "duration_bars": 358
    },
    {
      "id": 117,
      "symbol": "AUDUSD",
      "strategy": "komjathy",
      "direction": "sell",
      "entry_time": "2025-12-24T14:30:53",
      "exit_time": "2025-12-26T08:51:57",
      "entry_price": 0.64519,
      "exit_price": 0.63114,
      "sl_price": 0.64906,
      "tp_price": 0.63114,
      "lots": 0.26,
      "pnl_usd": 149.36,
      "pnl_r": 1.494,
      "exit_reason": "tp",
      "duration_bars": 508
    },
    {
      "id": 32,
      "symbol": "GBPUSD",
      "strategy": "macd_stochastic",
      "direction": "sell",
      "entry_time": "2025-12-24T19:03:45",
      "exit_time": "2025-12-26T01:41:59",
      "entry_price": 1.26476,
      "exit_price": 1.25996,
      "sl_price": 1.26677,
      "tp_price": 1.25996,
      "lots": 0.5,
      "pnl_usd": 102.15,
      "pnl_r": 1.022,
      "exit_reason": "tp",
      "duration_bars": 367
    },
    {
      "id": 73,
      "symbol": "USDCHF",
      "strategy": "macd_stochastic",
      "direction": "buy",
      "entry_time": "2025-12-25T05:53:41",
      "exit_time": "2025-12-25T12:09:26",
      "entry_price": 0.90597,
      "exit_price": 0.91278,
      "sl_price": 0.90263,
      "tp_price": 0.91278,
      "lots": 0.3,
      "pnl_usd": 253.64,
      "pnl_r": 2.536,
      "exit_reason": "tp",
      "duration_bars": 75
    },
    {
      "id": 99,
      "symbol": "EURGBP",
      "strategy": "momentum_pullback",
      "direction": "buy",
      "entry_time": "2025-12-27T00:00:01",
      "exit_time": "2025-12-28T02:03:07",
      "entry_price": 0.85433,
      "exit_price": 0.86094,
      "sl_price": 0.8524,
      "tp_price": 0.86094,
      "lots": 0.52,
      "pnl_usd": 267.82,
      "pnl_r": 2.678,
      "exit_reason": "tp",
      "duration_bars": 312
    },
    {
      "id": 17,
      "symbol": "USDCAD",
      "strategy": "momentum_pullback",
      "direction": "buy",
      "entry_time": "2025-12-29T09:55:24",
      "exit_time": "2025-12-30T11:35:51",
      "entry_price": 1.36002,
      "exit_price": 1.35685,
      "sl_price": 1.35701,
      "tp_price": 1.37193,
      "lots": 0.33,
      "pnl_usd": -112.57,
      "pnl_r": -1.126,
      "exit_reason": "sl",
      "duration_bars": 308
    },
    {
      "id": 48,
      "symbol": "AUDUSD",
      "strategy": "komjathy",
      "direction": "buy",
      "entry_time": "2025-12-29T14:42:41",
      "exit_time": "2025-12-29T17:39:32",
      "entry_price": 0.64438,
      "exit_price": 0.64704,
      "sl_price": 0.64286,
      "tp_price": 0.64704,
      "lots": 0.66,
      "pnl_usd": 130.64,
      "pnl_r": 1.306,
      "exit_reason": "tp",
      "duration_bars": 35
    },
    {
      "id": 33,
      "symbol": "EURJPY",
      "strategy": "momentum_pullback",
      "direction": "sell",
      "entry_time": "2026-01-01T16:39:53",
      "exit_time": "2026-01-03T06:42:33",
      "entry_price": 161.14708,
      "exit_price": 159.87195,
      "sl_price": 161.51159,
      "tp_price": 159.87195,
      "lots": 0.3,
      "pnl_usd": 173.76,
      "pnl_r": 1.738,
      "exit_reason": "tp",
      "duration_bars": 456
    },
    {
      "id": 15,
      "symbol": "USDJPY",
      "strategy": "macd_stochastic",
      "direction": "buy",
      "entry_time": "2026-01-02T09:09:41",
      "exit_time": "2026-01-04T02:17:31",
      "entry_price": 148.48257,
      "exit_price": 148.22024,
      "sl_price": 148.22978,
      "tp_price": 148.95621,
      "lots": 0.44,
      "pnl_usd": -116.45,
      "pnl_r": -1.165,
      "exit_reason": "sl",
      "duration_bars": 493
    },
    {
      "id": 42,
      "symbol": "USDJPY",
      "strategy": "macd_stochastic",
      "direction": "sell",
      "entry_time": "2026-01-04T04:08:07",
      "exit_time": "2026-01-05T13:13:32",
      "entry_price": 148.47885,
      "exit_price": 147.72421,
      "sl_price": 148.70952,
      "tp_price": 147.72421,
      "lots": 0.48,
      "pnl_usd": 209.07,
      "pnl_r": 2.091,
      "exit_reason": "tp",
      "duration_bars": 397
    },
    {
      "id": 102,
      "symbol": "AUDUSD",
      "strategy": "komjathy",
      "direction": "buy",
      "entry_time": "2026-01-04T16:00:10",
      "exit_time": "2026-01-05T02:59:25",
      "entry_price": 0.64457,
      "exit_price": 0.64279,
      "sl_price": 0.6429,
      "tp_price": 0.64953,
      "lots": 0.6,
      "pnl_usd": -69.21,
      "pnl_r": -0.692,
      "exit_reason": "sl",
      "duration_bars": 131
    },
    {
      "id": 47,
      "symbol": "GBPUSD",
      "strategy": "macd_stochastic",
      "direction": "buy",
      "entry_time": "2026-01-05T16:01:52",
      "exit_time": "2026-01-05T23:49:16",
      "entry_price": 1.26475,
      "exit_price": 1.26264,
      "sl_price": 1.26245,
      "tp_price": 1.27203,
      "lots": 0.43,
      "pnl_usd": -73.37,
      "pnl_r": -0.734,
      "exit_reason": "trailing",
      "duration_bars": 93
    },
    {
      "id": 74,
      "symbol": "USDCHF",
      "strategy": "komjathy",
      "direction": "sell",
      "entry_time": "2026-01-07T00:22:52",
      "exit_time": "2026-01-08T06:44:10",
      "entry_price": 0.90496,
      "exit_price": 0.90897,
      "sl_price": 0.90883,
      "tp_price": 0.89615,
      "lots": 0.26,
      "pnl_usd": -87.01,
      "pnl_r": -0.87,
      "exit_reason": "sl",
      "duration_bars": 364
    },
    {
      "id": 11,
      "symbol": "EURGBP",
      "strategy": "komjathy",
      "direction": "sell",
      "entry_time": "2026-01-07T01:00:48",
      "exit_time": "2026-01-08T18:59:32",
      "entry_price": 0.8559,
      "exit_price": 0.8588,
      "sl_price": 0.85862,
      "tp_price": 0.84558,
      "lots": 0.37,
      "pnl_usd": -71.03,
      "pnl_r": -0.71,
      "exit_reason": "sl",
      "duration_bars": 503
    },
    {
      "id": 76,
      "symbol": "EURGBP",
      "strategy": "momentum_pullback",
      "direction": "buy",
      "entry_time": "2026-01-08T04:28:19",
      "exit_time": "2026-01-09T14:20:47",
      "entry_price": 0.85578,
      "exit_price": 0.85357,
      "sl_price": 0.85369,
      "tp_price": 0.86382,
      "lots": 0.48,
      "pnl_usd": -73.51,
      "pnl_r": -0.735,
      "exit_reason": "trailing",
      "duration_bars": 406
    },
    {
      "id": 3,
      "symbol": "USDCAD",
      "strategy": "komjathy",
      "direction": "buy",
      "entry_time": "2026-01-08T09:20:08",
      "exit_time": "2026-01-08T22:45:21",
      "entry_price": 1.36062,
      "exit_price": 1.36751,
      "sl_price": 1.3572,
      "tp_price": 1.36751,
      "lots": 0.29,
      "pnl_usd": 121.37,
      "pnl_r": 1.214,
      "exit_reason": "tp",
      "duration_bars": 161
    },
    {
      "id": 94,
      "symbol": "GBPUSD",
      "strategy": "momentum_pullback",
      "direction": "buy",
      "entry_time": "2026-01-12T15:54:25",
      "exit_time": "2026-01-13T00:50:47",
      "entry_price": 1.26403,
      "exit_price": 1.26046,
      "sl_price": 1.26055,
      "tp_price": 1.27091,
      "lots": 0.29,
      "pnl_usd": -87.55,
      "pnl_r": -0.875,
      "exit_reason": "sl",
      "duration_bars": 107
    },
    {
      "id": 16,
      "symbol": "EURJPY",
      "strategy": "macd_stochastic",
      "direction": "buy",
      "entry_time": "2026-01-14T12:12:56",
      "exit_time": "2026-01-14T15:15:49",
      "entry_price": 161.28336,
      "exit_price": 161.93182,
      "sl_price": 161.10238,
      "tp_price": 161.93182,
      "lots": 0.61,
      "pnl_usd": 176.61,
      "pnl_r": 1.766,
      "exit_reason": "tp",
      "duration_bars": 36
    },
    {
      "id": 40,
      "symbol": "EURJPY",
      "strategy": "momentum_pullback",
      "direction": "buy",
      "entry_time": "2026-01-16T02:37:09",
      "exit_time": "2026-01-17T08:26:04",
      "entry_price": 161.18029,
      "exit_price": 160.97972,
      "sl_price": 160.97557,
      "tp_price": 161.82966,
      "lots": 0.54,
      "pnl_usd": -53.29,
      "pnl_r": -0.533,
      "exit_reason": "sl",
      "duration_bars": 357
    },
    {
      "id": 67,
      "symbol": "EURJPY",
      "strategy": "macd_stochastic",
      "direction": "buy",
      "entry_time": "2026-01-18T16:24:55",
      "exit_time": "2026-01-20T10:57:58",
      "entry_price": 161.14151,
      "exit_price": 161.54853,
      "sl_price": 160.876,
      "tp_price": 161.54853,
      "lots": 0.42,
      "pnl_usd": 103.65,
      "pnl_r": 1.037,
      "exit_reason": "tp",
      "duration_bars": 510
    },
    {
      "id": 5,
      "symbol": "GBPUSD",
      "strategy": "macd_stochastic",
      "direction": "buy",
      "entry_time": "2026-01-19T10:18:54",
      "exit_time": "2026-01-20T23:32:50",
      "entry_price": 1.26557,
      "exit_price": 1.26331,
      "sl_price": 1.26312,
      "tp_price": 1.26934,
      "lots": 0.41,
      "pnl_usd": -61.9,
      "pnl_r": -0.619,
      "exit_reason": "sl",
      "duration_bars": 446
    },
    {
      "id": 31,
      "symbol": "GBPJPY",
      "strategy": "macd_stochastic",
      "direction": "sell",
      "entry_time": "2026-01-19T15:39:49",
      "exit_time": "2026-01-21T03:41:27",
      "entry_price": 188.60113,
      "exit_price": 188.17574,
      "sl_price": 188.86129,
      "tp_price": 188.17574,
      "lots": 0.43,
      "pnl_usd": 297.22,
      "pnl_r": 2.972,
      "exit_reason": "tp",
      "duration_bars": 432
    },
    {
      "id": 26,
      "symbol": "AUDUSD",
      "strategy": "komjathy",
      "direction": "sell",
      "entry_time": "2026-01-20T19:54:00",
      "exit_time": "2026-01-22T16:47:49",
      "entry_price": 0.64501,
      "exit_price": 0.6378,
      "sl_price": 0.64884,
      "tp_price": 0.6378,
      "lots": 0.26,
      "pnl_usd": 241.41,
      "pnl_r": 2.414,
      "exit_reason": "tp",
      "duration_bars": 538
    },
    {
      "id": 44,
      "symbol": "EURUSD",
      "strategy": "macd_stochastic",
      "direction": "sell",
      "entry_time": "2026-01-21T00:32:57",
      "exit_time": "2026-01-22T15:00:53",
      "entry_price": 1.08473,
      "exit_price": 1.08807,
      "sl_price": 1.08822,
      "tp_price": 1.07833,
      "lots": 0.29,
      "pnl_usd": -77.44,
      "pnl_r": -0.774,
      "exit_reason": "trailing",
      "duration_bars": 461
    },
    {
      "id": 25,
      "symbol": "XAUUSD",
      "strategy": "komjathy",
      "direction": "sell",
      "entry_time": "2026-01-22T14:18:16",
      "exit_time": "2026-01-23T14:31:56",
      "entry_price": 2311.55479,
      "exit_price": 2242.80018,
      "sl_price": 2330.82985,
      "tp_price": 2242.80018,
      "lots": 0.52,
      "pnl_usd": 227.31,
      "pnl_r": 2.273,
      "exit_reason": "tp",
      "duration_bars": 290
    },
    {
      "id": 119,
      "symbol": "AUDUSD",
      "strategy": "momentum_pullback",
      "direction": "buy",
      "entry_time": "2026-01-23T11:44:27",
      "exit_time": "2026-01-24T03:06:54",
      "entry_price": 0.64478,
      "exit_price": 0.64118,
      "sl_price": 0.64104,
      "tp_price": 0.6556,
      "lots": 0.27,
      "pnl_usd": -73.81,
      "pnl_r": -0.738,
      "exit_reason": "trailing",
      "duration_bars": 184
    },
    {
      "id": 41,
      "symbol": "GBPUSD",
      "strategy": "komjathy",
      "direction": "sell",
      "entry_time": "2026-01-24T22:42:20",
      "exit_time": "2026-01-25T07:41:13",
      "entry_price": 1.26439,
      "exit_price": 1.26739,
      "sl_price": 1.26747,
      "tp_price": 1.2537,
      "lots": 0.32,
      "pnl_usd": -95.49,
      "pnl_r": -0.955,
      "exit_reason": "trailing",
      "duration_bars": 107
    },
    {
      "id": 71,
      "symbol": "GBPJPY",
      "strategy": "momentum_pullback",
      "direction": "sell",
      "entry_time": "2026-01-25T13:10:34",
      "exit_time": "2026-01-26T09:22:36",
      "entry_price": 188.70537,
      "exit_price": 188.90664,
      "sl_price": 188.89185,
      "tp_price": 188.34553,
      "lots": 0.6,
      "pnl_usd": -85.93,
      "pnl_r": -0.859,
      "exit_reason": "trailing",
      "duration_bars": 242
    },
    {
      "id": 20,
      "symbol": "EURGBP",
      "strategy": "macd_stochastic",
      "direction": "sell",
      "entry_time": "2026-01-28T04:46:22",
      "exit_time": "2026-01-29T01:41:49",
      "entry_price": 0.85598,
      "exit_price": 0.85797,
      "sl_price": 0.85783,
      "tp_price": 0.84862,
      "lots": 0.54,
      "pnl_usd": -102.57,
      "pnl_r": -1.026,
      "exit_reason": "sl",
      "duration_bars": 251
    },
    {
      "id": 13,
      "symbol": "XAUUSD",
      "strategy": "momentum_pullback",
      "direction": "buy",
      "entry_time": "2026-01-29T04:22:11",
      "exit_time": "2026-01-30T13:35:58",
      "entry_price": 2316.55405,
      "exit_price": 2366.32698,
      "sl_price": 2289.87295,
      "tp_price": 2366.32698,
      "lots": 0.37,
      "pnl_usd": 213.63,
      "pnl_r": 2.136,
      "exit_reason": "tp",
      "duration_bars": 398
    },
    {
      "id": 90,
      "symbol": "EURUSD",
      "strategy": "momentum_pullback",
      "direction": "buy",
      "entry_time": "2026-01-29T10:28:13",
      "exit_time": "2026-01-31T08:25:22",
      "entry_price": 1.08448,
      "exit_price": 1.09195,
      "sl_price": 1.0825,
      "tp_price": 1.09195,
      "lots": 0.5,
      "pnl_usd": 123.88,
      "pnl_r": 1.239,
      "exit_reason": "tp",
      "duration_bars": 551
    },
    {
      "id": 81,
      "symbol": "EURUSD",
      "strategy": "komjathy",
      "direction": "buy",
      "entry_time": "2026-01-30T01:45:28",
      "exit_time": "2026-01-31T08:22:17",
      "entry_price": 1.08467,
      "exit_price": 1.08103,
      "sl_price": 1.08103,
      "tp_price": 1.09057,
      "lots": 0.27,
      "pnl_usd": -78.59,
      "pnl_r": -0.786,
      "exit_reason": "trailing",
      "duration_bars": 367
    },
    {
      "id": 113,
      "symbol": "USDCHF",
      "strategy": "momentum_pullback",
      "direction": "sell",
      "entry_time": "2026-01-30T19:01:48",
      "exit_time": "2026-02-01T03:55:07",
      "entry_price": 0.9056,
      "exit_price": 0.90865,
      "sl_price": 0.90868,
      "tp_price": 0.89611,
      "lots": 0.33,
      "pnl_usd": -87.42,
      "pnl_r": -0.874,
      "exit_reason": "sl",
      "duration_bars": 394
    },
    {
      "id": 39,
      "symbol": "USDJPY",
      "strategy": "macd_stochastic",
      "direction": "sell",
      "entry_time": "2026-01-30T19:22:12",
      "exit_time": "2026-02-01T18:28:22",
      "entry_price": 148.53709,
      "exit_price": 147.11131,
      "sl_price": 148.92285,
      "tp_price": 147.11131,
      "lots": 0.29,
      "pnl_usd": 266.86,
      "pnl_r": 2.669,
      "exit_reason": "tp",
      "duration_bars": 565
    },
    {
      "id": 95,
      "symbol": "USDCAD",
      "strategy": "komjathy",
      "direction": "buy",
      "entry_time": "2026-02-02T14:34:30",
      "exit_time": "2026-02-03T07:11:36",
      "entry_price": 1.36076,
      "exit_price": 1.35863,
      "sl_price": 1.35855,
      "tp_price": 1.36609,
      "lots": 0.45,
      "pnl_usd": -94.1,
      "pnl_r": -0.941,
      "exit_reason": "trailing",
      "duration_bars": 199
    },
    {
      "id": 14,
      "symbol": "GBPUSD",
      "strategy": "komjathy",
      "direction": "sell",
      "entry_time": "2026-02-03T07:45:25",
      "exit_time": "2026-02-03T16:50:30",
      "entry_price": 1.26401,
      "exit_price": 1.25803,
      "sl_price": 1.26799,
      "tp_price": 1.25803,
      "lots": 0.25,
      "pnl_usd": 226.54,
      "pnl_r": 2.265,
      "exit_reason": "tp",
      "duration_bars": 109
    },
    {
      "id": 49,
      "symbol": "GBPUSD",
      "strategy": "komjathy",
      "direction": "buy",
      "entry_time": "2026-02-07T00:14:00",
      "exit_time": "2026-02-07T21:14:35",
      "entry_price": 1.26549,
      "exit_price": 1.2629,
      "sl_price": 1.26303,
      "tp_price": 1.27182,
      "lots": 0.41,
      "pnl_usd": -53.4,
      "pnl_r": -0.534,
      "exit_reason": "sl",
      "duration_bars": 252
    },
    {
      "id": 9,
      "symbol": "EURJPY",
      "strategy": "komjathy",
      "direction": "buy",
      "entry_time": "2026-02-08T05:17:50",
      "exit_time": "2026-02-08T11:25:29",
      "entry_price": 161.27478,
      "exit_price": 162.05578,
      "sl_price": 160.91786,
      "tp_price": 162.05578,
      "lots": 0.31,
      "pnl_usd": 276.46,
      "pnl_r": 2.765,
      "exit_reason": "tp",
      "duration_bars": 73
    },
    {
      "id": 100,
      "symbol": "EURGBP",
      "strategy": "komjathy",
      "direction": "buy",
      "entry_time": "2026-02-09T17:25:10",
      "exit_time": "2026-02-11T11:08:14",
      "entry_price": 0.8551,
      "exit_price": 0.85165,
      "sl_price": 0.85178,
      "tp_price": 0.86152,
      "lots": 0.3,
      "pnl_usd": -82.86,
      "pnl_r": -0.829,
      "exit_reason": "trailing",
      "duration_bars": 500
    },
    {
      "id": 57,
      "symbol": "USDJPY",
      "strategy": "macd_stochastic",
      "direction": "buy",
      "entry_time": "2026-02-11T11:07:19",
      "exit_time": "2026-02-12T09:14:28",
      "entry_price": 148.50875,
      "exit_price": 149.08225,
      "sl_price": 148.30405,
      "tp_price": 149.08225,
      "lots": 0.54,
      "pnl_usd": 298.99,
      "pnl_r": 2.99,
      "exit_reason": "tp",
      "duration_bars": 265
    },
    {
      "id": 114,
      "symbol": "EURUSD",
      "strategy": "macd_stochastic",
      "direction": "sell",
      "entry_time": "2026-02-11T23:28:14",
      "exit_time": "2026-02-12T18:51:31",
      "entry_price": 1.08565,
      "exit_price": 1.08959,
      "sl_price": 1.08961,
      "tp_price": 1.07906,
      "lots": 0.25,
      "pnl_usd": -107.89,
      "pnl_r": -1.079,
      "exit_reason": "sl",
      "duration_bars": 232
    },
    {
      "id": 68,
      "symbol": "GBPUSD",
      "strategy": "macd_stochastic",
      "direction": "buy",
      "entry_time": "2026-02-13T20:48:12",
      "exit_time": "2026-02-14T10:00:13",
      "entry_price": 1.26533,
      "exit_price": 1.26359,
      "sl_price": 1.26356,
      "tp_price": 1.27041,
      "lots": 0.57,
      "pnl_usd": -107.06,
      "pnl_r": -1.071,
      "exit_reason": "trailing",
      "duration_bars": 158
    },
    {
      "id": 103,
      "symbol": "GBPJPY",
      "strategy": "komjathy",
      "direction": "buy",
      "entry_time": "2026-02-18T10:02:12",
      "exit_time": "2026-02-20T00:02:26",
      "entry_price": 188.68568,
      "exit_price": 188.48288,
      "sl_price": 188.4973,
      "tp_price": 189.29627,
      "lots": 0.59,
      "pnl_usd": -94.57,
      "pnl_r": -0.946,
      "exit_reason": "sl",
      "duration_bars": 456
    },
    {
      "id": 110,
      "symbol": "AUDUSD",
      "strategy": "macd_stochastic",
      "direction": "buy",
      "entry_time": "2026-02-19T03:13:33",
      "exit_time": "2026-02-20T16:59:34",
      "entry_price": 0.64559,
      "exit_price": 0.64262,
      "sl_price": 0.6428,
      "tp_price": 0.65453,
      "lots": 0.36,
      "pnl_usd": -53.48,
      "pnl_r": -0.535,
      "exit_reason": "sl",
      "duration_bars": 453
    },
    {
      "id": 118,
      "symbol": "EURUSD",
      "strategy": "macd_stochastic",
      "direction": "sell",
      "entry_time": "2026-02-20T12:23:40",
      "exit_time": "2026-02-21T14:14:41",
      "entry_price": 1.08407,
      "exit_price": 1.08756,
      "sl_price": 1.08763,
      "tp_price": 1.0773,
      "lots": 0.28,
      "pnl_usd": -88.79,
      "pnl_r": -0.888,
      "exit_reason": "sl",
      "duration_bars": 310
    },
    {
      "id": 18,
      "symbol": "EURUSD",
      "strategy": "komjathy",
      "direction": "sell",
      "entry_time": "2026-02-20T14:49:35",
      "exit_time": "2026-02-21T08:22:03",
      "entry_price": 1.085,
      "exit_price": 1.08674,
      "sl_price": 1.08674,
      "tp_price": 1.08218,
      "lots": 0.58,
      "pnl_usd": -100.19,
      "pnl_r": -1.002,
      "exit_reason": "sl",
      "duration_bars": 210
    },
    {
      "id": 62,
      "symbol": "EURJPY",
      "strategy": "komjathy",
      "direction": "sell",
      "entry_time": "2026-02-20T21:39:33",
      "exit_time": "2026-02-21T10:31:26",
      "entry_price": 161.1204,
      "exit_price": 161.30111,
      "sl_price": 161.30676,
      "tp_price": 160.64242,
      "lots": 0.6,
      "pnl_usd": -68.99,
      "pnl_r": -0.69,
      "exit_reason": "trailing",
      "duration_bars": 154
    },
    {
      "id": 58,
      "symbol": "EURUSD",
      "strategy": "komjathy",
      "direction": "buy",
      "entry_time": "2026-02-25T16:28:32",
      "exit_time": "2026-02-26T10:38:21",
      "entry_price": 1.08591,
      "exit_price": 1.08357,
      "sl_price": 1.08344,
      "tp_price": 1.09482,
      "lots": 0.4,
      "pnl_usd": -110.77,
      "pnl_r": -1.108,
      "exit_reason": "sl",
      "duration_bars": 217
    },
    {
      "id": 37,
      "symbol": "EURJPY",
      "strategy": "komjathy",
      "direction": "sell",
      "entry_time": "2026-02-26T06:41:10",
      "exit_time": "2026-02-27T06:35:48",
      "entry_price": 161.10718,
      "exit_price": 160.0115,
      "sl_price": 161.39242,
      "tp_price": 160.0115,
      "lots": 0.39,
      "pnl_usd": 251.07,
      "pnl_r": 2.511,
      "exit_reason": "tp",
      "duration_bars": 286
    },
    {
      "id": 93,
      "symbol": "GBPJPY",
      "strategy": "momentum_pullback",
      "direction": "buy",
      "entry_time": "2026-02-26T10:27:33",
      "exit_time": "2026-02-26T13:54:19",
      "entry_price": 188.72659,
      "exit_price": 189.26752,
      "sl_price": 188.47841,
      "tp_price": 189.26752,
      "lots": 0.45,
      "pnl_usd": 166.83,
      "pnl_r": 1.668,
      "exit_reason": "tp",
      "duration_bars": 41
    },
    {
      "id": 36,
      "symbol": "EURGBP",
      "strategy": "komjathy",
      "direction": "buy",
      "entry_time": "2026-02-26T17:08:12",
      "exit_time": "2026-02-27T08:08:41",
      "entry_price": 0.85597,
      "exit_price": 0.8613,
      "sl_price": 0.8531,
      "tp_price": 0.8613,
      "lots": 0.35,
      "pnl_usd": 154.55,
      "pnl_r": 1.545,
      "exit_reason": "tp",
      "duration_bars": 180
    },
    {
      "id": 82,
      "symbol": "USDJPY",
      "strategy": "komjathy",
      "direction": "sell",
      "entry_time": "2026-02-27T05:37:24",
      "exit_time": "2026-02-28T15:28:46",
      "entry_price": 148.47601,
      "exit_price": 147.34582,
      "sl_price": 148.79003,
      "tp_price": 147.34582,
      "lots": 0.35,
      "pnl_usd": 175.03,
      "pnl_r": 1.75,
      "exit_reason": "tp",
      "duration_bars": 406
    },
    {
      "id": 83,
      "symbol": "USDJPY",
      "strategy": "momentum_pullback",
      "direction": "sell",
      "entry_time": "2026-02-28T19:08:31",
      "exit_time": "2026-02-28T21:57:37",
      "entry_price": 148.57492,
      "exit_price": 147.03815,
      "sl_price": 148.97277,
      "tp_price": 147.03815,
      "lots": 0.28,
      "pnl_usd": 161.93,
      "pnl_r": 1.619,
      "exit_reason": "tp",
      "duration_bars": 33
    },
    {
      "id": 77,
      "symbol": "XAUUSD",
      "strategy": "momentum_pullback",
      "direction": "buy",
      "entry_time": "2026-02-28T19:11:33",
      "exit_time": "2026-03-01T03:23:27",
      "entry_price": 2329.12583,
      "exit_price": 2312.2946,
      "sl_price": 2313.90617,
      "tp_price": 2367.46894,
      "lots": 0.66,
      "pnl_usd": -93.96,
      "pnl_r": -0.94,
      "exit_reason": "sl",
      "duration_bars": 98
    },
    {
      "id": 19,
      "symbol": "USDCAD",
      "strategy": "macd_stochastic",
      "direction": "buy",
      "entry_time": "2026-03-01T12:10:47",
      "exit_time": "2026-03-02T10:35:40",
      "entry_price": 1.36077,
      "exit_price": 1.35938,
      "sl_price": 1.35924,
      "tp_price": 1.36421,
      "lots": 0.65,
      "pnl_usd": -85.87,
      "pnl_r": -0.859,
      "exit_reason": "trailing",
      "duration_bars": 268
    },
    {
      "id": 10,
      "symbol": "XAUUSD",
      "strategy": "momentum_pullback",
      "direction": "sell",
      "entry_time": "2026-03-01T13:18:02",
      "exit_time": "2026-03-01T19:47:02",
      "entry_price": 2311.99575,
      "exit_price": 2340.57332,
      "sl_price": 2341.58828,
      "tp_price": 2220.92012,
      "lots": 0.34,
      "pnl_usd": -71.58,
      "pnl_r": -0.716,
      "exit_reason": "sl",
      "duration_bars": 77
    },
    {
      "id": 1,
      "symbol": "EURJPY",
      "strategy": "macd_stochastic",
      "direction": "buy",
      "entry_time": "2026-03-02T07:05:52",
      "exit_time": "2026-03-04T02:53:31",
      "entry_price": 161.14086,
      "exit_price": 162.48621,
      "sl_price": 160.78445,
      "tp_price": 162.48621,
      "lots": 0.31,
      "pnl_usd": 252.9,
      "pnl_r": 2.529,
      "exit_reason": "tp",
      "duration_bars": 525
    },
    {
      "id": 2,
      "symbol": "EURUSD",
      "strategy": "komjathy",
      "direction": "buy",
      "entry_time": "2026-03-03T23:40:31",
      "exit_time": "2026-03-04T22:28:04",
      "entry_price": 1.08595,
      "exit_price": 1.08347,
      "sl_price": 1.08339,
      "tp_price": 1.09425,
      "lots": 0.39,
      "pnl_usd": -93.79,
      "pnl_r": -0.938,
      "exit_reason": "sl",
      "duration_bars": 273
    },
    {
      "id": 66,
      "symbol": "GBPUSD",
      "strategy": "macd_stochastic",
      "direction": "sell",
      "entry_time": "2026-03-05T13:47:10",
      "exit_time": "2026-03-06T11:37:51",
      "entry_price": 1.26523,
      "exit_price": 1.26785,
      "sl_price": 1.26783,
      "tp_price": 1.26037,
      "lots": 0.39,
      "pnl_usd": -60.21,
      "pnl_r": -0.602,
      "exit_reason": "sl",
      "duration_bars": 262
    },
    {
      "id": 80,
      "symbol": "GBPJPY",
      "strategy": "momentum_pullback",
      "direction": "buy",
      "entry_time": "2026-03-06T19:04:31",
      "exit_time": "2026-03-08T16:09:49",
      "entry_price": 188.78717,
      "exit_price": 188.58041,
      "sl_price": 188.56623,
      "tp_price": 189.50536,
      "lots": 0.5,
      "pnl_usd": -51.72,
      "pnl_r": -0.517,
      "exit_reason": "trailing",
      "duration_bars": 541
    },
    {
      "id": 28,
      "symbol": "EURUSD",
      "strategy": "komjathy",
      "direction": "buy",
      "entry_time": "2026-03-07T00:44:44",
      "exit_time": "2026-03-08T06:33:03",
      "entry_price": 1.08412,
      "exit_price": 1.08901,
      "sl_price": 1.08257,
      "tp_price": 1.08901,
      "lots": 0.64,
      "pnl_usd": 295.66,
      "pnl_r": 2.957,
      "exit_reason": "tp",
      "duration_bars": 357
    },
    {
      "id": 72,
      "symbol": "GBPJPY",
      "strategy": "macd_stochastic",
      "direction": "buy",
      "entry_time": "2026-03-08T05:49:10",
      "exit_time": "2026-03-09T18:45:52",
      "entry_price": 188.71544,
      "exit_price": 188.38999,
      "sl_price": 188.393,
      "tp_price": 189.82394,
      "lots": 0.34,
      "pnl_usd": -80.87,
      "pnl_r": -0.809,
      "exit_reason": "sl",
      "duration_bars": 443
    },
    {
      "id": 46,
      "symbol": "EURUSD",
      "strategy": "macd_stochastic",
      "direction": "sell",
      "entry_time": "2026-03-08T18:52:10",
      "exit_time": "2026-03-09T11:04:05",
      "entry_price": 1.08535,
      "exit_price": 1.07318,
      "sl_price": 1.08866,
      "tp_price": 1.07318,
      "lots": 0.3,
      "pnl_usd": 221.85,
      "pnl_r": 2.218,
      "exit_reason": "tp",
      "duration_bars": 194
    },
    {
      "id": 106,
      "symbol": "EURJPY",
      "strategy": "komjathy",
      "direction": "buy",
      "entry_time": "2026-03-10T03:44:23",
      "exit_time": "2026-03-11T16:18:41",
      "entry_price": 161.25996,
      "exit_price": 161.88791,
      "sl_price": 161.02887,
      "tp_price": 161.88791,
      "lots": 0.48,
      "pnl_usd": 261.9,
      "pnl_r": 2.619,
      "exit_reason": "tp",
      "duration_bars": 438
    },
    {
      "id": 101,
      "symbol": "GBPUSD",
      "strategy": "momentum_pullback",
      "direction": "sell",
      "entry_time": "2026-03-10T04:33:10",
      "exit_time": "2026-03-10T19:46:19",
      "entry_price": 1.26443,
      "exit_price": 1.25317,
      "sl_price": 1.26744,
      "tp_price": 1.25317,
      "lots": 0.33,
      "pnl_usd": 129.62,
      "pnl_r": 1.296,
      "exit_reason": "tp",
      "duration_bars": 182
    },
    {
      "id": 115,
      "symbol": "GBPUSD",
      "strategy": "komjathy",
      "direction": "sell",
      "entry_time": "2026-03-10T07:57:30",
      "exit_time": "2026-03-11T18:50:40",
      "entry_price": 1.264,
      "exit_price": 1.24986,
      "sl_price": 1.26757,
      "tp_price": 1.24986,
      "lots": 0.28,
      "pnl_usd": 297.2,
      "pnl_r": 2.972,
      "exit_reason": "tp",
      "duration_bars": 418
    },
    {
      "id": 53,
      "symbol": "USDCAD",
      "strategy": "komjathy",
      "direction": "buy",
      "entry_time": "2026-03-11T03:28:48",
      "exit_time": "2026-03-12T05:45:33",
      "entry_price": 1.3608,
      "exit_price": 1.36445,
      "sl_price": 1.3591,
      "tp_price": 1.36445,
      "lots": 0.59,
      "pnl_usd": 101.66,
      "pnl_r": 1.017,
      "exit_reason": "tp",
      "duration_bars": 315
    },
    {
      "id": 54,
      "symbol": "USDCAD",
      "strategy": "macd_stochastic",
      "direction": "sell",
      "entry_time": "2026-03-11T04:45:18",
      "exit_time": "2026-03-12T03:36:13",
      "entry_price": 1.36014,
      "exit_price": 1.35164,
      "sl_price": 1.36364,
      "tp_price": 1.35164,
      "lots": 0.29,
      "pnl_usd": 184.1,
      "pnl_r": 1.841,
      "exit_reason": "tp",
      "duration_bars": 274
    }
  ]
}